Workbook
Name aa: #REF!
Name ABDERA_: #REF!
Name ACABAMENTO_: #REF!
Name ACACIA_: #REF!
Name ACCOR_: #REF!
Name ADANA_: #REF!
Name AF_general: #REF!
Name AFTONE_: #REF!
Name AGHATA_: #REF!
Name ALAMO_: #REF!
Name ÁLAVA_: #REF!
Name ALINA_: #REF!
Name ALLADRO_: #REF!
Name ALLEGRO_: #REF!
Name ALLURE_: #REF!
Name ALMADA_: #REF!
Name ALMOFADA_: #REF!
Name AMALFI_: #REF!
Name AMAZONAS_: #REF!
Name AMELIA_: #REF!
Name ANCONA_: #REF!
Name ANDRIA_: #REF!
Name ANDROS_: #REF!
Name ANTARES_: #REF!
Name ARAGUAIA_: #REF!
Name ARAMIS_: #REF!
Name AREZZO_: #REF!
Name ARGOS_: #REF!
Name ARMANY_: #REF!
Name ARMENIA_: #REF!
Name ARROYOS_: #REF!
Name ARTTIS_: #REF!
Name ARTTIS_CAMA_: #REF!
Name ASIA_: #REF!
Name ASSUNÇÃO_: #REF!
Name ASTON_: #REF!
Name ASTOR_: #REF!
Name ASTORY_: #REF!
Name ASTURIAS_: #REF!
Name ASUNCION_: #REF!
Name ATHENAS_: #REF!
Name ATILA_: #REF!
Name ATLAS_: #REF!
Name ATRANI_: #REF!
Name AUSTRIA_: #REF!
Name BACCUS_: #REF!
Name BAEZA_: #REF!
Name BANCO_AMATRICE_: #REF!
Name BANCO_BERNARDINO_: #REF!
Name BANCO_DALI_: #REF!
Name BANCO_GRAZ_: #REF!
Name BANCO_KANOPE_: #REF!
Name BANCO_NEW_: #REF!
Name BANCO_VELDE_: #REF!
Name BANCO_VERNASA_: #REF!
Name BARRAGAN_: #REF!
Name BARROMINI_: #REF!
Name BAUHAUS_: #REF!
Name bb: #REF!
Name BEDFORD_: #REF!

Sheet CAPA
A1: Tabela de Preço de Venda
A12: PRAZO MÉDIO DE PAGAMENTO | B12: 15 DIAS - OURO
A14: MARKUP LOJISTA | B14: 1
A31: FRETE: FOB
A32: PRAZO DE ENTREGA: 50 DIAS
A33: PRAZO DE ENTREGA E/: ATÉ 65 DIAS
A35: OBSERVAÇÕES:
A36: *MEDIDAS ESPECIAIS: SEMPRE MEDIANTE APROVAÇÃO DA INDUSTRIA;
A37: *PRATO GIRATÓRIO EM MESAS REDONDAS: ACRÉSCIMO DE 10% NO VALOR DO ACABAMENTO ESCOLHIDO; | L37: Versão:0001
A38: *EM CASO DE ASSITÊNCIA TÉCNICA, ENTRAR EM CONTATO COM O REPRESENTANTE COMERCIAL DE SUA REGIÃO; | L38: Atualização: 22/01/2026

Sheet APARADOR
B2: TABELA DE PREÇO CENTURY | MADEIRA
C5: Dimensoes (metros)
A6: Imagem | B6: Nome | C6: C | D6: L | E6: A | G6: Tampo: Espelho Bronze, Fume, Prata, Vidro Fosco ou Clear Corpo: Laca ou Lamina | H6: Tampo: Laca ou Lamina com ou sem Vidro Normal Pintado Corpo: Laca ou Lamina | I6: Tampo: Mármore Especial Corpo: Laca ou Lamina | J6: Tampo: Mármore Normal Corpo: Laca ou Lamina | K6: Tampo ou Base em Recoro
B7: Sienna Aparador - 1.4x0.45x0.75 - Acabamentos Customizados | C7: 1.4 | D7: 0.45 | E7: 0.75 | G7: =IFERROR(IF('BASE DE DADOS PREÇOS'!$M$71="com",VLOOKUP(CONCATENATE(B7,$G$6),'BASE DE DADOS PREÇOS'!$E:$H,4,0)/(1-SUM($F$1))*VLOOKUP(CAPA!$B$12,'POLITICA DE PREÇO'!#REF!,2,0)*0.95,VLOOKUP(CONCATENATE(B7,$G$6),'BASE DE DADOS PREÇOS'!$E:$H,4,0)/(1-SUM($F$1))*VLOOKUP(CAPA!$B$12,'POLITICA DE PREÇO'!$B$4:$F$100,5,0))*CAPA!$B$14,"") -> 3254.8243 | H7: =IFERROR(IF('BASE DE DADOS PREÇOS'!$M$71="com",VLOOKUP(CONCATENATE(B7,$H$6),'BASE DE DADOS PREÇOS'!$E:$H,4,0)/(1-SUM($F$1))*VLOOKUP(CAPA!$B$12,'POLITICA DE PREÇO'!#REF!,2,0)*0.95,VLOOKUP(CONCATENATE(B7,$H$6),'BASE DE DADOS PREÇOS'!$E:$H,4,0)/(1-SUM($F$1))*VLOOKUP(CAPA!$B$12,'POLITICA DE PREÇO'!$B$4:$F$100,5,0))*CAPA!$B$14,"") -> 2640.8313 | I7: =IFERROR(IF('BASE DE DADOS PREÇOS'!$M$71="com",VLOOKUP(CONCATENATE(B7,$I$6),'BASE DE DADOS PREÇOS'!$E:$H,4,0)/(1-SUM($F$1))*VLOOKUP(CAPA!$B$12,'POLITICA DE PREÇO'!#REF!,2,0)*0.95,VLOOKUP(CONCATENATE(B7,$I$6),'BASE DE DADOS PREÇOS'!$E:$H,4,0)/(1-SUM($F$1))*VLOOKUP(CAPA!$B$12,'POLITICA DE PREÇO'!$B$4:$F$100,5,0))*CAPA!$B$14,"") -> 5550.635 | J7: =I7*0.9 -> 4995.5715 | K7: =H7*1.05 -> 2772.8729
B8: Sienna Aparador - 1.6x0.45x0.75 - Acabamentos Customizados | C8: 1.6 | D8: 0.45 | E8: 0.75 | G8: =IFERROR(IF('BASE DE DADOS PREÇOS'!$M$71="com",VLOOKUP(CONCATENATE(B8,$G$6),'BASE DE DADOS PREÇOS'!$E:$H,4,0)/(1-SUM($F$1))*VLOOKUP(CAPA!$B$12,'POLITICA DE PREÇO'!#REF!,2,0)*0.95,VLOOKUP(CONCATENATE(B8,$G$6),'BASE DE DADOS PREÇOS'!$E:$H,4,0)/(1-SUM($F$1))*VLOOKUP(CAPA!$B$12,'POLITICA DE PREÇO'!$B$4:$F$100,5,0))*CAPA!$B$14,"") -> 3719.7992 | H8: =IFERROR(IF('BASE DE DADOS PREÇOS'!$M$71="com",VLOOKUP(CONCATENATE(B8,$H$6),'BASE DE DADOS PREÇOS'!$E:$H,4,0)/(1-SUM($F$1))*VLOOKUP(CAPA!$B$12,'POLITICA DE PREÇO'!#REF!,2,0)*0.95,VLOOKUP(CONCATENATE(B8,$H$6),'BASE DE DADOS PREÇOS'!$E:$H,4,0)/(1-SUM($F$1))*VLOOKUP(CAPA!$B$12,'POLITICA DE PREÇO'!$B$4:$F$100,5,0))*CAPA!$B$14,"") -> 3018.093 | I8: =IFERROR(IF('BASE DE DADOS PREÇOS'!$M$71="com",VLOOKUP(CONCATENATE(B8,$I$6),'BASE DE DADOS PREÇOS'!$E:$H,4,0)/(1-SUM($F$1))*VLOOKUP(CAPA!$B$12,'POLITICA DE PREÇO'!#REF!,2,0)*0.95,VLOOKUP(CONCATENATE(B8,$I$6),'BASE DE DADOS PREÇOS'!$E:$H,4,0)/(1-SUM($F$1))*VLOOKUP(CAPA!$B$12,'POLITICA DE PREÇO'!$B$4:$F$100,5,0))*CAPA!$B$14,"") -> 6343.5829 | J8: =I8*0.9 -> 5709.2246 | K8: =H8*1.05 -> 3168.9976
B9: Sienna Aparador - 1.8x0.45x0.75 - Acabamentos Customizados | C9: 1.8 | D9: 0.45 | E9: 0.75 | G9: =IFERROR(IF('BASE DE DADOS PREÇOS'!$M$71="com",VLOOKUP(CONCATENATE(B9,$G$6),'BASE DE DADOS PREÇOS'!$E:$H,4,0)/(1-SUM($F$1))*VLOOKUP(CAPA!$B$12,'POLITICA DE PREÇO'!#REF!,2,0)*0.95,VLOOKUP(CONCATENATE(B9,$G$6),'BASE DE DADOS PREÇOS'!$E:$H,4,0)/(1-SUM($F$1))*VLOOKUP(CAPA!$B$12,'POLITICA DE PREÇO'!$B$4:$F$100,5,0))*CAPA!$B$14,"") -> 4184.7741 | H9: =IFERROR(IF('BASE DE DADOS PREÇOS'!$M$71="com",VLOOKUP(CONCATENATE(B9,$H$6),'BASE DE DADOS PREÇOS'!$E:$H,4,0)/(1-SUM($F$1))*VLOOKUP(CAPA!$B$12,'POLITICA DE PREÇO'!#REF!,2,0)*0.95,VLOOKUP(CONCATENATE(B9,$H$6),'BASE DE DADOS PREÇOS'!$E:$H,4,0)/(1-SUM($F$1))*VLOOKUP(CAPA!$B$12,'POLITICA DE PREÇO'!$B$4:$F$100,5,0))*CAPA!$B$14,"") -> 3395.3546 | I9: =IFERROR(IF('BASE DE DADOS PREÇOS'!$M$71="com",VLOOKUP(CONCATENATE(B9,$I$6),'BASE DE DADOS PREÇOS'!$E:$H,4,0)/(1-SUM($F$1))*VLOOKUP(CAPA!$B$12,'POLITICA DE PREÇO'!#REF!,2,0)*0.95,VLOOKUP(CONCATENATE(B9,$I$6),'BASE DE DADOS PREÇOS'!$E:$H,4,0)/(1-SUM($F$1))*VLOOKUP(CAPA!$B$12,'POLITICA DE PREÇO'!$B$4:$F$100,5,0))*CAPA!$B$14,"") -> 7136.5308 | J9: =I9*0.9 -> 6422.8777 | K9: =H9*1.05 -> 3565.1223
B10: Sienna Aparador - 2x0.45x0.75 - Acabamentos Customizados | C10: 2 | D10: 0.45 | E10: 0.75 | G10: =IFERROR(IF('BASE DE DADOS PREÇOS'!$M$71="com",VLOOKUP(CONCATENATE(B10,$G$6),'BASE DE DADOS PREÇOS'!$E:$H,4,0)/(1-SUM($F$1))*VLOOKUP(CAPA!$B$12,'POLITICA DE PREÇO'!#REF!,2,0)*0.95,VLOOKUP(CONCATENATE(B10,$G$6),'BASE DE DADOS PREÇOS'!$E:$H,4,0)/(1-SUM($F$1))*VLOOKUP(CAPA!$B$12,'POLITICA DE PREÇO'!$B$4:$F$100,5,0))*CAPA!$B$14,"") -> 4649.749 | H10: =IFERROR(IF('BASE DE DADOS PREÇOS'!$M$71="com",VLOOKUP(CONCATENATE(B10,$H$6),'BASE DE DADOS PREÇOS'!$E:$H,4,0)/(1-SUM($F$1))*VLOOKUP(CAPA!$B$12,'POLITICA DE PREÇO'!#REF!,2,0)*0.95,VLOOKUP(CONCATENATE(B10,$H$6),'BASE DE DADOS PREÇOS'!$E:$H,4,0)/(1-SUM($F$1))*VLOOKUP(CAPA!$B$12,'POLITICA DE PREÇO'!$B$4:$F$100,5,0))*CAPA!$B$14,"") -> 3772.6162 | I10: =IFERROR(IF('BASE DE DADOS PREÇOS'!$M$71="com",VLOOKUP(CONCATENATE(B10,$I$6),'BASE DE DADOS PREÇOS'!$E:$H,4,0)/(1-SUM($F$1))*VLOOKUP(CAPA!$B$12,'POLITICA DE PREÇO'!#REF!,2,0)*0.95,VLOOKUP(CONCATENATE(B10,$I$6),'BASE DE DADOS PREÇOS'!$E:$H,4,0)/(1-SUM($F$1))*VLOOKUP(CAPA!$B$12,'POLITICA DE PREÇO'!$B$4:$F$100,5,0))*CAPA!$B$14,"") -> 7929.4786 | J10: =I10*0.9 -> 7136.5308 | K10: =H10*1.05 -> 3961.247
B11: Sienna Aparador - 2.2x0.45x0.75 - Acabamentos Customizados | C11: 2.2 | D11: 0.45 | E11: 0.75 | G11: =IFERROR(IF('BASE DE DADOS PREÇOS'!$M$71="com",VLOOKUP(CONCATENATE(B11,$G$6),'BASE DE DADOS PREÇOS'!$E:$H,4,0)/(1-SUM($F$1))*VLOOKUP(CAPA!$B$12,'POLITICA DE PREÇO'!#REF!,2,0)*0.95,VLOOKUP(CONCATENATE(B11,$G$6),'BASE DE DADOS PREÇOS'!$E:$H,4,0)/(1-SUM($F$1))*VLOOKUP(CAPA!$B$12,'POLITICA DE PREÇO'!$B$4:$F$100,5,0))*CAPA!$B$14,"") -> 5114.7239 | H11: =IFERROR(IF('BASE DE DADOS PREÇOS'!$M$71="com",VLOOKUP(CONCATENATE(B11,$H$6),'BASE DE DADOS PREÇOS'!$E:$H,4,0)/(1-SUM($F$1))*VLOOKUP(CAPA!$B$12,'POLITICA DE PREÇO'!#REF!,2,0)*0.95,VLOOKUP(CONCATENATE(B11,$H$6),'BASE DE DADOS PREÇOS'!$E:$H,4,0)/(1-SUM($F$1))*VLOOKUP(CAPA!$B$12,'POLITICA DE PREÇO'!$B$4:$F$100,5,0))*CAPA!$B$14,"") -> 4149.8778 | I11: =IFERROR(IF('BASE DE DADOS PREÇOS'!$M$71="com",VLOOKUP(CONCATENATE(B11,$I$6),'BASE DE DADOS PREÇOS'!$E:$H,4,0)/(1-SUM($F$1))*VLOOKUP(CAPA!$B$12,'POLITICA DE PREÇO'!#REF!,2,0)*0.95,VLOOKUP(CONCATENATE(B11,$I$6),'BASE DE DADOS PREÇOS'!$E:$H,4,0)/(1-SUM($F$1))*VLOOKUP(CAPA!$B$12,'POLITICA DE PREÇO'!$B$4:$F$100,5,0))*CAPA!$B$14,"") -> 8722.4265 | J11: =I11*0.9 -> 7850.1839 | K11: =H11*1.05 -> 4357.3717
B12: Sienna Aparador - 2.4x0.45x0.75 - Acabamentos Customizados | C12: 2.4 | D12: 0.45 | E12: 0.75 | G12: =IFERROR(IF('BASE DE DADOS PREÇOS'!$M$71="com",VLOOKUP(CONCATENATE(B12,$G$6),'BASE DE DADOS PREÇOS'!$E:$H,4,0)/(1-SUM($F$1))*VLOOKUP(CAPA!$B$12,'POLITICA DE PREÇO'!#REF!,2,0)*0.95,VLOOKUP(CONCATENATE(B12,$G$6),'BASE DE DADOS PREÇOS'!$E:$H,4,0)/(1-SUM($F$1))*VLOOKUP(CAPA!$B$12,'POLITICA DE PREÇO'!$B$4:$F$100,5,0))*CAPA!$B$14,"") -> 5579.6988 | H12: =IFERROR(IF('BASE DE DADOS PREÇOS'!$M$71="com",VLOOKUP(CONCATENATE(B12,$H$6),'BASE DE DADOS PREÇOS'!$E:$H,4,0)/(1-SUM($F$1))*VLOOKUP(CAPA!$B$12,'POLITICA DE PREÇO'!#REF!,2,0)*0.95,VLOOKUP(CONCATENATE(B12,$H$6),'BASE DE DADOS PREÇOS'!$E:$H,4,0)/(1-SUM($F$1))*VLOOKUP(CAPA!$B$12,'POLITICA DE PREÇO'!$B$4:$F$100,5,0))*CAPA!$B$14,"") -> 4527.1395 | I12: =IFERROR(IF('BASE DE DADOS PREÇOS'!$M$71="com",VLOOKUP(CONCATENATE(B12,$I$6),'BASE DE DADOS PREÇOS'!$E:$H,4,0)/(1-SUM($F$1))*VLOOKUP(CAPA!$B$12,'POLITICA DE PREÇO'!#REF!,2,0)*0.95,VLOOKUP(CONCATENATE(B12,$I$6),'BASE DE DADOS PREÇOS'!$E:$H,4,0)/(1-SUM($F$1))*VLOOKUP(CAPA!$B$12,'POLITICA DE PREÇO'!$B$4:$F$100,5,0))*CAPA!$B$14,"") -> 9515.3744 | J12: =I12*0.9 -> 8563.8369 | K12: =H12*1.05 -> 4753.4964
B13: Taijin Aparador - 1.6x0.5x0.79 - Acabamentos Customizados | C13: 1.6 | D13: 0.5 | E13: 0.79 | G13: =IFERROR(IF('BASE DE DADOS PREÇOS'!$M$71="com",VLOOKUP(CONCATENATE(B13,$G$6),'BASE DE DADOS PREÇOS'!$E:$H,4,0)/(1-SUM($F$1))*VLOOKUP(CAPA!$B$12,'POLITICA DE PREÇO'!#REF!,2,0)*0.95,VLOOKUP(CONCATENATE(B13,$G$6),'BASE DE DADOS PREÇOS'!$E:$H,4,0)/(1-SUM($F$1))*VLOOKUP(CAPA!$B$12,'POLITICA DE PREÇO'!$B$4:$F$100,5,0))*CAPA!$B$14,"") -> 4589.4646 | H13: =IFERROR(IF('BASE DE DADOS PREÇOS'!$M$71="com",VLOOKUP(CONCATENATE(B13,$H$6),'BASE DE DADOS PREÇOS'!$E:$H,4,0)/(1-SUM($F$1))*VLOOKUP(CAPA!$B$12,'POLITICA DE PREÇO'!#REF!,2,0)*0.95,VLOOKUP(CONCATENATE(B13,$H$6),'BASE DE DADOS PREÇOS'!$E:$H,4,0)/(1-SUM($F$1))*VLOOKUP(CAPA!$B$12,'POLITICA DE PREÇO'!$B$4:$F$100,5,0))*CAPA!$B$14,"") -> 3725.2907 | I13: =IFERROR(IF('BASE DE DADOS PREÇOS'!$M$71="com",VLOOKUP(CONCATENATE(B13,$I$6),'BASE DE DADOS PREÇOS'!$E:$H,4,0)/(1-SUM($F$1))*VLOOKUP(CAPA!$B$12,'POLITICA DE PREÇO'!#REF!,2,0)*0.95,VLOOKUP(CONCATENATE(B13,$I$6),'BASE DE DADOS PREÇOS'!$E:$H,4,0)/(1-SUM($F$1))*VLOOKUP(CAPA!$B$12,'POLITICA DE PREÇO'!$B$4:$F$100,5,0))*CAPA!$B$14,"") -> 7432.0488 | J13: =I13*0.9 -> 6688.8439 | K13: =H13*1.05 -> 3911.5552
B14: Taijin Aparador - 1.8x0.5x0.79 - Acabamentos Customizados | C14: 1.8 | D14: 0.5 | E14: 0.79 | G14: =IFERROR(IF('BASE DE DADOS PREÇOS'!$M$71="com",VLOOKUP(CONCATENATE(B14,$G$6),'BASE DE DADOS PREÇOS'!$E:$H,4,0)/(1-SUM($F$1))*VLOOKUP(CAPA!$B$12,'POLITICA DE PREÇO'!#REF!,2,0)*0.95,VLOOKUP(CONCATENATE(B14,$G$6),'BASE DE DADOS PREÇOS'!$E:$H,4,0)/(1-SUM($F$1))*VLOOKUP(CAPA!$B$12,'POLITICA DE PREÇO'!$B$4:$F$100,5,0))*CAPA!$B$14,"") -> 4990.8096 | H14: =IFERROR(IF('BASE DE DADOS PREÇOS'!$M$71="com",VLOOKUP(CONCATENATE(B14,$H$6),'BASE DE DADOS PREÇOS'!$E:$H,4,0)/(1-SUM($F$1))*VLOOKUP(CAPA!$B$12,'POLITICA DE PREÇO'!#REF!,2,0)*0.95,VLOOKUP(CONCATENATE(B14,$H$6),'BASE DE DADOS PREÇOS'!$E:$H,4,0)/(1-SUM($F$1))*VLOOKUP(CAPA!$B$12,'POLITICA DE PREÇO'!$B$4:$F$100,5,0))*CAPA!$B$14,"") -> 4007.527 | I14: =IFERROR(IF('BASE DE DADOS PREÇOS'!$M$71="com",VLOOKUP(CONCATENATE(B14,$I$6),'BASE DE DADOS PREÇOS'!$E:$H,4,0)/(1-SUM($F$1))*VLOOKUP(CAPA!$B$12,'POLITICA DE PREÇO'!#REF!,2,0)*0.95,VLOOKUP(CONCATENATE(B14,$I$6),'BASE DE DADOS PREÇOS'!$E:$H,4,0)/(1-SUM($F$1))*VLOOKUP(CAPA!$B$12,'POLITICA DE PREÇO'!$B$4:$F$100,5,0))*CAPA!$B$14,"") -> 8176.8255 | J14: =I14*0.9 -> 7359.1429 | K14: =H14*1.05 -> 4207.9034
B15: Taijin Aparador - 2x0.5x0.79 - Acabamentos Customizados | C15: 2 | D15: 0.5 | E15: 0.79 | G15: =IFERROR(IF('BASE DE DADOS PREÇOS'!$M$71="com",VLOOKUP(CONCATENATE(B15,$G$6),'BASE DE DADOS PREÇOS'!$E:$H,4,0)/(1-SUM($F$1))*VLOOKUP(CAPA!$B$12,'POLITICA DE PREÇO'!#REF!,2,0)*0.95,VLOOKUP(CONCATENATE(B15,$G$6),'BASE DE DADOS PREÇOS'!$E:$H,4,0)/(1-SUM($F$1))*VLOOKUP(CAPA!$B$12,'POLITICA DE PREÇO'!$B$4:$F$100,5,0))*CAPA!$B$14,"") -> 5394.4517 | H15: =IFERROR(IF('BASE DE DADOS PREÇOS'!$M$71="com",VLOOKUP(CONCATENATE(B15,$H$6),'BASE DE DADOS PREÇOS'!$E:$H,4,0)/(1-SUM($F$1))*VLOOKUP(CAPA!$B$12,'POLITICA DE PREÇO'!#REF!,2,0)*0.95,VLOOKUP(CONCATENATE(B15,$H$6),'BASE DE DADOS PREÇOS'!$E:$H,4,0)/(1-SUM($F$1))*VLOOKUP(CAPA!$B$12,'POLITICA DE PREÇO'!$B$4:$F$100,5,0))*CAPA!$B$14,"") -> 4292.1814 | I15: =IFERROR(IF('BASE DE DADOS PREÇOS'!$M$71="com",VLOOKUP(CONCATENATE(B15,$I$6),'BASE DE DADOS PREÇOS'!$E:$H,4,0)/(1-SUM($F$1))*VLOOKUP(CAPA!$B$12,'POLITICA DE PREÇO'!#REF!,2,0)*0.95,VLOOKUP(CONCATENATE(B15,$I$6),'BASE DE DADOS PREÇOS'!$E:$H,4,0)/(1-SUM($F$1))*VLOOKUP(CAPA!$B$12,'POLITICA DE PREÇO'!$B$4:$F$100,5,0))*CAPA!$B$14,"") -> 8924.0044 | J15: =I15*0.9 -> 8031.6039 | K15: =H15*1.05 -> 4506.7904
B16: Taijin Aparador Com Gaveta - 1.6x0.5x0.79 - Acabamentos Customizados | C16: 1.6 | D16: 0.5 | E16: 0.79 | G16: =IFERROR(IF('BASE DE DADOS PREÇOS'!$M$71="com",VLOOKUP(CONCATENATE(B16,$G$6),'BASE DE DADOS PREÇOS'!$E:$H,4,0)/(1-SUM($F$1))*VLOOKUP(CAPA!$B$12,'POLITICA DE PREÇO'!#REF!,2,0)*0.95,VLOOKUP(CONCATENATE(B16,$G$6),'BASE DE DADOS PREÇOS'!$E:$H,4,0)/(1-SUM($F$1))*VLOOKUP(CAPA!$B$12,'POLITICA DE PREÇO'!$B$4:$F$100,5,0))*CAPA!$B$14,"") -> 4895.9677 | H16: =IFERROR(IF('BASE DE DADOS PREÇOS'!$M$71="com",VLOOKUP(CONCATENATE(B16,$H$6),'BASE DE DADOS PREÇOS'!$E:$H,4,0)/(1-SUM($F$1))*VLOOKUP(CAPA!$B$12,'POLITICA DE PREÇO'!#REF!,2,0)*0.95,VLOOKUP(CONCATENATE(B16,$H$6),'BASE DE DADOS PREÇOS'!$E:$H,4,0)/(1-SUM($F$1))*VLOOKUP(CAPA!$B$12,'POLITICA DE PREÇO'!$B$4:$F$100,5,0))*CAPA!$B$14,"") -> 4031.7938 | I16: =IFERROR(IF('BASE DE DADOS PREÇOS'!$M$71="com",VLOOKUP(CONCATENATE(B16,$I$6),'BASE DE DADOS PREÇOS'!$E:$H,4,0)/(1-SUM($F$1))*VLOOKUP(CAPA!$B$12,'POLITICA DE PREÇO'!#REF!,2,0)*0.95,VLOOKUP(CONCATENATE(B16,$I$6),'BASE DE DADOS PREÇOS'!$E:$H,4,0)/(1-SUM($F$1))*VLOOKUP(CAPA!$B$12,'POLITICA DE PREÇO'!$B$4:$F$100,5,0))*CAPA!$B$14,"") -> 7720.5223 | J16: =I16*0.9 -> 6948.4701 | K16: =H16*1.05 -> 4233.3835
B17: Taijin Aparador Com Gaveta - 1.8x0.5x0.79 - Acabamentos Customizados | C17: 1.8 | D17: 0.5 | E17: 0.79 | G17: =IFERROR(IF('BASE DE DADOS PREÇOS'!$M$71="com",VLOOKUP(CONCATENATE(B17,$G$6),'BASE DE DADOS PREÇOS'!$E:$H,4,0)/(1-SUM($F$1))*VLOOKUP(CAPA!$B$12,'POLITICA DE PREÇO'!#REF!,2,0)*0.95,VLOOKUP(CONCATENATE(B17,$G$6),'BASE DE DADOS PREÇOS'!$E:$H,4,0)/(1-SUM($F$1))*VLOOKUP(CAPA!$B$12,'POLITICA DE PREÇO'!$B$4:$F$100,5,0))*CAPA!$B$14,"") -> 5297.3127 | H17: =IFERROR(IF('BASE DE DADOS PREÇOS'!$M$71="com",VLOOKUP(CONCATENATE(B17,$H$6),'BASE DE DADOS PREÇOS'!$E:$H,4,0)/(1-SUM($F$1))*VLOOKUP(CAPA!$B$12,'POLITICA DE PREÇO'!#REF!,2,0)*0.95,VLOOKUP(CONCATENATE(B17,$H$6),'BASE DE DADOS PREÇOS'!$E:$H,4,0)/(1-SUM($F$1))*VLOOKUP(CAPA!$B$12,'POLITICA DE PREÇO'!$B$4:$F$100,5,0))*CAPA!$B$14,"") -> 4314.0301 | I17: =IFERROR(IF('BASE DE DADOS PREÇOS'!$M$71="com",VLOOKUP(CONCATENATE(B17,$I$6),'BASE DE DADOS PREÇOS'!$E:$H,4,0)/(1-SUM($F$1))*VLOOKUP(CAPA!$B$12,'POLITICA DE PREÇO'!#REF!,2,0)*0.95,VLOOKUP(CONCATENATE(B17,$I$6),'BASE DE DADOS PREÇOS'!$E:$H,4,0)/(1-SUM($F$1))*VLOOKUP(CAPA!$B$12,'POLITICA DE PREÇO'!$B$4:$F$100,5,0))*CAPA!$B$14,"") -> 8465.299 | J17: =I17*0.9 -> 7618.7691 | K17: =H17*1.05 -> 4529.7316
B18: Taijin Aparador Com Gaveta - 2x0.5x0.79 - Acabamentos Customizados | C18: 2 | D18: 0.5 | E18: 0.79 | G18: =IFERROR(IF('BASE DE DADOS PREÇOS'!$M$71="com",VLOOKUP(CONCATENATE(B18,$G$6),'BASE DE DADOS PREÇOS'!$E:$H,4,0)/(1-SUM($F$1))*VLOOKUP(CAPA!$B$12,'POLITICA DE PREÇO'!#REF!,2,0)*0.95,VLOOKUP(CONCATENATE(B18,$G$6),'BASE DE DADOS PREÇOS'!$E:$H,4,0)/(1-SUM($F$1))*VLOOKUP(CAPA!$B$12,'POLITICA DE PREÇO'!$B$4:$F$100,5,0))*CAPA!$B$14,"") -> 5700.9548 | H18: =IFERROR(IF('BASE DE DADOS PREÇOS'!$M$71="com",VLOOKUP(CONCATENATE(B18,$H$6),'BASE DE DADOS PREÇOS'!$E:$H,4,0)/(1-SUM($F$1))*VLOOKUP(CAPA!$B$12,'POLITICA DE PREÇO'!#REF!,2,0)*0.95,VLOOKUP(CONCATENATE(B18,$H$6),'BASE DE DADOS PREÇOS'!$E:$H,4,0)/(1-SUM($F$1))*VLOOKUP(CAPA!$B$12,'POLITICA DE PREÇO'!$B$4:$F$100,5,0))*CAPA!$B$14,"") -> 4598.6845 | I18: =IFERROR(IF('BASE DE DADOS PREÇOS'!$M$71="com",VLOOKUP(CONCATENATE(B18,$I$6),'BASE DE DADOS PREÇOS'!$E:$H,4,0)/(1-SUM($F$1))*VLOOKUP(CAPA!$B$12,'POLITICA DE PREÇO'!#REF!,2,0)*0.95,VLOOKUP(CONCATENATE(B18,$I$6),'BASE DE DADOS PREÇOS'!$E:$H,4,0)/(1-SUM($F$1))*VLOOKUP(CAPA!$B$12,'POLITICA DE PREÇO'!$B$4:$F$100,5,0))*CAPA!$B$14,"") -> 9212.4779 | J18: =I18*0.9 -> 8291.2301 | K18: =H18*1.05 -> 4828.6187

Sheet BUFFET
B2: TABELA DE PREÇO CENTURY | MADEIRA
C5: Dimensoes (metros)
A6: Imagem | B6: Nome | C6: C | D6: L | E6: A | G6: Tampo: Espelho Bronze, Fume, Prata, Vidro Fosco ou Clear Corpo: Laca ou Lamina | H6: Tampo: Laca ou Lamina com ou sem Vidro Normal Pintado Corpo: Laca ou Lamina | I6: Tampo: Mármore ou Porcelana Especial Corpo: Laca ou Lamina | J6: Tampo: Mármore Normal Corpo: Laca ou Lamina | K6: Tampo ou Base em Recoro
B7: Mantova Buffet - 2x0.5x76 - Acabamentos Customizados | C7: 2 | D7: 0.5 | E7: 0.76 | G7: =IFERROR(IF('BASE DE DADOS PREÇOS'!$M$71="com",VLOOKUP(CONCATENATE(B7,$G$6),'BASE DE DADOS PREÇOS'!$E:$H,4,0)/(1-SUM($G$1))*VLOOKUP(CAPA!$B$12,'POLITICA DE PREÇO'!#REF!,2,0)*0.95,VLOOKUP(CONCATENATE(B7,$G$6),'BASE DE DADOS PREÇOS'!$E:$H,4,0)/(1-SUM($G$1))*VLOOKUP(CAPA!$B$12,'POLITICA DE PREÇO'!$B$4:$F$100,5,0))*CAPA!$B$14,"") -> 9702.4251 | H7: =IFERROR(IF('BASE DE DADOS PREÇOS'!$M$71="com",VLOOKUP(CONCATENATE(B7,$H$6),'BASE DE DADOS PREÇOS'!$E:$H,4,0)/(1-SUM($G$1))*VLOOKUP(CAPA!$B$12,'POLITICA DE PREÇO'!#REF!,2,0)*0.95,VLOOKUP(CONCATENATE(B7,$H$6),'BASE DE DADOS PREÇOS'!$E:$H,4,0)/(1-SUM($G$1))*VLOOKUP(CAPA!$B$12,'POLITICA DE PREÇO'!$B$4:$F$100,5,0))*CAPA!$B$14,"") -> 8144.2059 | I7: =IFERROR(IF('BASE DE DADOS PREÇOS'!$M$71="com",VLOOKUP(CONCATENATE(B7,$I$6),'BASE DE DADOS PREÇOS'!$E:$H,4,0)/(1-SUM($G$1))*VLOOKUP(CAPA!$B$12,'POLITICA DE PREÇO'!#REF!,2,0)*0.95,VLOOKUP(CONCATENATE(B7,$I$6),'BASE DE DADOS PREÇOS'!$E:$H,4,0)/(1-SUM($G$1))*VLOOKUP(CAPA!$B$12,'POLITICA DE PREÇO'!$B$4:$F$100,5,0))*CAPA!$B$14,"") -> 13200.611 | J7: =I7*0.9 -> 11880.55
B8: Mantova Buffet - 2.2x0.5x76 - Acabamentos Customizados | C8: 2.2 | D8: 0.5 | E8: 0.76 | G8: =IFERROR(IF('BASE DE DADOS PREÇOS'!$M$71="com",VLOOKUP(CONCATENATE(B8,$G$6),'BASE DE DADOS PREÇOS'!$E:$H,4,0)/(1-SUM($G$1))*VLOOKUP(CAPA!$B$12,'POLITICA DE PREÇO'!#REF!,2,0)*0.95,VLOOKUP(CONCATENATE(B8,$G$6),'BASE DE DADOS PREÇOS'!$E:$H,4,0)/(1-SUM($G$1))*VLOOKUP(CAPA!$B$12,'POLITICA DE PREÇO'!$B$4:$F$100,5,0))*CAPA!$B$14,"") -> 9974.3609 | H8: =IFERROR(IF('BASE DE DADOS PREÇOS'!$M$71="com",VLOOKUP(CONCATENATE(B8,$H$6),'BASE DE DADOS PREÇOS'!$E:$H,4,0)/(1-SUM($G$1))*VLOOKUP(CAPA!$B$12,'POLITICA DE PREÇO'!#REF!,2,0)*0.95,VLOOKUP(CONCATENATE(B8,$H$6),'BASE DE DADOS PREÇOS'!$E:$H,4,0)/(1-SUM($G$1))*VLOOKUP(CAPA!$B$12,'POLITICA DE PREÇO'!$B$4:$F$100,5,0))*CAPA!$B$14,"") -> 8429.4784 | I8: =IFERROR(IF('BASE DE DADOS PREÇOS'!$M$71="com",VLOOKUP(CONCATENATE(B8,$I$6),'BASE DE DADOS PREÇOS'!$E:$H,4,0)/(1-SUM($G$1))*VLOOKUP(CAPA!$B$12,'POLITICA DE PREÇO'!#REF!,2,0)*0.95,VLOOKUP(CONCATENATE(B8,$I$6),'BASE DE DADOS PREÇOS'!$E:$H,4,0)/(1-SUM($G$1))*VLOOKUP(CAPA!$B$12,'POLITICA DE PREÇO'!$B$4:$F$100,5,0))*CAPA!$B$14,"") -> 13908.141 | J8: =I8*0.9 -> 12517.327
B9: Mantova Buffet - 2.4x0.5x76 - Acabamentos Customizados | C9: 2.4 | D9: 0.5 | E9: 0.76 | G9: =IFERROR(IF('BASE DE DADOS PREÇOS'!$M$71="com",VLOOKUP(CONCATENATE(B9,$G$6),'BASE DE DADOS PREÇOS'!$E:$H,4,0)/(1-SUM($G$1))*VLOOKUP(CAPA!$B$12,'POLITICA DE PREÇO'!#REF!,2,0)*0.95,VLOOKUP(CONCATENATE(B9,$G$6),'BASE DE DADOS PREÇOS'!$E:$H,4,0)/(1-SUM($G$1))*VLOOKUP(CAPA!$B$12,'POLITICA DE PREÇO'!$B$4:$F$100,5,0))*CAPA!$B$14,"") -> 10338.43 | H9: =IFERROR(IF('BASE DE DADOS PREÇOS'!$M$71="com",VLOOKUP(CONCATENATE(B9,$H$6),'BASE DE DADOS PREÇOS'!$E:$H,4,0)/(1-SUM($G$1))*VLOOKUP(CAPA!$B$12,'POLITICA DE PREÇO'!#REF!,2,0)*0.95,VLOOKUP(CONCATENATE(B9,$H$6),'BASE DE DADOS PREÇOS'!$E:$H,4,0)/(1-SUM($G$1))*VLOOKUP(CAPA!$B$12,'POLITICA DE PREÇO'!$B$4:$F$100,5,0))*CAPA!$B$14,"") -> 9177.0523 | I9: =IFERROR(IF('BASE DE DADOS PREÇOS'!$M$71="com",VLOOKUP(CONCATENATE(B9,$I$6),'BASE DE DADOS PREÇOS'!$E:$H,4,0)/(1-SUM($G$1))*VLOOKUP(CAPA!$B$12,'POLITICA DE PREÇO'!#REF!,2,0)*0.95,VLOOKUP(CONCATENATE(B9,$I$6),'BASE DE DADOS PREÇOS'!$E:$H,4,0)/(1-SUM($G$1))*VLOOKUP(CAPA!$B$12,'POLITICA DE PREÇO'!$B$4:$F$100,5,0))*CAPA!$B$14,"") -> 14724.157 | J9: =I9*0.9 -> 13251.741
B10: Modena Buffet - 2x0.5x76 - Acabamentos Customizados | C10: 2 | D10: 0.5 | E10: 0.76 | G10: =IFERROR(IF('BASE DE DADOS PREÇOS'!$M$71="com",VLOOKUP(CONCATENATE(B10,$G$6),'BASE DE DADOS PREÇOS'!$E:$H,4,0)/(1-SUM($G$1))*VLOOKUP(CAPA!$B$12,'POLITICA DE PREÇO'!#REF!,2,0)*0.95,VLOOKUP(CONCATENATE(B10,$G$6),'BASE DE DADOS PREÇOS'!$E:$H,4,0)/(1-SUM($G$1))*VLOOKUP(CAPA!$B$12,'POLITICA DE PREÇO'!$B$4:$F$100,5,0))*CAPA!$B$14,"") -> 9713.2448 | H10: =IFERROR(IF('BASE DE DADOS PREÇOS'!$M$71="com",VLOOKUP(CONCATENATE(B10,$H$6),'BASE DE DADOS PREÇOS'!$E:$H,4,0)/(1-SUM($G$1))*VLOOKUP(CAPA!$B$12,'POLITICA DE PREÇO'!#REF!,2,0)*0.95,VLOOKUP(CONCATENATE(B10,$H$6),'BASE DE DADOS PREÇOS'!$E:$H,4,0)/(1-SUM($G$1))*VLOOKUP(CAPA!$B$12,'POLITICA DE PREÇO'!$B$4:$F$100,5,0))*CAPA!$B$14,"") -> 8160.8946 | I10: =IFERROR(IF('BASE DE DADOS PREÇOS'!$M$71="com",VLOOKUP(CONCATENATE(B10,$I$6),'BASE DE DADOS PREÇOS'!$E:$H,4,0)/(1-SUM($G$1))*VLOOKUP(CAPA!$B$12,'POLITICA DE PREÇO'!#REF!,2,0)*0.95,VLOOKUP(CONCATENATE(B10,$I$6),'BASE DE DADOS PREÇOS'!$E:$H,4,0)/(1-SUM($G$1))*VLOOKUP(CAPA!$B$12,'POLITICA DE PREÇO'!$B$4:$F$100,5,0))*CAPA!$B$14,"") -> 13487.504 | J10: =I10*0.9 -> 12138.754
B11: Modena Buffet - 2.2x0.5x76 - Acabamentos Customizados | C11: 2.2 | D11: 0.5 | E11: 0.76 | G11: =IFERROR(IF('BASE DE DADOS PREÇOS'!$M$71="com",VLOOKUP(CONCATENATE(B11,$G$6),'BASE DE DADOS PREÇOS'!$E:$H,4,0)/(1-SUM($G$1))*VLOOKUP(CAPA!$B$12,'POLITICA DE PREÇO'!#REF!,2,0)*0.95,VLOOKUP(CONCATENATE(B11,$G$6),'BASE DE DADOS PREÇOS'!$E:$H,4,0)/(1-SUM($G$1))*VLOOKUP(CAPA!$B$12,'POLITICA DE PREÇO'!$B$4:$F$100,5,0))*CAPA!$B$14,"") -> 9851.9858 | H11: =IFERROR(IF('BASE DE DADOS PREÇOS'!$M$71="com",VLOOKUP(CONCATENATE(B11,$H$6),'BASE DE DADOS PREÇOS'!$E:$H,4,0)/(1-SUM($G$1))*VLOOKUP(CAPA!$B$12,'POLITICA DE PREÇO'!#REF!,2,0)*0.95,VLOOKUP(CONCATENATE(B11,$H$6),'BASE DE DADOS PREÇOS'!$E:$H,4,0)/(1-SUM($G$1))*VLOOKUP(CAPA!$B$12,'POLITICA DE PREÇO'!$B$4:$F$100,5,0))*CAPA!$B$14,"") -> 8517.7873 | I11: =IFERROR(IF('BASE DE DADOS PREÇOS'!$M$71="com",VLOOKUP(CONCATENATE(B11,$I$6),'BASE DE DADOS PREÇOS'!$E:$H,4,0)/(1-SUM($G$1))*VLOOKUP(CAPA!$B$12,'POLITICA DE PREÇO'!#REF!,2,0)*0.95,VLOOKUP(CONCATENATE(B11,$I$6),'BASE DE DADOS PREÇOS'!$E:$H,4,0)/(1-SUM($G$1))*VLOOKUP(CAPA!$B$12,'POLITICA DE PREÇO'!$B$4:$F$100,5,0))*CAPA!$B$14,"") -> 14229.144 | J11: =I11*0.9 -> 12806.229
B12: Modena Buffet - 2.4x0.5x76 - Acabamentos Customizados | C12: 2.4 | D12: 0.5 | E12: 0.76 | G12: =IFERROR(IF('BASE DE DADOS PREÇOS'!$M$71="com",VLOOKUP(CONCATENATE(B12,$G$6),'BASE DE DADOS PREÇOS'!$E:$H,4,0)/(1-SUM($G$1))*VLOOKUP(CAPA!$B$12,'POLITICA DE PREÇO'!#REF!,2,0)*0.95,VLOOKUP(CONCATENATE(B12,$G$6),'BASE DE DADOS PREÇOS'!$E:$H,4,0)/(1-SUM($G$1))*VLOOKUP(CAPA!$B$12,'POLITICA DE PREÇO'!$B$4:$F$100,5,0))*CAPA!$B$14,"") -> 10243.881 | H12: =IFERROR(IF('BASE DE DADOS PREÇOS'!$M$71="com",VLOOKUP(CONCATENATE(B12,$H$6),'BASE DE DADOS PREÇOS'!$E:$H,4,0)/(1-SUM($G$1))*VLOOKUP(CAPA!$B$12,'POLITICA DE PREÇO'!#REF!,2,0)*0.95,VLOOKUP(CONCATENATE(B12,$H$6),'BASE DE DADOS PREÇOS'!$E:$H,4,0)/(1-SUM($G$1))*VLOOKUP(CAPA!$B$12,'POLITICA DE PREÇO'!$B$4:$F$100,5,0))*CAPA!$B$14,"") -> 9368.4558 | I12: =IFERROR(IF('BASE DE DADOS PREÇOS'!$M$71="com",VLOOKUP(CONCATENATE(B12,$I$6),'BASE DE DADOS PREÇOS'!$E:$H,4,0)/(1-SUM($G$1))*VLOOKUP(CAPA!$B$12,'POLITICA DE PREÇO'!#REF!,2,0)*0.95,VLOOKUP(CONCATENATE(B12,$I$6),'BASE DE DADOS PREÇOS'!$E:$H,4,0)/(1-SUM($G$1))*VLOOKUP(CAPA!$B$12,'POLITICA DE PREÇO'!$B$4:$F$100,5,0))*CAPA!$B$14,"") -> 15189.577 | J12: =I12*0.9 -> 13670.619
B13: Modena Bar - 1.3x0.5x76 - Acabamentos Customizados | C13: 1.3 | D13: 0.5 | E13: 0.76 | G13: =IFERROR(IF('BASE DE DADOS PREÇOS'!$M$71="com",VLOOKUP(CONCATENATE(B13,$G$6),'BASE DE DADOS PREÇOS'!$E:$H,4,0)/(1-SUM($G$1))*VLOOKUP(CAPA!$B$12,'POLITICA DE PREÇO'!#REF!,2,0)*0.95,VLOOKUP(CONCATENATE(B13,$G$6),'BASE DE DADOS PREÇOS'!$E:$H,4,0)/(1-SUM($G$1))*VLOOKUP(CAPA!$B$12,'POLITICA DE PREÇO'!$B$4:$F$100,5,0))*CAPA!$B$14,"") -> 6426.2923 | H13: =IFERROR(IF('BASE DE DADOS PREÇOS'!$M$71="com",VLOOKUP(CONCATENATE(B13,$H$6),'BASE DE DADOS PREÇOS'!$E:$H,4,0)/(1-SUM($G$1))*VLOOKUP(CAPA!$B$12,'POLITICA DE PREÇO'!#REF!,2,0)*0.95,VLOOKUP(CONCATENATE(B13,$H$6),'BASE DE DADOS PREÇOS'!$E:$H,4,0)/(1-SUM($G$1))*VLOOKUP(CAPA!$B$12,'POLITICA DE PREÇO'!$B$4:$F$100,5,0))*CAPA!$B$14,"") -> 5860.1048 | I13: =IFERROR(IF('BASE DE DADOS PREÇOS'!$M$71="com",VLOOKUP(CONCATENATE(B13,$I$6),'BASE DE DADOS PREÇOS'!$E:$H,4,0)/(1-SUM($G$1))*VLOOKUP(CAPA!$B$12,'POLITICA DE PREÇO'!#REF!,2,0)*0.95,VLOOKUP(CONCATENATE(B13,$I$6),'BASE DE DADOS PREÇOS'!$E:$H,4,0)/(1-SUM($G$1))*VLOOKUP(CAPA!$B$12,'POLITICA DE PREÇO'!$B$4:$F$100,5,0))*CAPA!$B$14,"") -> 8533.0382 | J13: =I13*0.9 -> 7679.7344

Sheet BASE DE DADOS PREÇOS
C1: Imagem | D1: Item/Module | F1: Nome | G1: Acabamento | H1: Preco Unitario (Real) | S1: PREÇO PRÉ AJUSTES | T1: PREÇO SEM OVER | U1: REAJUSTE 7% | V1: OVER 16,63 | W1: OVER 5,26 PARA NEGOCIAÇÕES
E2: =F2&G2 -> BRIDGE BUFFET 2.0X0.55X0.8 - Acabamentos CustomizadosTampo: Espelho Bronze, Fume, Prata, Vidro Fosco ou Clear Corpo: Laca ou Lamina | F2: BRIDGE BUFFET 2.0X0.55X0.8 - Acabamentos Customizados | G2: Tampo: Espelho Bronze, Fume, Prata, Vidro Fosco ou Clear Corpo: Laca ou Lamina | H2: 10201.078 | N2: 8594.8055 | P2: #N/A | S2: 8134.2732 | T2: =IF(S2,S2*(1-0.05)) -> 7727.5595 | U2: =IF(T2,T2/(1-0.07)) -> 8309.2038 | V2: =U2*1.1663 -> 9691.0244 | W2: =V2*1.05263157894 -> 10201.078
E3: =F3&G3 -> BRIDGE BUFFET 2.0X0.55X0.8 - Acabamentos CustomizadosTampo: Laca ou Lamina com ou sem Vidro Normal Pintado Corpo: Laca ou Lamina | F3: BRIDGE BUFFET 2.0X0.55X0.8 - Acabamentos Customizados | G3: Tampo: Laca ou Lamina com ou sem Vidro Normal Pintado Corpo: Laca ou Lamina | H3: 8543.1718 | N3: 9912.0891 | P3: #N/A | S3: 6812.2693 | T3: =IF(S3,S3*(1-0.05)) -> 6471.6559 | U3: =IF(T3,T3/(1-0.07)) -> 6958.7698 | V3: =U3*1.1663 -> 8116.0132 | W3: =V3*1.05263157894 -> 8543.1718
E4: =F4&G4 -> BRIDGE BUFFET 2.0X0.55X0.8 - Acabamentos CustomizadosTampo: Mármore ou Porcelana Especial Corpo: Laca ou Lamina | F4: BRIDGE BUFFET 2.0X0.55X0.8 - Acabamentos Customizados | G4: Tampo: Mármore ou Porcelana Especial Corpo: Laca ou Lamina | H4: 14649.577 | N4: 15023.58 | P4: #N/A | S4: 11681.477 | T4: =IF(S4,S4*(1-0.05)) -> 11097.403 | U4: =IF(T4,T4/(1-0.07)) -> 11932.692 | V4: =U4*1.1663 -> 13917.099 | W4: =V4*1.05263157894 -> 14649.577
E5: =F5&G5 -> BRIDGE BUFFET 2.2X0.55X0.8 - Acabamentos CustomizadosTampo: Espelho Bronze, Fume, Prata, Vidro Fosco ou Clear Corpo: Laca ou Lamina | F5: BRIDGE BUFFET 2.2X0.55X0.8 - Acabamentos Customizados | G5: Tampo: Espelho Bronze, Fume, Prata, Vidro Fosco ou Clear Corpo: Laca ou Lamina | H5: 10460.36 | S5: 8341.023 | T5: =IF(S5,S5*(1-0.05)) -> 7923.9719 | U5: =IF(T5,T5/(1-0.07)) -> 8520.3998 | V5: =U5*1.1663 -> 9937.3423 | W5: =V5*1.05263157894 -> 10460.36
E6: =F6&G6 -> BRIDGE BUFFET 2.2X0.55X0.8 - Acabamentos CustomizadosTampo: Laca ou Lamina com ou sem Vidro Normal Pintado Corpo: Laca ou Lamina | F6: BRIDGE BUFFET 2.2X0.55X0.8 - Acabamentos Customizados | G6: Tampo: Laca ou Lamina com ou sem Vidro Normal Pintado Corpo: Laca ou Lamina | H6: 9070.2133 | S6: 7232.5288 | T6: =IF(S6,S6*(1-0.05)) -> 6870.9024 | U6: =IF(T6,T6/(1-0.07)) -> 7388.0671 | V6: =U6*1.1663 -> 8616.7026 | W6: =V6*1.05263157894 -> 9070.2133
E7: =F7&G7 -> BRIDGE BUFFET 2.2X0.55X0.8 - Acabamentos CustomizadosTampo: Mármore ou Porcelana Especial Corpo: Laca ou Lamina | F7: BRIDGE BUFFET 2.2X0.55X0.8 - Acabamentos Customizados | G7: Tampo: Mármore ou Porcelana Especial Corpo: Laca ou Lamina | H7: 15133.922 | S7: 12067.69 | T7: =IF(S7,S7*(1-0.05)) -> 11464.306 | U7: =IF(T7,T7/(1-0.07)) -> 12327.21 | V7: =U7*1.1663 -> 14377.226 | W7: =V7*1.05263157894 -> 15133.922
E8: =F8&G8 -> BRIDGE BUFFET 2.4X0.55X0.8 - Acabamentos CustomizadosTampo: Espelho Bronze, Fume, Prata, Vidro Fosco ou Clear Corpo: Laca ou Lamina | F8: BRIDGE BUFFET 2.4X0.55X0.8 - Acabamentos Customizados | G8: Tampo: Espelho Bronze, Fume, Prata, Vidro Fosco ou Clear Corpo: Laca ou Lamina | H8: 11125.394 | S8: 8871.3164 | T8: =IF(S8,S8*(1-0.05)) -> 8427.7506 | U8: =IF(T8,T8/(1-0.07)) -> 9062.0974 | V8: =U8*1.1663 -> 10569.124 | W8: =V8*1.05263157894 -> 11125.394
E9: =F9&G9 -> BRIDGE BUFFET 2.4X0.55X0.8 - Acabamentos CustomizadosTampo: Laca ou Lamina com ou sem Vidro Normal Pintado Corpo: Laca ou Lamina | F9: BRIDGE BUFFET 2.4X0.55X0.8 - Acabamentos Customizados | G9: Tampo: Laca ou Lamina com ou sem Vidro Normal Pintado Corpo: Laca ou Lamina | H9: 9559.4811 | S9: 7622.6678 | T9: =IF(S9,S9*(1-0.05)) -> 7241.5344 | U9: =IF(T9,T9/(1-0.07)) -> 7786.5961 | V9: =U9*1.1663 -> 9081.5071 | W9: =V9*1.05263157894 -> 9559.4811
E10: =F10&G10 -> BRIDGE BUFFET 2.4X0.55X0.8 - Acabamentos CustomizadosTampo: Mármore ou Porcelana Especial Corpo: Laca ou Lamina | F10: BRIDGE BUFFET 2.4X0.55X0.8 - Acabamentos Customizados | G10: Tampo: Mármore ou Porcelana Especial Corpo: Laca ou Lamina | H10: 16249.816 | S10: 12957.497 | T10: =IF(S10,S10*(1-0.05)) -> 12309.622 | U10: =IF(T10,T10/(1-0.07)) -> 13236.153 | V10: =U10*1.1663 -> 15437.325 | W10: =V10*1.05263157894 -> 16249.816
E11: =F11&G11 -> AERIS BUFFET 2X0.45X0.77 - Acabamentos CustomizadosTampo: Laca ou Lamina com ou sem Vidro Normal Pintado Corpo: Laca ou Lamina | F11: AERIS BUFFET 2X0.45X0.77 - Acabamentos Customizados | G11: Tampo: Laca ou Lamina com ou sem Vidro Normal Pintado Corpo: Laca ou Lamina | H11: 8263.577 | I11: =H11*1.12 -> 9255.2063 | S11: 6589.3223 | T11: =IF(S11,S11*(1-0.05)) -> 6259.8562 | U11: =IF(T11,T11/(1-0.07)) -> 6731.0282 | V11: =U11*1.1663 -> 7850.3982 | W11: =V11*1.05263157894 -> 8263.577
E12: =F12&G12 -> AERIS BUFFET 2X0.45X0.77 - Acabamentos CustomizadosTampo: Espelho Bronze, Fume, Prata, Vidro Fosco ou Clear Corpo: Laca ou Lamina | F12: AERIS BUFFET 2X0.45X0.77 - Acabamentos Customizados | G12: Tampo: Espelho Bronze, Fume, Prata, Vidro Fosco ou Clear Corpo: Laca ou Lamina | H12: 9438.215 | I12: =H12*1.12 -> 10570.801 | S12: 7525.971 | T12: =IF(S12,S12*(1-0.05)) -> 7149.6724 | U12: =IF(T12,T12/(1-0.07)) -> 7687.8198 | V12: =U12*1.1663 -> 8966.3043 | W12: =V12*1.05263157894 -> 9438.215
E13: =F13&G13 -> AERIS BUFFET 2X0.45X0.77 - Acabamentos CustomizadosTampo: Mármore ou Porcelana Especial Corpo: Laca ou Lamina | F13: AERIS BUFFET 2X0.45X0.77 - Acabamentos Customizados | G13: Tampo: Mármore ou Porcelana Especial Corpo: Laca ou Lamina | H13: 15041.713 | I13: =H13*1.07 -> 16094.632 | S13: 11994.163 | T13: =IF(S13,S13*(1-0.05)) -> 11394.455 | U13: =IF(T13,T13/(1-0.07)) -> 12252.102 | V13: =U13*1.1663 -> 14289.627 | W13: =V13*1.05263157894 -> 15041.713
E14: =F14&G14 -> AERIS BUFFET 2.2X0.45X0.77 - Acabamentos CustomizadosTampo: Laca ou Lamina com ou sem Vidro Normal Pintado Corpo: Laca ou Lamina | F14: AERIS BUFFET 2.2X0.45X0.77 - Acabamentos Customizados | G14: Tampo: Laca ou Lamina com ou sem Vidro Normal Pintado Corpo: Laca ou Lamina | H14: 8773.3699 | I14: =H14*1.12 -> 9826.1743 | S14: 6995.8279 | T14: =IF(S14,S14*(1-0.05)) -> 6646.0365 | U14: =IF(T14,T14/(1-0.07)) -> 7146.2758 | V14: =U14*1.1663 -> 8334.7014 | W14: =V14*1.05263157894 -> 8773.3699
E15: =F15&G15 -> AERIS BUFFET 2.2X0.45X0.77 - Acabamentos CustomizadosTampo: Espelho Bronze, Fume, Prata, Vidro Fosco ou Clear Corpo: Laca ou Lamina | F15: AERIS BUFFET 2.2X0.45X0.77 - Acabamentos Customizados | G15: Tampo: Espelho Bronze, Fume, Prata, Vidro Fosco ou Clear Corpo: Laca ou Lamina | H15: 10118.021 | I15: =H15*1.12 -> 11332.184 | S15: 8068.0441 | T15: =IF(S15,S15*(1-0.05)) -> 7664.6419 | U15: =IF(T15,T15/(1-0.07)) -> 8241.5504 | V15: =U15*1.1663 -> 9612.1202 | W15: =V15*1.05263157894 -> 10118.021
E16: =F16&G16 -> AERIS BUFFET 2.2X0.45X0.77 - Acabamentos CustomizadosTampo: Mármore ou Porcelana Especial Corpo: Laca ou Lamina | F16: AERIS BUFFET 2.2X0.45X0.77 - Acabamentos Customizados | G16: Tampo: Mármore ou Porcelana Especial Corpo: Laca ou Lamina | H16: 16278.975 | I16: =H16*1.07 -> 17418.503 | S16: 12980.748 | T16: =IF(S16,S16*(1-0.05)) -> 12331.711 | U16: =IF(T16,T16/(1-0.07)) -> 13259.904 | V16: =U16*1.1663 -> 15465.026 | W16: =V16*1.05263157894 -> 16278.975
E17: =F17&G17 -> AERIS BUFFET 2.4X0.45X0.77 - Acabamentos CustomizadosTampo: Laca ou Lamina com ou sem Vidro Normal Pintado Corpo: Laca ou Lamina | F17: AERIS BUFFET 2.4X0.45X0.77 - Acabamentos Customizados | G17: Tampo: Laca ou Lamina com ou sem Vidro Normal Pintado Corpo: Laca ou Lamina | H17: 9246.6254 | I17: =H17*1.12 -> 10356.22 | S17: 7373.1987 | T17: =IF(S17,S17*(1-0.05)) -> 7004.5387 | U17: =IF(T17,T17/(1-0.07)) -> 7531.7621 | V17: =U17*1.1663 -> 8784.2941 | W17: =V17*1.05263157894 -> 9246.6254
E18: =F18&G18 -> AERIS BUFFET 2.4X0.45X0.77 - Acabamentos CustomizadosTampo: Espelho Bronze, Fume, Prata, Vidro Fosco ou Clear Corpo: Laca ou Lamina | F18: AERIS BUFFET 2.4X0.45X0.77 - Acabamentos Customizados | G18: Tampo: Espelho Bronze, Fume, Prata, Vidro Fosco ou Clear Corpo: Laca ou Lamina | H18: 10761.29 | I18: =H18*1.12 -> 12052.645 | S18: 8580.9825 | T18: =IF(S18,S18*(1-0.05)) -> 8151.9333 | U18: =IF(T18,T18/(1-0.07)) -> 8765.5197 | V18: =U18*1.1663 -> 10223.226 | W18: =V18*1.05263157894 -> 10761.29
E19: =F19&G19 -> AERIS BUFFET 2.4X0.45X0.77 - Acabamentos CustomizadosTampo: Mármore ou Porcelana Especial Corpo: Laca ou Lamina | F19: AERIS BUFFET 2.4X0.45X0.77 - Acabamentos Customizados | G19: Tampo: Mármore ou Porcelana Especial Corpo: Laca ou Lamina | H19: 17479.3 | I19: =H19*1.07 -> 18702.851 | S19: 13937.879 | T19: =IF(S19,S19*(1-0.05)) -> 13240.985 | U19: =IF(T19,T19/(1-0.07)) -> 14237.619 | V19: =U19*1.1663 -> 16605.335 | W19: =V19*1.05263157894 -> 17479.3
E20: =F20&G20 -> CHERI BUFFET 1.2X0.5X0.83 - Acabamentos CustomizadosTampo: Espelho Bronze, Fume, Prata, Vidro Fosco ou Clear Corpo: Laca ou Lamina | F20: CHERI BUFFET 1.2X0.5X0.83 - Acabamentos Customizados | G20: Tampo: Espelho Bronze, Fume, Prata, Vidro Fosco ou Clear Corpo: Laca ou Lamina | H20: 8711.6429 | N20: 6551.1532 | P20: 6066.6269 | S20: 6946.6071 | T20: =IF(S20,S20*(1-0.05)) -> 6599.2768 | U20: =IF(T20,T20/(1-0.07)) -> 7095.9965 | V20: =U20*1.1663 -> 8276.0608 | W20: =V20*1.05263157894 -> 8711.6429
E21: =F21&G21 -> CHERI BUFFET 1.2X0.5X0.83 - Acabamentos CustomizadosTampo: Laca ou Lamina com ou sem Vidro Normal Pintado Corpo: Laca ou Lamina | F21: CHERI BUFFET 1.2X0.5X0.83 - Acabamentos Customizados | G21: Tampo: Laca ou Lamina com ou sem Vidro Normal Pintado Corpo: Laca ou Lamina | H21: 7710.7246 | N21: 7633.9995 | P21: 5568.4802 | S21: 6148.4814 | T21: =IF(S21,S21*(1-0.05)) -> 5841.0573 | U21: =IF(T21,T21/(1-0.07)) -> 6280.7068 | V21: =U21*1.1663 -> 7325.1883 | W21: =V21*1.05263157894 -> 7710.7246
E22: =F22&G22 -> CHERI BUFFET 1.2X0.5X0.83 - Acabamentos CustomizadosTampo: Mármore ou Porcelana Especial Corpo: Laca ou Lamina | F22: CHERI BUFFET 1.2X0.5X0.83 - Acabamentos Customizados | G22: Tampo: Mármore ou Porcelana Especial Corpo: Laca ou Lamina | H22: 10874.987 | S22: 8671.6436 | T22: =IF(S22,S22*(1-0.05)) -> 8238.0614 | U22: =IF(T22,T22/(1-0.07)) -> 8858.1305 | V22: =U22*1.1663 -> 10331.238 | W22: =V22*1.05263157894 -> 10874.987
E23: =F23&G23 -> CHERI BUFFET 1.6X0.5X0.83 - Acabamentos CustomizadosTampo: Espelho Bronze, Fume, Prata, Vidro Fosco ou Clear Corpo: Laca ou Lamina | F23: CHERI BUFFET 1.6X0.5X0.83 - Acabamentos Customizados | G23: Tampo: Espelho Bronze, Fume, Prata, Vidro Fosco ou Clear Corpo: Laca ou Lamina | H23: 10270.179 | S23: 8189.3736 | T23: =IF(S23,S23*(1-0.05)) -> 7779.9049 | U23: =IF(T23,T23/(1-0.07)) -> 8365.4892 | V23: =U23*1.1663 -> 9756.67 | W23: =V23*1.05263157894 -> 10270.179
E24: =F24&G24 -> CHERI BUFFET 1.6X0.5X0.83 - Acabamentos CustomizadosTampo: Laca ou Lamina com ou sem Vidro Normal Pintado Corpo: Laca ou Lamina | F24: CHERI BUFFET 1.6X0.5X0.83 - Acabamentos Customizados | G24: Tampo: Laca ou Lamina com ou sem Vidro Normal Pintado Corpo: Laca ou Lamina | H24: 8486.0576 | S24: 6766.7269 | T24: =IF(S24,S24*(1-0.05)) -> 6428.3906 | U24: =IF(T24,T24/(1-0.07)) -> 6912.2479 | V24: =U24*1.1663 -> 8061.7547 | W24: =V24*1.05263157894 -> 8486.0576
E25: =F25&G25 -> CHERI BUFFET 1.6X0.5X0.83 - Acabamentos CustomizadosTampo: Mármore ou Porcelana Especial Corpo: Laca ou Lamina | F25: CHERI BUFFET 1.6X0.5X0.83 - Acabamentos Customizados | G25: Tampo: Mármore ou Porcelana Especial Corpo: Laca ou Lamina | H25: 13326.504 | N25: 8525.2327 | P25: #N/A | S25: 10626.467 | T25: =IF(S25,S25*(1-0.05)) -> 10095.144 | U25: =IF(T25,T25/(1-0.07)) -> 10854.993 | V25: =U25*1.1663 -> 12660.179 | W25: =V25*1.05263157894 -> 13326.504
E26: =F26&G26 -> CHERI BUFFET 1.8X0.5X0.83 - Acabamentos CustomizadosTampo: Espelho Bronze, Fume, Prata, Vidro Fosco ou Clear Corpo: Laca ou Lamina | F26: CHERI BUFFET 1.8X0.5X0.83 - Acabamentos Customizados | G26: Tampo: Espelho Bronze, Fume, Prata, Vidro Fosco ou Clear Corpo: Laca ou Lamina | H26: 10810.715 | N26: 7137.2082 | P26: #N/A | S26: 8620.3933 | T26: =IF(S26,S26*(1-0.05)) -> 8189.3736 | U26: =IF(T26,T26/(1-0.07)) -> 8805.7781 | V26: =U26*1.1663 -> 10270.179 | W26: =V26*1.05263157894 -> 10810.715
E27: =F27&G27 -> CHERI BUFFET 1.8X0.5X0.83 - Acabamentos CustomizadosTampo: Laca ou Lamina com ou sem Vidro Normal Pintado Corpo: Laca ou Lamina | F27: CHERI BUFFET 1.8X0.5X0.83 - Acabamentos Customizados | G27: Tampo: Laca ou Lamina com ou sem Vidro Normal Pintado Corpo: Laca ou Lamina | H27: 8932.6922 | N27: 8414.0737 | P27: #N/A | S27: 7122.8704 | T27: =IF(S27,S27*(1-0.05)) -> 6766.7269 | U27: =IF(T27,T27/(1-0.07)) -> 7276.0504 | V27: =U27*1.1663 -> 8486.0576 | W27: =V27*1.05263157894 -> 8932.6922
E28: =F28&G28 -> CHERI BUFFET 1.8X0.5X0.83 - Acabamentos CustomizadosTampo: Mármore ou Porcelana Especial Corpo: Laca ou Lamina | F28: CHERI BUFFET 1.8X0.5X0.83 - Acabamentos Customizados | G28: Tampo: Mármore ou Porcelana Especial Corpo: Laca ou Lamina | H28: 14027.899 | N28: 9500.3255 | P28: #N/A | S28: 11185.755 | T28: =IF(S28,S28*(1-0.05)) -> 10626.467 | U28: =IF(T28,T28/(1-0.07)) -> 11426.309 | V28: =U28*1.1663 -> 13326.504 | W28: =V28*1.05263157894 -> 14027.899
E29: =F29&G29 -> CHERI BUFFET 2.0X0.5X0.83 - Acabamentos CustomizadosTampo: Espelho Bronze, Fume, Prata, Vidro Fosco ou Clear Corpo: Laca ou Lamina | F29: CHERI BUFFET 2.0X0.5X0.83 - Acabamentos Customizados | G29: Tampo: Espelho Bronze, Fume, Prata, Vidro Fosco ou Clear Corpo: Laca ou Lamina | H29: 11379.7 | N29: 9503.5479 | P29: #N/A | S29: 9074.0982 | T29: =IF(S29,S29*(1-0.05)) -> 8620.3933 | U29: =IF(T29,T29/(1-0.07)) -> 9269.2401 | V29: =U29*1.1663 -> 10810.715 | W29: =V29*1.05263157894 -> 11379.7
E30: =F30&G30 -> CHERI BUFFET 2.0X0.5X0.83 - Acabamentos CustomizadosTampo: Laca ou Lamina com ou sem Vidro Normal Pintado Corpo: Laca ou Lamina | F30: CHERI BUFFET 2.0X0.5X0.83 - Acabamentos Customizados | G30: Tampo: Laca ou Lamina com ou sem Vidro Normal Pintado Corpo: Laca ou Lamina | H30: 9476.7646 | N30: 11645.905 | P30: #N/A | S30: 7556.7102 | T30: =IF(S30,S30*(1-0.05)) -> 7178.8747 | U30: =IF(T30,T30/(1-0.07)) -> 7719.2201 | V30: =U30*1.1663 -> 9002.9264 | W30: =V30*1.05263157894 -> 9476.7646
E31: =F31&G31 -> CHERI BUFFET 2.0X0.5X0.83 - Acabamentos CustomizadosTampo: Mármore ou Porcelana Especial Corpo: Laca ou Lamina | F31: CHERI BUFFET 2.0X0.5X0.83 - Acabamentos Customizados | G31: Tampo: Mármore ou Porcelana Especial Corpo: Laca ou Lamina | H31: 14927.515 | N31: 13588.556 | P31: #N/A | S31: 11903.103 | T31: =IF(S31,S31*(1-0.05)) -> 11307.948 | U31: =IF(T31,T31/(1-0.07)) -> 12159.084 | V31: =U31*1.1663 -> 14181.139 | W31: =V31*1.05263157894 -> 14927.515
E32: =F32&G32 -> CHERI BUFFET 2.2X0.5X0.83 - Acabamentos CustomizadosTampo: Espelho Bronze, Fume, Prata, Vidro Fosco ou Clear Corpo: Laca ou Lamina | F32: CHERI BUFFET 2.2X0.5X0.83 - Acabamentos Customizados | G32: Tampo: Espelho Bronze, Fume, Prata, Vidro Fosco ou Clear Corpo: Laca ou Lamina | H32: 11711.285 | S32: 9338.502 | T32: =IF(S32,S32*(1-0.05)) -> 8871.5769 | U32: =IF(T32,T32/(1-0.07)) -> 9539.33 | V32: =U32*1.1663 -> 11125.721 | W32: =V32*1.05263157894 -> 11711.285
E33: =F33&G33 -> CHERI BUFFET 2.2X0.5X0.83 - Acabamentos CustomizadosTampo: Laca ou Lamina com ou sem Vidro Normal Pintado Corpo: Laca ou Lamina | F33: CHERI BUFFET 2.2X0.5X0.83 - Acabamentos Customizados | G33: Tampo: Laca ou Lamina com ou sem Vidro Normal Pintado Corpo: Laca ou Lamina | H33: 10307.887 | S33: 8219.4418 | T33: =IF(S33,S33*(1-0.05)) -> 7808.4697 | U33: =IF(T33,T33/(1-0.07)) -> 8396.204 | V33: =U33*1.1663 -> 9792.4927 | W33: =V33*1.05263157894 -> 10307.887
E34: =F34&G34 -> CHERI BUFFET 2.2X0.5X0.83 - Acabamentos CustomizadosTampo: Mármore ou Porcelana Especial Corpo: Laca ou Lamina | F34: CHERI BUFFET 2.2X0.5X0.83 - Acabamentos Customizados | G34: Tampo: Mármore ou Porcelana Especial Corpo: Laca ou Lamina | H34: 16386.479 | S34: 13066.472 | T34: =IF(S34,S34*(1-0.05)) -> 12413.148 | U34: =IF(T34,T34/(1-0.07)) -> 13347.471 | V34: =U34*1.1663 -> 15567.155 | W34: =V34*1.05263157894 -> 16386.479
E35: =F35&G35 -> CHERI BUFFET 2.4X0.5X0.83 - Acabamentos CustomizadosTampo: Espelho Bronze, Fume, Prata, Vidro Fosco ou Clear Corpo: Laca ou Lamina | F35: CHERI BUFFET 2.4X0.5X0.83 - Acabamentos Customizados | G35: Tampo: Espelho Bronze, Fume, Prata, Vidro Fosco ou Clear Corpo: Laca ou Lamina | H35: 12514.428 | S35: 9978.9231 | T35: =IF(S35,S35*(1-0.05)) -> 9479.9769 | U35: =IF(T35,T35/(1-0.07)) -> 10193.524 | V35: =U35*1.1663 -> 11888.707 | W35: =V35*1.05263157894 -> 12514.428
E36: =F36&G36 -> CHERI BUFFET 2.4X0.5X0.83 - Acabamentos CustomizadosTampo: Laca ou Lamina com ou sem Vidro Normal Pintado Corpo: Laca ou Lamina | F36: CHERI BUFFET 2.4X0.5X0.83 - Acabamentos Customizados | G36: Tampo: Laca ou Lamina com ou sem Vidro Normal Pintado Corpo: Laca ou Lamina | H36: 10927.274 | S36: 8713.3365 | T36: =IF(S36,S36*(1-0.05)) -> 8277.6697 | U36: =IF(T36,T36/(1-0.07)) -> 8900.7201 | V36: =U36*1.1663 -> 10380.91 | W36: =V36*1.05263157894 -> 10927.274
E37: =F37&G37 -> CHERI BUFFET 2.4X0.5X0.83 - Acabamentos CustomizadosTampo: Mármore ou Porcelana Especial Corpo: Laca ou Lamina | F37: CHERI BUFFET 2.4X0.5X0.83 - Acabamentos Customizados | G37: Tampo: Mármore ou Porcelana Especial Corpo: Laca ou Lamina | H37: 17634.757 | S37: 14061.84 | T37: =IF(S37,S37*(1-0.05)) -> 13358.748 | U37: =IF(T37,T37/(1-0.07)) -> 14364.245 | V37: =U37*1.1663 -> 16753.019 | W37: =V37*1.05263157894 -> 17634.757
E38: =F38&G38 -> YOKO BUFFET 1.2X0.55X0.755 - Acabamentos CustomizadosTampo: Espelho Bronze, Fume, Prata, Vidro Fosco ou Clear Corpo: Laca ou Lamina | F38: YOKO BUFFET 1.2X0.55X0.755 - Acabamentos Customizados | G38: Tampo: Espelho Bronze, Fume, Prata, Vidro Fosco ou Clear Corpo: Laca ou Lamina | H38: 7703.4635 | N38: 5361.8429 | P38: #N/A | S38: 6142.6915 | T38: =IF(S38,S38*(1-0.05)) -> 5835.5569 | U38: =IF(T38,T38/(1-0.07)) -> 6274.7924 | V38: =U38*1.1663 -> 7318.2904 | W38: =V38*1.05263157894 -> 7703.4635
E39: =F39&G39 -> YOKO BUFFET 1.2X0.55X0.755 - Acabamentos CustomizadosTampo: Laca ou Lamina com ou sem Vidro Normal Pintado Corpo: Laca ou Lamina | F39: YOKO BUFFET 1.2X0.55X0.755 - Acabamentos Customizados | G39: Tampo: Laca ou Lamina com ou sem Vidro Normal Pintado Corpo: Laca ou Lamina | H39: 6687.229 | N39: 6128.6622 | P39: #N/A | S39: 5332.3527 | T39: =IF(S39,S39*(1-0.05)) -> 5065.7351 | U39: =IF(T39,T39/(1-0.07)) -> 5447.027 | V39: =U39*1.1663 -> 6352.8676 | W39: =V39*1.05263157894 -> 6687.229
E40: =F40&G40 -> YOKO BUFFET 1.2X0.55X0.755 - Acabamentos CustomizadosTampo: Mármore ou Porcelana Especial Corpo: Laca ou Lamina | F40: YOKO BUFFET 1.2X0.55X0.755 - Acabamentos Customizados | G40: Tampo: Mármore ou Porcelana Especial Corpo: Laca ou Lamina | H40: 10038.514 | N40: 7019.8954 | P40: #N/A | S40: 8004.6458 | T40: =IF(S40,S40*(1-0.05)) -> 7604.4135 | U40: =IF(T40,T40/(1-0.07)) -> 8176.7887 | V40: =U40*1.1663 -> 9536.5887 | W40: =V40*1.05263157894 -> 10038.514
E41: =F41&G41 -> YOKO BUFFET 1.6X0.55X0.755 - Acabamentos CustomizadosTampo: Espelho Bronze, Fume, Prata, Vidro Fosco ou Clear Corpo: Laca ou Lamina | F41: YOKO BUFFET 1.6X0.55X0.755 - Acabamentos Customizados | G41: Tampo: Espelho Bronze, Fume, Prata, Vidro Fosco ou Clear Corpo: Laca ou Lamina | H41: 8285.0932 | N41: 5947.8978 | P41: #N/A | S41: 6606.4792 | T41: =IF(S41,S41*(1-0.05)) -> 6276.1552 | U41: =IF(T41,T41/(1-0.07)) -> 6748.554 | V41: =U41*1.1663 -> 7870.8385 | W41: =V41*1.05263157894 -> 8285.0932
E42: =F42&G42 -> YOKO BUFFET 1.6X0.55X0.755 - Acabamentos CustomizadosTampo: Laca ou Lamina com ou sem Vidro Normal Pintado Corpo: Laca ou Lamina | F42: YOKO BUFFET 1.6X0.55X0.755 - Acabamentos Customizados | G42: Tampo: Laca ou Lamina com ou sem Vidro Normal Pintado Corpo: Laca ou Lamina | H42: 7349.6128 | N42: 6908.7364 | P42: #N/A | S42: 5860.5332 | T42: =IF(S42,S42*(1-0.05)) -> 5567.5066 | U42: =IF(T42,T42/(1-0.07)) -> 5986.5662 | V42: =U42*1.1663 -> 6982.1322 | W42: =V42*1.05263157894 -> 7349.6128
E43: =F43&G43 -> YOKO BUFFET 1.6X0.55X0.755 - Acabamentos CustomizadosTampo: Mármore ou Porcelana Especial Corpo: Laca ou Lamina | F43: YOKO BUFFET 1.6X0.55X0.755 - Acabamentos Customizados | G43: Tampo: Mármore ou Porcelana Especial Corpo: Laca ou Lamina | H43: 11756.863 | N43: 7994.9882 | P43: #N/A | S43: 9374.846 | T43: =IF(S43,S43*(1-0.05)) -> 8906.1037 | U43: =IF(T43,T43/(1-0.07)) -> 9576.4556 | V43: =U43*1.1663 -> 11169.02 | W43: =V43*1.05263157894 -> 11756.863
E44: =F44&G44 -> YOKO BUFFET 2.0X0.55X0.755 - Acabamentos CustomizadosTampo: Espelho Bronze, Fume, Prata, Vidro Fosco ou Clear Corpo: Laca ou Lamina | F44: YOKO BUFFET 2.0X0.55X0.755 - Acabamentos Customizados | G44: Tampo: Espelho Bronze, Fume, Prata, Vidro Fosco ou Clear Corpo: Laca ou Lamina | H44: 9204.2379 | N44: 8370.8714 | P44: #N/A | S44: 7339.3992 | T44: =IF(S44,S44*(1-0.05)) -> 6972.4292 | U44: =IF(T44,T44/(1-0.07)) -> 7497.2357 | V44: =U44*1.1663 -> 8744.026 | W44: =V44*1.05263157894 -> 9204.2379
E45: =F45&G45 -> YOKO BUFFET 2.0X0.55X0.755 - Acabamentos CustomizadosTampo: Laca ou Lamina com ou sem Vidro Normal Pintado Corpo: Laca ou Lamina | F45: YOKO BUFFET 2.0X0.55X0.755 - Acabamentos Customizados | G45: Tampo: Laca ou Lamina com ou sem Vidro Normal Pintado Corpo: Laca ou Lamina | H45: 8081.6614 | N45: 10212.251 | P45: #N/A | S45: 6444.264 | T45: =IF(S45,S45*(1-0.05)) -> 6122.0508 | U45: =IF(T45,T45/(1-0.07)) -> 6582.8503 | V45: =U45*1.1663 -> 7677.5783 | W45: =V45*1.05263157894 -> 8081.6614
E46: =F46&G46 -> YOKO BUFFET 2.0X0.55X0.755 - Acabamentos CustomizadosTampo: Mármore ou Porcelana Especial Corpo: Laca ou Lamina | F46: YOKO BUFFET 2.0X0.55X0.755 - Acabamentos Customizados | G46: Tampo: Mármore ou Porcelana Especial Corpo: Laca ou Lamina | H46: 13410.286 | S46: 10693.275 | T46: =IF(S46,S46*(1-0.05)) -> 10158.611 | U46: =IF(T46,T46/(1-0.07)) -> 10923.238 | V46: =U46*1.1663 -> 12739.772 | W46: =V46*1.05263157894 -> 13410.286
E47: =F47&G47 -> YOKO BUFFET 2.2X0.55X0.755 - Acabamentos CustomizadosTampo: Espelho Bronze, Fume, Prata, Vidro Fosco ou Clear Corpo: Laca ou Lamina | F47: YOKO BUFFET 2.2X0.55X0.755 - Acabamentos Customizados | G47: Tampo: Espelho Bronze, Fume, Prata, Vidro Fosco ou Clear Corpo: Laca ou Lamina | H47: 9629.2503 | S47: 7678.3013 | T47: =IF(S47,S47*(1-0.05)) -> 7294.3862 | U47: =IF(T47,T47/(1-0.07)) -> 7843.426 | V47: =U47*1.1663 -> 9147.7878 | W47: =V47*1.05263157894 -> 9629.2503
E48: =F48&G48 -> YOKO BUFFET 2.2X0.55X0.755 - Acabamentos CustomizadosTampo: Laca ou Lamina com ou sem Vidro Normal Pintado Corpo: Laca ou Lamina | F48: YOKO BUFFET 2.2X0.55X0.755 - Acabamentos Customizados | G48: Tampo: Laca ou Lamina com ou sem Vidro Normal Pintado Corpo: Laca ou Lamina | H48: 8459.8998 | S48: 6745.8688 | T48: =IF(S48,S48*(1-0.05)) -> 6408.5754 | U48: =IF(T48,T48/(1-0.07)) -> 6890.9413 | V48: =U48*1.1663 -> 8036.9048 | W48: =V48*1.05263157894 -> 8459.8998
E49: =F49&G49 -> YOKO BUFFET 2.2X0.55X0.755 - Acabamentos CustomizadosTampo: Mármore ou Porcelana Especial Corpo: Laca ou Lamina | F49: YOKO BUFFET 2.2X0.55X0.755 - Acabamentos Customizados | G49: Tampo: Mármore ou Porcelana Especial Corpo: Laca ou Lamina | H49: 14128.658 | S49: 11266.099 | T49: =IF(S49,S49*(1-0.05)) -> 10702.794 | U49: =IF(T49,T49/(1-0.07)) -> 11508.381 | V49: =U49*1.1663 -> 13422.225 | W49: =V49*1.05263157894 -> 14128.658
E50: =F50&G50 -> YOKO BUFFET 2.4X0.55X0.755 - Acabamentos CustomizadosTampo: Espelho Bronze, Fume, Prata, Vidro Fosco ou Clear Corpo: Laca ou Lamina | F50: YOKO BUFFET 2.4X0.55X0.755 - Acabamentos Customizados | G50: Tampo: Espelho Bronze, Fume, Prata, Vidro Fosco ou Clear Corpo: Laca ou Lamina | H50: 10611.505 | S50: 8461.5445 | T50: =IF(S50,S50*(1-0.05)) -> 8038.4673 | U50: =IF(T50,T50/(1-0.07)) -> 8643.5132 | V50: =U50*1.1663 -> 10080.929 | W50: =V50*1.05263157894 -> 10611.505
E51: =F51&G51 -> YOKO BUFFET 2.4X0.55X0.755 - Acabamentos CustomizadosTampo: Laca ou Lamina com ou sem Vidro Normal Pintado Corpo: Laca ou Lamina | F51: YOKO BUFFET 2.4X0.55X0.755 - Acabamentos Customizados | G51: Tampo: Laca ou Lamina com ou sem Vidro Normal Pintado Corpo: Laca ou Lamina | H51: 9074.6441 | S51: 7236.0619 | T51: =IF(S51,S51*(1-0.05)) -> 6874.2588 | U51: =IF(T51,T51/(1-0.07)) -> 7391.6761 | V51: =U51*1.1663 -> 8620.9119 | W51: =V51*1.05263157894 -> 9074.6441
E52: =F52&G52 -> YOKO BUFFET 2.4X0.55X0.755 - Acabamentos CustomizadosTampo: Mármore ou Porcelana Especial Corpo: Laca ou Lamina | F52: YOKO BUFFET 2.4X0.55X0.755 - Acabamentos Customizados | G52: Tampo: Mármore ou Porcelana Especial Corpo: Laca ou Lamina | H52: 14631.102 | N52: 12154.902 | P52: #N/A | S52: 11666.745 | T52: =IF(S52,S52*(1-0.05)) -> 11083.408 | U52: =IF(T52,T52/(1-0.07)) -> 11917.643 | V52: =U52*1.1663 -> 13899.547 | W52: =V52*1.05263157894 -> 14631.102
E53: =F53&G53 -> YOKO BUFFET 2.7X0.55X0.755 - Acabamentos CustomizadosTampo: Espelho Bronze, Fume, Prata, Vidro Fosco ou Clear Corpo: Laca ou Lamina | F53: YOKO BUFFET 2.7X0.55X0.755 - Acabamentos Customizados | G53: Tampo: Espelho Bronze, Fume, Prata, Vidro Fosco ou Clear Corpo: Laca ou Lamina | H53: 10784.593 | S53: 8599.5636 | T53: =IF(S53,S53*(1-0.05)) -> 8169.5855 | U53: =IF(T53,T53/(1-0.07)) -> 8784.5005 | V53: =U53*1.1663 -> 10245.363 | W53: =V53*1.05263157894 -> 10784.593
E54: =F54&G54 -> YOKO BUFFET 2.7X0.55X0.755 - Acabamentos CustomizadosTampo: Laca ou Lamina com ou sem Vidro Normal Pintado Corpo: Laca ou Lamina | F54: YOKO BUFFET 2.7X0.55X0.755 - Acabamentos Customizados | G54: Tampo: Laca ou Lamina com ou sem Vidro Normal Pintado Corpo: Laca ou Lamina | H54: 10082.938 | S54: 8040.0688 | T54: =IF(S54,S54*(1-0.05)) -> 7638.0653 | U54: =IF(T54,T54/(1-0.07)) -> 8212.9735 | V54: =U54*1.1663 -> 9578.791 | W54: =V54*1.05263157894 -> 10082.938
E55: =F55&G55 -> YOKO BUFFET 2.7X0.55X0.755 - Acabamentos CustomizadosTampo: Mármore ou Porcelana Especial Corpo: Laca ou Lamina | F55: YOKO BUFFET 2.7X0.55X0.755 - Acabamentos Customizados | G55: Tampo: Mármore ou Porcelana Especial Corpo: Laca ou Lamina | H55: 16256.78 | S55: 12963.05 | T55: =IF(S55,S55*(1-0.05)) -> 12314.898 | U55: =IF(T55,T55/(1-0.07)) -> 13241.825 | V55: =U55*1.1663 -> 15443.941 | W55: =V55*1.05263157894 -> 16256.78
E56: =F56&G56 -> TAOS BUFFET 2.0X0.52X0.83 - Acabamentos CustomizadosTampo: Espelho Bronze, Fume, Prata, Vidro Fosco ou Clear Corpo: Laca ou Lamina | F56: TAOS BUFFET 2.0X0.52X0.83 - Acabamentos Customizados | G56: Tampo: Espelho Bronze, Fume, Prata, Vidro Fosco ou Clear Corpo: Laca ou Lamina | H56: 10788.561 | N56: 8829.2374 | P56: #N/A | S56: 8602.7284 | T56: =IF(S56,S56*(1-0.05)) -> 8172.592 | U56: =IF(T56,T56/(1-0.07)) -> 8787.7333 | V56: =U56*1.1663 -> 10249.133 | W56: =V56*1.05263157894 -> 10788.561
E57: =F57&G57 -> TAOS BUFFET 2.0X0.52X0.83 - Acabamentos CustomizadosTampo: Laca ou Lamina com ou sem Vidro Normal Pintado Corpo: Laca ou Lamina | F57: TAOS BUFFET 2.0X0.52X0.83 - Acabamentos Customizados | G57: Tampo: Laca ou Lamina com ou sem Vidro Normal Pintado Corpo: Laca ou Lamina | H57: 9317.6124 | N57: 9486.4559 | P57: #N/A | S57: 7429.8032 | T57: =IF(S57,S57*(1-0.05)) -> 7058.3131 | U57: =IF(T57,T57/(1-0.07)) -> 7589.584 | V57: =U57*1.1663 -> 8851.7318 | W57: =V57*1.05263157894 -> 9317.6124
E58: =F58&G58 -> TAOS BUFFET 2.0X0.52X0.83 - Acabamentos CustomizadosTampo: Mármore ou Porcelana Especial Corpo: Laca ou Lamina | F58: TAOS BUFFET 2.0X0.52X0.83 - Acabamentos Customizados | G58: Tampo: Mármore ou Porcelana Especial Corpo: Laca ou Lamina | H58: 15257.147 | N58: 10147.504 | P58: #N/A | S58: 12165.95 | T58: =IF(S58,S58*(1-0.05)) -> 11557.652 | U58: =IF(T58,T58/(1-0.07)) -> 12427.583 | V58: =U58*1.1663 -> 14494.29 | W58: =V58*1.05263157894 -> 15257.147
E59: =F59&G59 -> TAOS BUFFET 2.2X0.52X0.83 - Acabamentos CustomizadosTampo: Espelho Bronze, Fume, Prata, Vidro Fosco ou Clear Corpo: Laca ou Lamina | F59: TAOS BUFFET 2.2X0.52X0.83 - Acabamentos Customizados | G59: Tampo: Espelho Bronze, Fume, Prata, Vidro Fosco ou Clear Corpo: Laca ou Lamina | H59: 11289.48 | N59: 10040.533 | P59: #N/A | S59: 9002.1577 | T59: =IF(S59,S59*(1-0.05)) -> 8552.0498 | U59: =IF(T59,T59/(1-0.07)) -> 9195.7525 | V59: =U59*1.1663 -> 10725.006 | W59: =V59*1.05263157894 -> 11289.48
E60: =F60&G60 -> TAOS BUFFET 2.2X0.52X0.83 - Acabamentos CustomizadosTampo: Laca ou Lamina com ou sem Vidro Normal Pintado Corpo: Laca ou Lamina | F60: TAOS BUFFET 2.2X0.52X0.83 - Acabamentos Customizados | G60: Tampo: Laca ou Lamina com ou sem Vidro Normal Pintado Corpo: Laca ou Lamina | H60: 10011.184 | N60: 10697.751 | P60: #N/A | S60: 7982.8527 | T60: =IF(S60,S60*(1-0.05)) -> 7583.71 | U60: =IF(T60,T60/(1-0.07)) -> 8154.5269 | V60: =U60*1.1663 -> 9510.6247 | W60: =V60*1.05263157894 -> 10011.184
E61: =F61&G61 -> TAOS BUFFET 2.2X0.52X0.83 - Acabamentos CustomizadosTampo: Mármore ou Porcelana Especial Corpo: Laca ou Lamina | F61: TAOS BUFFET 2.2X0.52X0.83 - Acabamentos Customizados | G61: Tampo: Mármore ou Porcelana Especial Corpo: Laca ou Lamina | H61: 15887.667 | N61: 11525.353 | P61: #N/A | S61: 12668.722 | T61: =IF(S61,S61*(1-0.05)) -> 12035.286 | U61: =IF(T61,T61/(1-0.07)) -> 12941.167 | V61: =U61*1.1663 -> 15093.284 | W61: =V61*1.05263157894 -> 15887.667
E62: =F62&G62 -> TAOS BUFFET 2.4X0.52X0.83 - Acabamentos CustomizadosTampo: Espelho Bronze, Fume, Prata, Vidro Fosco ou Clear Corpo: Laca ou Lamina | F62: TAOS BUFFET 2.4X0.52X0.83 - Acabamentos Customizados | G62: Tampo: Espelho Bronze, Fume, Prata, Vidro Fosco ou Clear Corpo: Laca ou Lamina | H62: 11831.145 | N62: 15145.907 | P62: #N/A | S62: 9434.0776 | T62: =IF(S62,S62*(1-0.05)) -> 8962.3737 | U62: =IF(T62,T62/(1-0.07)) -> 9636.9609 | V62: =U62*1.1663 -> 11239.588 | W62: =V62*1.05263157894 -> 11831.145
E63: =F63&G63 -> TAOS BUFFET 2.4X0.52X0.83 - Acabamentos CustomizadosTampo: Laca ou Lamina com ou sem Vidro Normal Pintado Corpo: Laca ou Lamina | F63: TAOS BUFFET 2.4X0.52X0.83 - Acabamentos Customizados | G63: Tampo: Laca ou Lamina com ou sem Vidro Normal Pintado Corpo: Laca ou Lamina | H63: 10416.739 | N63: 15771.829 | P63: #N/A | S63: 8306.2397 | T63: =IF(S63,S63*(1-0.05)) -> 7890.9277 | U63: =IF(T63,T63/(1-0.07)) -> 8484.8685 | V63: =U63*1.1663 -> 9895.9022 | W63: =V63*1.05263157894 -> 10416.739
E64: =F64&G64 -> TAOS BUFFET 2.4X0.52X0.83 - Acabamentos CustomizadosTampo: Mármore ou Porcelana Especial Corpo: Laca ou Lamina | F64: TAOS BUFFET 2.4X0.52X0.83 - Acabamentos Customizados | G64: Tampo: Mármore ou Porcelana Especial Corpo: Laca ou Lamina | H64: 16701.739 | N64: 17067.612 | P64: #N/A | S64: 13317.857 | T64: =IF(S64,S64*(1-0.05)) -> 12651.964 | U64: =IF(T64,T64/(1-0.07)) -> 13604.263 | V64: =U64*1.1663 -> 15866.652 | W64: =V64*1.05263157894 -> 16701.739
E65: =F65&G65 -> DUO CAR BAR 1.42x0.54x0.638 - Acabamentos CustomizadosTampo: Laca ou Verniz com ou sem Vidro Normal Pintado Corpo: Laca ou Verniz | F65: DUO CAR BAR 1.42x0.54x0.638 - Acabamentos Customizados | G65: Tampo: Laca ou Verniz com ou sem Vidro Normal Pintado Corpo: Laca ou Verniz | H65: 6616.7175 | N65: 6896.8984 | P65: #N/A | S65: 5276.1273 | T65: =IF(S65,S65*(1-0.05)) -> 5012.3209 | U65: =IF(T65,T65/(1-0.07)) -> 5389.5924 | V65: =U65*1.1663 -> 6285.8816 | W65: =V65*1.05263157894 -> 6616.7175
E66: =F66&G66 -> DUO CAR BAR 1.42x0.54x0.638 - Acabamentos CustomizadosTampo: Espelho Bronze, Fume, Prata, Vidro Fosco ou Clear Corpo: Laca ou Verniz | F66: DUO CAR BAR 1.42x0.54x0.638 - Acabamentos Customizados | G66: Tampo: Espelho Bronze, Fume, Prata, Vidro Fosco ou Clear Corpo: Laca ou Verniz | H66: 7476.3025 | N66: 7792.882 | P66: #N/A | S66: 5961.5547 | T66: =IF(S66,S66*(1-0.05)) -> 5663.477 | U66: =IF(T66,T66/(1-0.07)) -> 6089.7602 | V66: =U66*1.1663 -> 7102.4873 | W66: =V66*1.05263157894 -> 7476.3025
E67: =F67&G67 -> DUO CAR BAR 1.42x0.54x0.638 - Acabamentos CustomizadosTampo:Porcelana Corpo: Laca ou Verniz | F67: DUO CAR BAR 1.42x0.54x0.638 - Acabamentos Customizados | G67: Tampo:Porcelana Corpo: Laca ou Verniz | H67: 13610.803 | N67: 12768.43 | P67: #N/A | S67: 10853.165 | T67: =IF(S67,S67*(1-0.05)) -> 10310.507 | U67: =IF(T67,T67/(1-0.07)) -> 11086.567 | V67: =U67*1.1663 -> 12930.263 | W67: =V67*1.05263157894 -> 13610.803
E68: =F68&G68 -> DUO CAR BAR 1.44x0.68x0.65 - Acabamentos CustomizadosTampo: Laca ou Verniz com ou sem Vidro Normal Pintado Corpo: Laca ou Verniz | F68: DUO CAR BAR 1.44x0.68x0.65 - Acabamentos Customizados | G68: Tampo: Laca ou Verniz com ou sem Vidro Normal Pintado Corpo: Laca ou Verniz | H68: 6947.5533 | S68: 5539.9336 | T68: =IF(S68,S68*(1-0.05)) -> 5262.9369 | U68: =IF(T68,T68/(1-0.07)) -> 5659.072 | V68: =U68*1.1663 -> 6600.1757 | W68: =V68*1.05263157894 -> 6947.5533
E69: =F69&G69 -> DUO CAR BAR 1.44x0.68x0.65 - Acabamentos CustomizadosTampo: Espelho Bronze, Fume, Prata, Vidro Fosco ou Clear Corpo: Laca ou Verniz | F69: DUO CAR BAR 1.44x0.68x0.65 - Acabamentos Customizados | G69: Tampo: Espelho Bronze, Fume, Prata, Vidro Fosco ou Clear Corpo: Laca ou Verniz | H69: 7850.1176 | S69: 6259.6325 | T69: =IF(S69,S69*(1-0.05)) -> 5946.6508 | U69: =IF(T69,T69/(1-0.07)) -> 6394.2482 | V69: =U69*1.1663 -> 7457.6117 | W69: =V69*1.05263157894 -> 7850.1176
E70: =F70&G70 -> DUO CAR BAR 1.44x0.68x0.65 - Acabamentos CustomizadosTampo:Porcelana Corpo: Laca ou Verniz | F70: DUO CAR BAR 1.44x0.68x0.65 - Acabamentos Customizados | G70: Tampo:Porcelana Corpo: Laca ou Verniz | H70: 14291.343 | S70: 11395.823 | T70: =IF(S70,S70*(1-0.05)) -> 10826.032 | U70: =IF(T70,T70/(1-0.07)) -> 11640.895 | V70: =U70*1.1663 -> 13576.776 | W70: =V70*1.05263157894 -> 14291.343
B71: X | D71: Edge Console - Bronze/Grey Mirror - 63x20x30 - Custom Finishes | E71: =F71&G71 -> Edge Aparador - 1.6x0.5x0.75 - Acabamentos CustomizadosTampo: Espelho Bronze, Fume, Prata, Vidro Fosco ou Clear Corpo: Laca ou Lamina | F71: Edge Aparador - 1.6x0.5x0.75 - Acabamentos Customizados | G71: Tampo: Espelho Bronze, Fume, Prata, Vidro Fosco ou Clear Corpo: Laca ou Lamina | H71: 5940.1369 | M71: SEM | N71: 5262.9181 | P71: 5262.9181 | S71: 4736.6263 | T71: =IF(S71,S71*(1-0.05)) -> 4499.795 | U71: =IF(T71,T71/(1-0.07)) -> 4838.4892 | V71: =U71*1.1663 -> 5643.13 | W71: =V71*1.05263157894 -> 5940.1369
B72: X | D72: Edge Console - Bronze/Grey Mirror - 71x20x30 - Custom Finishes | E72: =F72&G72 -> Edge Aparador - 1.8x0.5x0.75 - Acabamentos CustomizadosTampo: Espelho Bronze, Fume, Prata, Vidro Fosco ou Clear Corpo: Laca ou Lamina | F72: Edge Aparador - 1.8x0.5x0.75 - Acabamentos Customizados | G72: Tampo: Espelho Bronze, Fume, Prata, Vidro Fosco ou Clear Corpo: Laca ou Lamina | H72: 6410.646 | N72: 5679.7858 | P72: 5679.7858 | S72: 5111.8073 | T72: =IF(S72,S72*(1-0.05)) -> 4856.2169 | U72: =IF(T72,T72/(1-0.07)) -> 5221.7386 | V72: =U72*1.1663 -> 6090.1137 | W72: =V72*1.05263157894 -> 6410.646
B73: X | D73: Edge Console - Bronze/Grey Mirror - 79x20x30 - Custom Finishes | E73: =F73&G73 -> Edge Aparador - 2.00x0.5x0.75 - Acabamentos CustomizadosTampo: Espelho Bronze, Fume, Prata, Vidro Fosco ou Clear Corpo: Laca ou Lamina | F73: Edge Aparador - 2.00x0.5x0.75 - Acabamentos Customizados | G73: Tampo: Espelho Bronze, Fume, Prata, Vidro Fosco ou Clear Corpo: Laca ou Lamina | H73: 6884.1215 | N73: 6099.2816 | P73: 6099.2816 | S73: 5489.3535 | T73: =IF(S73,S73*(1-0.05)) -> 5214.8858 | U73: =IF(T73,T73/(1-0.07)) -> 5607.4041 | V73: =U73*1.1663 -> 6539.9154 | W73: =V73*1.05263157894 -> 6884.1215
B74: X | D74: Edge Console - Marble - 63x20x30 - Custom Finishes | E74: =F74&G74 -> Edge Aparador - 1.6x0.5x0.75 - Acabamentos CustomizadosTampo: Mármore Especial Corpo: Laca ou Lamina | F74: Edge Aparador - 1.6x0.5x0.75 - Acabamentos Customizados | G74: Tampo: Mármore Especial Corpo: Laca ou Lamina | H74: 9177.9628 | N74: 7318.4475 | P74: #N/A | S74: 7318.4475 | T74: =IF(S74,S74*(1-0.05)) -> 6952.5252 | U74: =IF(T74,T74/(1-0.07)) -> 7475.8335 | V74: =U74*1.1663 -> 8719.0646 | W74: =V74*1.05263157894 -> 9177.9628
B75: X | D75: Edge Console - Marble - 71x20x30 - Custom Finishes | E75: =F75&G75 -> Edge Aparador - 1.8x0.5x0.75 - Acabamentos CustomizadosTampo: Mármore Especial Corpo: Laca ou Lamina | F75: Edge Aparador - 1.8x0.5x0.75 - Acabamentos Customizados | G75: Tampo: Mármore Especial Corpo: Laca ou Lamina | H75: 10022.977 | N75: 7992.2564 | P75: #N/A | S75: 7992.2564 | T75: =IF(S75,S75*(1-0.05)) -> 7592.6436 | U75: =IF(T75,T75/(1-0.07)) -> 8164.1329 | V75: =U75*1.1663 -> 9521.8282 | W75: =V75*1.05263157894 -> 10022.977
B76: X | D76: Edge Console - Marble - 79x20x30 - Custom Finishes | E76: =F76&G76 -> Edge Aparador - 2.00x0.5x0.75 - Acabamentos CustomizadosTampo: Mármore Especial Corpo: Laca ou Lamina | F76: Edge Aparador - 2.00x0.5x0.75 - Acabamentos Customizados | G76: Tampo: Mármore Especial Corpo: Laca ou Lamina | H76: 10871.287 | N76: 8668.6934 | P76: #N/A | S76: 8668.6934 | T76: =IF(S76,S76*(1-0.05)) -> 8235.2587 | U76: =IF(T76,T76/(1-0.07)) -> 8855.1169 | V76: =U76*1.1663 -> 10327.723 | W76: =V76*1.05263157894 -> 10871.287
B77: X | D77: Edge Console - Painted Glass Top - 63x20x30 - Custom Finishes | E77: =F77&G77 -> Edge Aparador - 1.6x0.5x0.75 - Acabamentos CustomizadosTampo: Laca ou Lamina com ou sem Vidro Normal Pintado Corpo: Laca ou Lamina | F77: Edge Aparador - 1.6x0.5x0.75 - Acabamentos Customizados | G77: Tampo: Laca ou Lamina com ou sem Vidro Normal Pintado Corpo: Laca ou Lamina | H77: 5206.1457 | N77: 4381.977 | P77: 4381.977 | S77: 4151.3466 | T77: =IF(S77,S77*(1-0.05)) -> 3943.7793 | U77: =IF(T77,T77/(1-0.07)) -> 4240.6229 | V77: =U77*1.1663 -> 4945.8384 | W77: =V77*1.05263157894 -> 5206.1457
B78: X | D78: Edge Console - Painted Glass Top - 71x20x30 - Custom Finishes | E78: =F78&G78 -> Edge Aparador - 1.8x0.5x0.75 - Acabamentos CustomizadosTampo: Laca ou Lamina com ou sem Vidro Normal Pintado Corpo: Laca ou Lamina | F78: Edge Aparador - 1.8x0.5x0.75 - Acabamentos Customizados | G78: Tampo: Laca ou Lamina com ou sem Vidro Normal Pintado Corpo: Laca ou Lamina | H78: 5570.5898 | N78: 4688.727 | P78: 4688.727 | S78: 4441.9519 | T78: =IF(S78,S78*(1-0.05)) -> 4219.8543 | U78: =IF(T78,T78/(1-0.07)) -> 4537.4778 | V78: =U78*1.1663 -> 5292.0603 | W78: =V78*1.05263157894 -> 5570.5898
B79: X | D79: Edge Console - Painted Glass Top - 79x20x30 - Custom Finishes | E79: =F79&G79 -> Edge Aparador - 2.00x0.5x0.75 - Acabamentos CustomizadosTampo: Laca ou Lamina com ou sem Vidro Normal Pintado Corpo: Laca ou Lamina | F79: Edge Aparador - 2.00x0.5x0.75 - Acabamentos Customizados | G79: Tampo: Laca ou Lamina com ou sem Vidro Normal Pintado Corpo: Laca ou Lamina | H79: 5938.1562 | N79: 4998.1052 | P79: 4998.1052 | S79: 4735.047 | T79: =IF(S79,S79*(1-0.05)) -> 4498.2946 | U79: =IF(T79,T79/(1-0.07)) -> 4836.876 | V79: =U79*1.1663 -> 5641.2484 | W79: =V79*1.05263157894 -> 5938.1562
E80: =F80&G80 -> Docc Aparador - 1.4x0.52x0.76 - Acabamentos CustomizadosTampo: Laca ou Lamina com ou sem Vidro Normal Pintado Corpo: Laca ou Lamina | F80: Docc Aparador - 1.4x0.52x0.76 - Acabamentos Customizados | G80: Tampo: Laca ou Lamina com ou sem Vidro Normal Pintado Corpo: Laca ou Lamina | H80: 5520.3502 | S80: 4401.8912 | T80: =IF(S80,S80*(1-0.05)) -> 4181.7966 | U80: =IF(T80,T80/(1-0.07)) -> 4496.5555 | V80: =U80*1.1663 -> 5244.3327 | W80: =V80*1.05263157894 -> 5520.3502
E81: =F81&G81 -> Docc Aparador - 1.4x0.52x0.76 - Acabamentos CustomizadosTampo: Espelho Bronze, Fume, Prata, Vidro Fosco ou Clear Corpo: Laca ou Lamina | F81: Docc Aparador - 1.4x0.52x0.76 - Acabamentos Customizados | G81: Tampo: Espelho Bronze, Fume, Prata, Vidro Fosco ou Clear Corpo: Laca ou Lamina | H81: 6389.3559 | S81: 5094.8306 | T81: =IF(S81,S81*(1-0.05)) -> 4840.0891 | U81: =IF(T81,T81/(1-0.07)) -> 5204.3969 | V81: =U81*1.1663 -> 6069.8881 | W81: =V81*1.05263157894 -> 6389.3559
E82: =F82&G82 -> Docc Aparador - 1.4x0.52x0.76 - Acabamentos CustomizadosTampo: Mármore Especial Corpo: Laca ou Lamina | F82: Docc Aparador - 1.4x0.52x0.76 - Acabamentos Customizados | G82: Tampo: Mármore Especial Corpo: Laca ou Lamina | H82: 10032.306 | S82: 7999.6956 | T82: =IF(S82,S82*(1-0.05)) -> 7599.7108 | U82: =IF(T82,T82/(1-0.07)) -> 8171.732 | V82: =U82*1.1663 -> 9530.6911 | W82: =V82*1.05263157894 -> 10032.306
E83: =F83&G83 -> Docc Aparador - 1.6x0.52x0.76 - Acabamentos CustomizadosTampo: Laca ou Lamina com ou sem Vidro Normal Pintado Corpo: Laca ou Lamina | F83: Docc Aparador - 1.6x0.52x0.76 - Acabamentos Customizados | G83: Tampo: Laca ou Lamina com ou sem Vidro Normal Pintado Corpo: Laca ou Lamina | H83: 5935.8604 | S83: 4733.2163 | T83: =IF(S83,S83*(1-0.05)) -> 4496.5555 | U83: =IF(T83,T83/(1-0.07)) -> 4835.0059 | V83: =U83*1.1663 -> 5639.0674 | W83: =V83*1.05263157894 -> 5935.8604
E84: =F84&G84 -> Docc Aparador - 1.6x0.52x0.76 - Acabamentos CustomizadosTampo: Espelho Bronze, Fume, Prata, Vidro Fosco ou Clear Corpo: Laca ou Lamina | F84: Docc Aparador - 1.6x0.52x0.76 - Acabamentos Customizados | G84: Tampo: Espelho Bronze, Fume, Prata, Vidro Fosco ou Clear Corpo: Laca ou Lamina | H84: 6870.2751 | S84: 5478.3125 | T84: =IF(S84,S84*(1-0.05)) -> 5204.3969 | U84: =IF(T84,T84/(1-0.07)) -> 5596.1257 | V84: =U84*1.1663 -> 6526.7614 | W84: =V84*1.05263157894 -> 6870.2751
E85: =F85&G85 -> Docc Aparador - 1.6x0.52x0.76 - Acabamentos CustomizadosTampo: Mármore Especial Corpo: Laca ou Lamina | F85: Docc Aparador - 1.6x0.52x0.76 - Acabamentos Customizados | G85: Tampo: Mármore Especial Corpo: Laca ou Lamina | H85: 10787.426 | S85: 8601.8232 | T85: =IF(S85,S85*(1-0.05)) -> 8171.732 | U85: =IF(T85,T85/(1-0.07)) -> 8786.8086 | V85: =U85*1.1663 -> 10248.055 | W85: =V85*1.05263157894 -> 10787.426
B86: X | D86: Parma Console - Bronze/Grey Mirror - 63x20x31 - Custom Finishes | E86: =F86&G86 -> Parma Aparador - 1.6x0.5x0.75 - Acabamentos CustomizadosTampo: Espelho Bronze, Fume, Prata, Vidro Fosco ou Clear Corpo: Laca ou Lamina | F86: Parma Aparador - 1.6x0.5x0.75 - Acabamentos Customizados | G86: Tampo: Espelho Bronze, Fume, Prata, Vidro Fosco ou Clear Corpo: Laca ou Lamina | H86: 6115.6013 | I86: =H86/0.85 -> 7194.825 | N86: 4976.4768 | P86: 4605.6216 | S86: 4876.5405 | T86: =IF(S86,S86*(1-0.05)) -> 4632.7135 | U86: =IF(T86,T86/(1-0.07)) -> 4981.4123 | V86: =U86*1.1663 -> 5809.8212 | W86: =V86*1.05263157894 -> 6115.6013
B87: X | D87: Parma Console - Marble - 63x20x31 - Custom Finishes | E87: =F87&G87 -> Parma Aparador - 1.6x0.5x0.75 - Acabamentos CustomizadosTampo: Mármore Especial Corpo: Laca ou Lamina | F87: Parma Aparador - 1.6x0.5x0.75 - Acabamentos Customizados | G87: Tampo: Mármore Especial Corpo: Laca ou Lamina | H87: 9359.839 | I87: =H87/1.05 -> 8914.1324 | N87: 4605.6216 | P87: #N/A | S87: 7463.4745 | T87: =IF(S87,S87*(1-0.05)) -> 7090.3008 | U87: =IF(T87,T87/(1-0.07)) -> 7623.9793 | V87: =U87*1.1663 -> 8891.8471 | W87: =V87*1.05263157894 -> 9359.839
B88: X | D88: Parma Console - Painted Glass Top - 63x20x31 - Custom Finishes | E88: =F88&G88 -> Parma Aparador - 1.6x0.5x0.75 - Acabamentos CustomizadosTampo: Laca ou Lamina com ou sem Vidro Normal Pintado Corpo: Laca ou Lamina | F88: Parma Aparador - 1.6x0.5x0.75 - Acabamentos Customizados | G88: Tampo: Laca ou Lamina com ou sem Vidro Normal Pintado Corpo: Laca ou Lamina | H88: 5206.1457 | I88: =H88/0.85 -> 6124.8773 | N88: 5349.5659 | P88: 3724.6804 | S88: 4151.3466 | T88: =IF(S88,S88*(1-0.05)) -> 3943.7793 | U88: =IF(T88,T88/(1-0.07)) -> 4240.6229 | V88: =U88*1.1663 -> 4945.8384 | W88: =V88*1.05263157894 -> 5206.1457
B89: X | D89: Parma Console - Bronze/Grey Mirror - 71x20x31 - Custom Finishes | E89: =F89&G89 -> Parma Aparador - 1.8x0.5x0.75 - Acabamentos CustomizadosTampo: Espelho Bronze, Fume, Prata, Vidro Fosco ou Clear Corpo: Laca ou Lamina | F89: Parma Aparador - 1.8x0.5x0.75 - Acabamentos Customizados | G89: Tampo: Espelho Bronze, Fume, Prata, Vidro Fosco ou Clear Corpo: Laca ou Lamina | H89: 6799.329 | I89: =H89/0.95 -> 7157.1884 | J89: =I89*1.05 -> 7515.0478 | N89: 6661.151 | P89: 4976.4768 | S89: 5421.7405 | T89: =IF(S89,S89*(1-0.05)) -> 5150.6535 | U89: =IF(T89,T89/(1-0.07)) -> 5538.3371 | V89: =U89*1.1663 -> 6459.3625 | W89: =V89*1.05263157894 -> 6799.329
B90: X | D90: Parma Console - Marble - 71x20x31 - Custom Finishes | E90: =F90&G90 -> Parma Aparador - 1.8x0.5x0.75 - Acabamentos CustomizadosTampo: Mármore Especial Corpo: Laca ou Lamina | F90: Parma Aparador - 1.8x0.5x0.75 - Acabamentos Customizados | G90: Tampo: Mármore Especial Corpo: Laca ou Lamina | H90: 9958.843 | I90: =H90/0.95 -> 10482.993 | J90: =I90*1.05 -> 11007.142 | N90: 7918.9776 | P90: #N/A | S90: 7941.1163 | T90: =IF(S90,S90*(1-0.05)) -> 7544.0605 | U90: =IF(T90,T90/(1-0.07)) -> 8111.893 | V90: =U90*1.1663 -> 9460.9009 | W90: =V90*1.05263157894 -> 9958.843
B91: X | D91: Parma Console - Painted Glass Top - 71x20x31 - Custom Finishes | E91: =F91&G91 -> Parma Aparador - 1.8x0.5x0.75 - Acabamentos CustomizadosTampo: Laca ou Lamina com ou sem Vidro Normal Pintado Corpo: Laca ou Lamina | F91: Parma Aparador - 1.8x0.5x0.75 - Acabamentos Customizados | G91: Tampo: Laca ou Lamina com ou sem Vidro Normal Pintado Corpo: Laca ou Lamina | H91: 5731.8437 | I91: =H91/0.95 -> 6033.5197 | J91: =I91*1.05 -> 6335.1957 | N91: 7288.9474 | P91: 3985.418 | S91: 4570.5347 | T91: =IF(S91,S91*(1-0.05)) -> 4342.008 | U91: =IF(T91,T91/(1-0.07)) -> 4668.8258 | V91: =U91*1.1663 -> 5445.2515 | W91: =V91*1.05263157894 -> 5731.8437
B92: X | D92: Parma Console - Bronze/Grey Mirror - 79x20x31 - Custom Finishes | E92: =F92&G92 -> Parma Aparador - 2x0.5x0.75 - Acabamentos CustomizadosTampo: Espelho Bronze, Fume, Prata, Vidro Fosco ou Clear Corpo: Laca ou Lamina | F92: Parma Aparador - 2x0.5x0.75 - Acabamentos Customizados | G92: Tampo: Espelho Bronze, Fume, Prata, Vidro Fosco ou Clear Corpo: Laca ou Lamina | H92: 7103.452 | I92: =H92/0.85 -> 8357.0023 | N92: 3985.418 | P92: 5349.5659 | S92: 5664.2462 | T92: =IF(S92,S92*(1-0.05)) -> 5381.0339 | U92: =IF(T92,T92/(1-0.07)) -> 5786.0579 | V92: =U92*1.1663 -> 6748.2794 | W92: =V92*1.05263157894 -> 7103.452
B93: X | D93: Parma Console - Marble - 79x20x31 - Custom Finishes | E93: =F93&G93 -> Parma Aparador - 2x0.5x0.75 - Acabamentos CustomizadosTampo: Mármore Especial Corpo: Laca ou Lamina | F93: Parma Aparador - 2x0.5x0.75 - Acabamentos Customizados | G93: Tampo: Mármore Especial Corpo: Laca ou Lamina | H93: 11415.033 | I93: =H93/0.87 -> 13120.728 | N93: 3724.6804 | P93: #N/A | S93: 9102.2731 | T93: =IF(S93,S93*(1-0.05)) -> 8647.1595 | U93: =IF(T93,T93/(1-0.07)) -> 9298.0209 | V93: =U93*1.1663 -> 10844.282 | W93: =V93*1.05263157894 -> 11415.033
B94: X | D94: Parma Console - Painted Glass Top - 79x20x31 - Custom Finishes | E94: =F94&G94 -> Parma Aparador - 2x0.5x0.75 - Acabamentos CustomizadosTampo: Laca ou Lamina com ou sem Vidro Normal Pintado Corpo: Laca ou Lamina | F94: Parma Aparador - 2x0.5x0.75 - Acabamentos Customizados | G94: Tampo: Laca ou Lamina com ou sem Vidro Normal Pintado Corpo: Laca ou Lamina | H94: 5938.1562 | I94: =H94/0.85 -> 6986.0662 | N94: 4248.3894 | P94: 4248.3894 | S94: 4735.047 | T94: =IF(S94,S94*(1-0.05)) -> 4498.2946 | U94: =IF(T94,T94/(1-0.07)) -> 4836.876 | V94: =U94*1.1663 -> 5641.2484 | W94: =V94*1.05263157894 -> 5938.1562
E95: =F95&G95 -> Sienna Aparador - 1.4x0.45x0.75 - Acabamentos CustomizadosTampo: Laca ou Lamina com ou sem Vidro Normal Pintado Corpo: Laca ou Lamina | F95: Sienna Aparador - 1.4x0.45x0.75 - Acabamentos Customizados | G95: Tampo: Laca ou Lamina com ou sem Vidro Normal Pintado Corpo: Laca ou Lamina | H95: 3079.6867 | I95: =H95/0.9 -> 3421.8741 | S95: 2455.7221 | T95: =IF(S95,S95*(1-0.05)) -> 2332.936 | U95: =IF(T95,T95/(1-0.07)) -> 2508.5333 | V95: =U95*1.1663 -> 2925.7024 | W95: =V95*1.05263157894 -> 3079.6867
E96: =F96&G96 -> Sienna Aparador - 1.4x0.45x0.75 - Acabamentos CustomizadosTampo: Espelho Bronze, Fume, Prata, Vidro Fosco ou Clear Corpo: Laca ou Lamina | F96: Sienna Aparador - 1.4x0.45x0.75 - Acabamentos Customizados | G96: Tampo: Espelho Bronze, Fume, Prata, Vidro Fosco ou Clear Corpo: Laca ou Lamina | H96: 3795.7135 | I96: =H96/0.9 -> 4217.4594 | S96: 3026.6771 | T96: =IF(S96,S96*(1-0.05)) -> 2875.3433 | U96: =IF(T96,T96/(1-0.07)) -> 3091.767 | V96: =U96*1.1663 -> 3605.9278 | W96: =V96*1.05263157894 -> 3795.7135
E97: =F97&G97 -> Sienna Aparador - 1.4x0.45x0.75 - Acabamentos CustomizadosTampo: Mármore Especial Corpo: Laca ou Lamina | F97: Sienna Aparador - 1.4x0.45x0.75 - Acabamentos Customizados | G97: Tampo: Mármore Especial Corpo: Laca ou Lamina | H97: 6473.0438 | I97: =H97/0.9 -> 7192.2709 | S97: 5161.5628 | T97: =IF(S97,S97*(1-0.05)) -> 4903.4847 | U97: =IF(T97,T97/(1-0.07)) -> 5272.5642 | V97: =U97*1.1663 -> 6149.3916 | W97: =V97*1.05263157894 -> 6473.0438
E98: =F98&G98 -> Sienna Aparador - 2.2x0.45x0.75 - Acabamentos CustomizadosTampo: Laca ou Lamina com ou sem Vidro Normal Pintado Corpo: Laca ou Lamina | F98: Sienna Aparador - 2.2x0.45x0.75 - Acabamentos Customizados | G98: Tampo: Laca ou Lamina com ou sem Vidro Normal Pintado Corpo: Laca ou Lamina | H98: 4839.5077 | I98: =H98/0.9 -> 5377.2308 | S98: 3858.9918 | T98: =IF(S98,S98*(1-0.05)) -> 3666.0422 | U98: =IF(T98,T98/(1-0.07)) -> 3941.9809 | V98: =U98*1.1663 -> 4597.5323 | W98: =V98*1.05263157894 -> 4839.5077
E99: =F99&G99 -> Sienna Aparador - 2.2x0.45x0.75 - Acabamentos CustomizadosTampo: Espelho Bronze, Fume, Prata, Vidro Fosco ou Clear Corpo: Laca ou Lamina | F99: Sienna Aparador - 2.2x0.45x0.75 - Acabamentos Customizados | G99: Tampo: Espelho Bronze, Fume, Prata, Vidro Fosco ou Clear Corpo: Laca ou Lamina | H99: 5964.6926 | I99: =H99/0.9 -> 6627.4362 | S99: 4756.2069 | T99: =IF(S99,S99*(1-0.05)) -> 4518.3966 | U99: =IF(T99,T99/(1-0.07)) -> 4858.4909 | V99: =U99*1.1663 -> 5666.458 | W99: =V99*1.05263157894 -> 5964.6926
E100: =F100&G100 -> Sienna Aparador - 2.2x0.45x0.75 - Acabamentos CustomizadosTampo: Mármore Especial Corpo: Laca ou Lamina | F100: Sienna Aparador - 2.2x0.45x0.75 - Acabamentos Customizados | G100: Tampo: Mármore Especial Corpo: Laca ou Lamina | H100: 10171.926 | I100: =H100/0.9 -> 11302.14 | S100: 8111.0273 | T100: =IF(S100,S100*(1-0.05)) -> 7705.4759 | U100: =IF(T100,T100/(1-0.07)) -> 8285.458 | V100: =U100*1.1663 -> 9663.3297 | W100: =V100*1.05263157894 -> 10171.926
...

Sheet ESPELHO
B1: TABELA DE PREÇO CENTURY | MADEIRA
C5: Dimensoes (metros)
A6: Imagem | B6: Nome | C6: C | D6: L | E6: A | F6: Laca ou Lamina - Espelho Prata | G6: Laca ou Lamina - Espelho Bronze ou Fume | H6: Recoro - Espelho Prata | I6: Recoro - Espelho Bronze ou Fume
B7: Avant Espelho 1.84X0.1X1.91 - Acabamentos Customizados | C7: 1.84 | D7: 0.1 | E7: 1.91 | F7: =IFERROR(IF('BASE DE DADOS PREÇOS'!$M$71="com",VLOOKUP(CONCATENATE(B7,$F$6),'BASE DE DADOS PREÇOS'!$E:$H,4,0)/(1-SUM($G$1))*VLOOKUP(CAPA!$B$12,'POLITICA DE PREÇO'!#REF!,2,0)*0.95,VLOOKUP(CONCATENATE(B7,$F$6),'BASE DE DADOS PREÇOS'!$E:$H,4,0)/(1-SUM($G$1))*VLOOKUP(CAPA!$B$12,'POLITICA DE PREÇO'!$B$4:$F$100,5,0))*CAPA!$B$14,"") -> 3530.3932 | G7: =IFERROR(IF('BASE DE DADOS PREÇOS'!$M$71="com",VLOOKUP(CONCATENATE(B7,$G$6),'BASE DE DADOS PREÇOS'!$E:$H,4,0)/(1-SUM($G$1))*VLOOKUP(CAPA!$B$12,'POLITICA DE PREÇO'!#REF!,2,0)*0.95,VLOOKUP(CONCATENATE(B7,$G$6),'BASE DE DADOS PREÇOS'!$E:$H,4,0)/(1-SUM($G$1))*VLOOKUP(CAPA!$B$12,'POLITICA DE PREÇO'!$B$4:$F$100,5,0))*CAPA!$B$14,"") -> 6052.1026
B8: Ettore Espelho 2.05X0.14X1.95 - Acabamentos Customizados | C8: 2.05 | D8: 0.14 | E8: 1.95 | F8: =IFERROR(IF('BASE DE DADOS PREÇOS'!$M$71="com",VLOOKUP(CONCATENATE(B8,$F$6),'BASE DE DADOS PREÇOS'!$E:$H,4,0)/(1-SUM($G$1))*VLOOKUP(CAPA!$B$12,'POLITICA DE PREÇO'!#REF!,2,0)*0.95,VLOOKUP(CONCATENATE(B8,$F$6),'BASE DE DADOS PREÇOS'!$E:$H,4,0)/(1-SUM($G$1))*VLOOKUP(CAPA!$B$12,'POLITICA DE PREÇO'!$B$4:$F$100,5,0))*CAPA!$B$14,"") -> 3691.8218 | G8: =IFERROR(IF('BASE DE DADOS PREÇOS'!$M$71="com",VLOOKUP(CONCATENATE(B8,$G$6),'BASE DE DADOS PREÇOS'!$E:$H,4,0)/(1-SUM($G$1))*VLOOKUP(CAPA!$B$12,'POLITICA DE PREÇO'!#REF!,2,0)*0.95,VLOOKUP(CONCATENATE(B8,$G$6),'BASE DE DADOS PREÇOS'!$E:$H,4,0)/(1-SUM($G$1))*VLOOKUP(CAPA!$B$12,'POLITICA DE PREÇO'!$B$4:$F$100,5,0))*CAPA!$B$14,"") -> 6328.8374 | H8: =F8*1.05 -> 3876.4129 | I8: =G8*1.05 -> 6645.2792

Sheet POLITICA DE PREÇO
B2: PRAZO DE PAGAMENTO | C2: PRAZO MÉDIO | D2: DESCONTOS | E2: Coefic. (%) | F2: Coef. Desc
D3: Desc. 1
B4: 15 DIAS - OURO | C4: 15 DIAS | D4: 0.1425 | E4: 0.1425 | F4: =(1-E4) -> 0.8575
B5: 30 DIAS - OURO | C5: 30 DIAS | D5: 0.1325 | E5: 0.1325 | F5: =(1-E5) -> 0.8675
B6: 45 DIAS - OURO | C6: 45 DIAS | D6: 0.12 | E6: 0.12 | F6: =(1-E6) -> 0.88
B7: 60 DIAS - OURO | C7: 60 DIAS | D7: 0.1075 | E7: 0.1075 | F7: =(1-E7) -> 0.8925
B8: 75 DIAS - OURO | C8: 75 DIAS | D8: 0.09 | E8: 0.09 | F8: =(1-E8) -> 0.91
B9: 90 DIAS - OURO | C9: 90 DIAS | D9: 0.0725 | E9: 0.0725 | F9: =(1-E9) -> 0.9275
B10: 105 DIAS - OURO | C10: 105 DIAS | D10: 0.055 | E10: 0.055 | F10: =(1-E10) -> 0.945
B11: 120 DIAS - OURO | C11: 120 DIAS | D11: 0.035 | E11: 0.035 | F11: =(1-E11) -> 0.965
B12: 135 DIAS - OURO | C12: 135 DIAS | D12: 0.01 | E12: 0.01 | F12: =(1-E12) -> 0.99
B13: 150 DIAS - OURO | C13: 150 DIAS | D13: -0.015 | E13: -0.015 | F13: =(1-E13) -> 1.015
B14: 165 DIAS - OURO | C14: 165 DIAS | D14: -0.04 | E14: -0.04 | F14: =(1-E14) -> 1.04
B15: 180 DIAS - OURO | C15: 180 DIAS | D15: -0.0675 | E15: -0.0675 | F15: =(1-E15) -> 1.0675

Sheet MESA DE CABECEIRA
B1: TABELA DE PREÇO CENTURY | MADEIRA
C5: Dimensoes (metros)
A6: Imagem | B6: Nome | C6: C | D6: L | E6: A | G6: Tampo: Espelho Bronze, Fume, Prata, Vidro Fosco ou Clear Corpo: Laca ou Lamina | H6: Tampo: Laca ou Lamina com ou sem Vidro Normal Pintado Corpo: Laca ou Lamina | I6: Tampo: Mármore Especial Corpo: Laca ou Lamina | J6: Tampo: Mármore Normal Corpo: Laca ou Lamina | K6: Tampo ou Base em Recoro
B7: Barcelona Mesa de Cabeceira - Øx0.5x0.530 - Acabamentos Customizados | C7: Ø | D7: 0.5 | E7: 0.53 | G7: =IFERROR(IF('BASE DE DADOS PREÇOS'!$M$71="com",VLOOKUP(CONCATENATE(B7,$G$6),'BASE DE DADOS PREÇOS'!$E:$H,4,0)/(1-SUM($F$1))*VLOOKUP(CAPA!$B$12,'POLITICA DE PREÇO'!#REF!,2,0)*0.95,VLOOKUP(CONCATENATE(B7,$G$6),'BASE DE DADOS PREÇOS'!$E:$H,4,0)/(1-SUM($F$1))*VLOOKUP(CAPA!$B$12,'POLITICA DE PREÇO'!$B$4:$F$100,5,0))*CAPA!$B$14,"") -> 3253.0323 | H7: =IFERROR(IF('BASE DE DADOS PREÇOS'!$M$71="com",VLOOKUP(CONCATENATE(B7,$H$6),'BASE DE DADOS PREÇOS'!$E:$H,4,0)/(1-SUM($F$1))*VLOOKUP(CAPA!$B$12,'POLITICA DE PREÇO'!#REF!,2,0)*0.95,VLOOKUP(CONCATENATE(B7,$H$6),'BASE DE DADOS PREÇOS'!$E:$H,4,0)/(1-SUM($F$1))*VLOOKUP(CAPA!$B$12,'POLITICA DE PREÇO'!$B$4:$F$100,5,0))*CAPA!$B$14,"") -> 3083.3804 | I7: =IFERROR(IF('BASE DE DADOS PREÇOS'!$M$71="com",VLOOKUP(CONCATENATE(B7,$I$6),'BASE DE DADOS PREÇOS'!$E:$H,4,0)/(1-SUM($F$1))*VLOOKUP(CAPA!$B$12,'POLITICA DE PREÇO'!#REF!,2,0)*0.95,VLOOKUP(CONCATENATE(B7,$I$6),'BASE DE DADOS PREÇOS'!$E:$H,4,0)/(1-SUM($F$1))*VLOOKUP(CAPA!$B$12,'POLITICA DE PREÇO'!$B$4:$F$100,5,0))*CAPA!$B$14,"") -> 4087.7868 | J7: =I7*0.9 -> 3679.0081 | K7: =H7*1.05 -> 3237.5495
B8: Cayman Mesa de Cabeceira 0.7X0.45X0.53 - Acabamentos Customizados | C8: 0.7 | D8: 0.45 | E8: 0.53 | G8: =IFERROR(IF('BASE DE DADOS PREÇOS'!$M$71="com",VLOOKUP(CONCATENATE(B8,$G$6),'BASE DE DADOS PREÇOS'!$E:$H,4,0)/(1-SUM($F$1))*VLOOKUP(CAPA!$B$12,'POLITICA DE PREÇO'!#REF!,2,0)*0.95,VLOOKUP(CONCATENATE(B8,$G$6),'BASE DE DADOS PREÇOS'!$E:$H,4,0)/(1-SUM($F$1))*VLOOKUP(CAPA!$B$12,'POLITICA DE PREÇO'!$B$4:$F$100,5,0))*CAPA!$B$14,"") -> 3747.1793 | H8: =IFERROR(IF('BASE DE DADOS PREÇOS'!$M$71="com",VLOOKUP(CONCATENATE(B8,$H$6),'BASE DE DADOS PREÇOS'!$E:$H,4,0)/(1-SUM($F$1))*VLOOKUP(CAPA!$B$12,'POLITICA DE PREÇO'!#REF!,2,0)*0.95,VLOOKUP(CONCATENATE(B8,$H$6),'BASE DE DADOS PREÇOS'!$E:$H,4,0)/(1-SUM($F$1))*VLOOKUP(CAPA!$B$12,'POLITICA DE PREÇO'!$B$4:$F$100,5,0))*CAPA!$B$14,"") -> 3645.1765 | I8: =IFERROR(IF('BASE DE DADOS PREÇOS'!$M$71="com",VLOOKUP(CONCATENATE(B8,$I$6),'BASE DE DADOS PREÇOS'!$E:$H,4,0)/(1-SUM($F$1))*VLOOKUP(CAPA!$B$12,'POLITICA DE PREÇO'!#REF!,2,0)*0.95,VLOOKUP(CONCATENATE(B8,$I$6),'BASE DE DADOS PREÇOS'!$E:$H,4,0)/(1-SUM($F$1))*VLOOKUP(CAPA!$B$12,'POLITICA DE PREÇO'!$B$4:$F$100,5,0))*CAPA!$B$14,"") -> 4821.2372 | J8: =I8*0.9 -> 4339.1135 | K8: =H8*1.05 -> 3827.4353
B9: Cayman Mesa de Cabeceira 0.8X0.45X0.53 - Acabamentos Customizados | C9: 0.8 | D9: 0.45 | E9: 0.53 | G9: =IFERROR(IF('BASE DE DADOS PREÇOS'!$M$71="com",VLOOKUP(CONCATENATE(B9,$G$6),'BASE DE DADOS PREÇOS'!$E:$H,4,0)/(1-SUM($F$1))*VLOOKUP(CAPA!$B$12,'POLITICA DE PREÇO'!#REF!,2,0)*0.95,VLOOKUP(CONCATENATE(B9,$G$6),'BASE DE DADOS PREÇOS'!$E:$H,4,0)/(1-SUM($F$1))*VLOOKUP(CAPA!$B$12,'POLITICA DE PREÇO'!$B$4:$F$100,5,0))*CAPA!$B$14,"") -> 3999.5335 | H9: =IFERROR(IF('BASE DE DADOS PREÇOS'!$M$71="com",VLOOKUP(CONCATENATE(B9,$H$6),'BASE DE DADOS PREÇOS'!$E:$H,4,0)/(1-SUM($F$1))*VLOOKUP(CAPA!$B$12,'POLITICA DE PREÇO'!#REF!,2,0)*0.95,VLOOKUP(CONCATENATE(B9,$H$6),'BASE DE DADOS PREÇOS'!$E:$H,4,0)/(1-SUM($F$1))*VLOOKUP(CAPA!$B$12,'POLITICA DE PREÇO'!$B$4:$F$100,5,0))*CAPA!$B$14,"") -> 3833.642 | I9: =IFERROR(IF('BASE DE DADOS PREÇOS'!$M$71="com",VLOOKUP(CONCATENATE(B9,$I$6),'BASE DE DADOS PREÇOS'!$E:$H,4,0)/(1-SUM($F$1))*VLOOKUP(CAPA!$B$12,'POLITICA DE PREÇO'!#REF!,2,0)*0.95,VLOOKUP(CONCATENATE(B9,$I$6),'BASE DE DADOS PREÇOS'!$E:$H,4,0)/(1-SUM($F$1))*VLOOKUP(CAPA!$B$12,'POLITICA DE PREÇO'!$B$4:$F$100,5,0))*CAPA!$B$14,"") -> 5209.6803 | J9: =I9*0.9 -> 4688.7123 | K9: =H9*1.05 -> 4025.3241
B10: Cayman Mesa de Cabeceira 0.9X0.45X0.53 - Acabamentos Customizados | C10: 0.9 | D10: 0.45 | E10: 0.53 | G10: =IFERROR(IF('BASE DE DADOS PREÇOS'!$M$71="com",VLOOKUP(CONCATENATE(B10,$G$6),'BASE DE DADOS PREÇOS'!$E:$H,4,0)/(1-SUM($F$1))*VLOOKUP(CAPA!$B$12,'POLITICA DE PREÇO'!#REF!,2,0)*0.95,VLOOKUP(CONCATENATE(B10,$G$6),'BASE DE DADOS PREÇOS'!$E:$H,4,0)/(1-SUM($F$1))*VLOOKUP(CAPA!$B$12,'POLITICA DE PREÇO'!$B$4:$F$100,5,0))*CAPA!$B$14,"") -> 4323.2984 | H10: =IFERROR(IF('BASE DE DADOS PREÇOS'!$M$71="com",VLOOKUP(CONCATENATE(B10,$H$6),'BASE DE DADOS PREÇOS'!$E:$H,4,0)/(1-SUM($F$1))*VLOOKUP(CAPA!$B$12,'POLITICA DE PREÇO'!#REF!,2,0)*0.95,VLOOKUP(CONCATENATE(B10,$H$6),'BASE DE DADOS PREÇOS'!$E:$H,4,0)/(1-SUM($F$1))*VLOOKUP(CAPA!$B$12,'POLITICA DE PREÇO'!$B$4:$F$100,5,0))*CAPA!$B$14,"") -> 4045.3673 | I10: =IFERROR(IF('BASE DE DADOS PREÇOS'!$M$71="com",VLOOKUP(CONCATENATE(B10,$I$6),'BASE DE DADOS PREÇOS'!$E:$H,4,0)/(1-SUM($F$1))*VLOOKUP(CAPA!$B$12,'POLITICA DE PREÇO'!#REF!,2,0)*0.95,VLOOKUP(CONCATENATE(B10,$I$6),'BASE DE DADOS PREÇOS'!$E:$H,4,0)/(1-SUM($F$1))*VLOOKUP(CAPA!$B$12,'POLITICA DE PREÇO'!$B$4:$F$100,5,0))*CAPA!$B$14,"") -> 5381.7698 | J10: =I10*0.9 -> 4843.5928 | K10: =H10*1.05 -> 4247.6356
B11: Cayman Mesa de Cabeceira 1X0.45X0.53 - Acabamentos Customizados | C11: 1 | D11: 0.45 | E11: 0.53 | G11: =IFERROR(IF('BASE DE DADOS PREÇOS'!$M$71="com",VLOOKUP(CONCATENATE(B11,$G$6),'BASE DE DADOS PREÇOS'!$E:$H,4,0)/(1-SUM($F$1))*VLOOKUP(CAPA!$B$12,'POLITICA DE PREÇO'!#REF!,2,0)*0.95,VLOOKUP(CONCATENATE(B11,$G$6),'BASE DE DADOS PREÇOS'!$E:$H,4,0)/(1-SUM($F$1))*VLOOKUP(CAPA!$B$12,'POLITICA DE PREÇO'!$B$4:$F$100,5,0))*CAPA!$B$14,"") -> 4598.2763 | H11: =IFERROR(IF('BASE DE DADOS PREÇOS'!$M$71="com",VLOOKUP(CONCATENATE(B11,$H$6),'BASE DE DADOS PREÇOS'!$E:$H,4,0)/(1-SUM($F$1))*VLOOKUP(CAPA!$B$12,'POLITICA DE PREÇO'!#REF!,2,0)*0.95,VLOOKUP(CONCATENATE(B11,$H$6),'BASE DE DADOS PREÇOS'!$E:$H,4,0)/(1-SUM($F$1))*VLOOKUP(CAPA!$B$12,'POLITICA DE PREÇO'!$B$4:$F$100,5,0))*CAPA!$B$14,"") -> 4290.8689 | I11: =IFERROR(IF('BASE DE DADOS PREÇOS'!$M$71="com",VLOOKUP(CONCATENATE(B11,$I$6),'BASE DE DADOS PREÇOS'!$E:$H,4,0)/(1-SUM($F$1))*VLOOKUP(CAPA!$B$12,'POLITICA DE PREÇO'!#REF!,2,0)*0.95,VLOOKUP(CONCATENATE(B11,$I$6),'BASE DE DADOS PREÇOS'!$E:$H,4,0)/(1-SUM($F$1))*VLOOKUP(CAPA!$B$12,'POLITICA DE PREÇO'!$B$4:$F$100,5,0))*CAPA!$B$14,"") -> 6075.1001 | J11: =I11*0.9 -> 5467.5901 | K11: =H11*1.05 -> 4505.4124
B12: Stare Mesa de Cabeceira 0.7X0.45X0.53 - Acabamentos Customizados | C12: 0.7 | D12: 0.45 | E12: 0.53 | G12: =IFERROR(IF('BASE DE DADOS PREÇOS'!$M$71="com",VLOOKUP(CONCATENATE(B12,$G$6),'BASE DE DADOS PREÇOS'!$E:$H,4,0)/(1-SUM($F$1))*VLOOKUP(CAPA!$B$12,'POLITICA DE PREÇO'!#REF!,2,0)*0.95,VLOOKUP(CONCATENATE(B12,$G$6),'BASE DE DADOS PREÇOS'!$E:$H,4,0)/(1-SUM($F$1))*VLOOKUP(CAPA!$B$12,'POLITICA DE PREÇO'!$B$4:$F$100,5,0))*CAPA!$B$14,"") -> 3603.057 | H12: =IFERROR(IF('BASE DE DADOS PREÇOS'!$M$71="com",VLOOKUP(CONCATENATE(B12,$H$6),'BASE DE DADOS PREÇOS'!$E:$H,4,0)/(1-SUM($F$1))*VLOOKUP(CAPA!$B$12,'POLITICA DE PREÇO'!#REF!,2,0)*0.95,VLOOKUP(CONCATENATE(B12,$H$6),'BASE DE DADOS PREÇOS'!$E:$H,4,0)/(1-SUM($F$1))*VLOOKUP(CAPA!$B$12,'POLITICA DE PREÇO'!$B$4:$F$100,5,0))*CAPA!$B$14,"") -> 3504.9774 | I12: =IFERROR(IF('BASE DE DADOS PREÇOS'!$M$71="com",VLOOKUP(CONCATENATE(B12,$I$6),'BASE DE DADOS PREÇOS'!$E:$H,4,0)/(1-SUM($F$1))*VLOOKUP(CAPA!$B$12,'POLITICA DE PREÇO'!#REF!,2,0)*0.95,VLOOKUP(CONCATENATE(B12,$I$6),'BASE DE DADOS PREÇOS'!$E:$H,4,0)/(1-SUM($F$1))*VLOOKUP(CAPA!$B$12,'POLITICA DE PREÇO'!$B$4:$F$100,5,0))*CAPA!$B$14,"") -> 4635.805 | J12: =I12*0.9 -> 4172.2245 | K12: =H12*1.05 -> 3680.2263
B13: Stare Mesa de Cabeceira 0.8X0.45X0.53 - Acabamentos Customizados | C13: 0.8 | D13: 0.45 | E13: 0.53 | G13: =IFERROR(IF('BASE DE DADOS PREÇOS'!$M$71="com",VLOOKUP(CONCATENATE(B13,$G$6),'BASE DE DADOS PREÇOS'!$E:$H,4,0)/(1-SUM($F$1))*VLOOKUP(CAPA!$B$12,'POLITICA DE PREÇO'!#REF!,2,0)*0.95,VLOOKUP(CONCATENATE(B13,$G$6),'BASE DE DADOS PREÇOS'!$E:$H,4,0)/(1-SUM($F$1))*VLOOKUP(CAPA!$B$12,'POLITICA DE PREÇO'!$B$4:$F$100,5,0))*CAPA!$B$14,"") -> 3845.7053 | H13: =IFERROR(IF('BASE DE DADOS PREÇOS'!$M$71="com",VLOOKUP(CONCATENATE(B13,$H$6),'BASE DE DADOS PREÇOS'!$E:$H,4,0)/(1-SUM($F$1))*VLOOKUP(CAPA!$B$12,'POLITICA DE PREÇO'!#REF!,2,0)*0.95,VLOOKUP(CONCATENATE(B13,$H$6),'BASE DE DADOS PREÇOS'!$E:$H,4,0)/(1-SUM($F$1))*VLOOKUP(CAPA!$B$12,'POLITICA DE PREÇO'!$B$4:$F$100,5,0))*CAPA!$B$14,"") -> 3592.4774 | I13: =IFERROR(IF('BASE DE DADOS PREÇOS'!$M$71="com",VLOOKUP(CONCATENATE(B13,$I$6),'BASE DE DADOS PREÇOS'!$E:$H,4,0)/(1-SUM($F$1))*VLOOKUP(CAPA!$B$12,'POLITICA DE PREÇO'!#REF!,2,0)*0.95,VLOOKUP(CONCATENATE(B13,$I$6),'BASE DE DADOS PREÇOS'!$E:$H,4,0)/(1-SUM($F$1))*VLOOKUP(CAPA!$B$12,'POLITICA DE PREÇO'!$B$4:$F$100,5,0))*CAPA!$B$14,"") -> 5009.308 | J13: =I13*0.9 -> 4508.3772 | K13: =H13*1.05 -> 3772.1013
B14: Stare Mesa de Cabeceira 0.9X0.45X0.53 - Acabamentos Customizados | C14: 0.9 | D14: 0.45 | E14: 0.53 | G14: =IFERROR(IF('BASE DE DADOS PREÇOS'!$M$71="com",VLOOKUP(CONCATENATE(B14,$G$6),'BASE DE DADOS PREÇOS'!$E:$H,4,0)/(1-SUM($F$1))*VLOOKUP(CAPA!$B$12,'POLITICA DE PREÇO'!#REF!,2,0)*0.95,VLOOKUP(CONCATENATE(B14,$G$6),'BASE DE DADOS PREÇOS'!$E:$H,4,0)/(1-SUM($F$1))*VLOOKUP(CAPA!$B$12,'POLITICA DE PREÇO'!$B$4:$F$100,5,0))*CAPA!$B$14,"") -> 4157.0177 | H14: =IFERROR(IF('BASE DE DADOS PREÇOS'!$M$71="com",VLOOKUP(CONCATENATE(B14,$H$6),'BASE DE DADOS PREÇOS'!$E:$H,4,0)/(1-SUM($F$1))*VLOOKUP(CAPA!$B$12,'POLITICA DE PREÇO'!#REF!,2,0)*0.95,VLOOKUP(CONCATENATE(B14,$H$6),'BASE DE DADOS PREÇOS'!$E:$H,4,0)/(1-SUM($F$1))*VLOOKUP(CAPA!$B$12,'POLITICA DE PREÇO'!$B$4:$F$100,5,0))*CAPA!$B$14,"") -> 3889.7762 | I14: =IFERROR(IF('BASE DE DADOS PREÇOS'!$M$71="com",VLOOKUP(CONCATENATE(B14,$I$6),'BASE DE DADOS PREÇOS'!$E:$H,4,0)/(1-SUM($F$1))*VLOOKUP(CAPA!$B$12,'POLITICA DE PREÇO'!#REF!,2,0)*0.95,VLOOKUP(CONCATENATE(B14,$I$6),'BASE DE DADOS PREÇOS'!$E:$H,4,0)/(1-SUM($F$1))*VLOOKUP(CAPA!$B$12,'POLITICA DE PREÇO'!$B$4:$F$100,5,0))*CAPA!$B$14,"") -> 5409.9959 | J14: =I14*0.9 -> 4868.9963 | K14: =H14*1.05 -> 4084.265
B15: Stare Mesa de Cabeceira 1X0.45X0.53 - Acabamentos Customizados | C15: 1 | D15: 0.45 | E15: 0.53 | G15: =IFERROR(IF('BASE DE DADOS PREÇOS'!$M$71="com",VLOOKUP(CONCATENATE(B15,$G$6),'BASE DE DADOS PREÇOS'!$E:$H,4,0)/(1-SUM($F$1))*VLOOKUP(CAPA!$B$12,'POLITICA DE PREÇO'!#REF!,2,0)*0.95,VLOOKUP(CONCATENATE(B15,$G$6),'BASE DE DADOS PREÇOS'!$E:$H,4,0)/(1-SUM($F$1))*VLOOKUP(CAPA!$B$12,'POLITICA DE PREÇO'!$B$4:$F$100,5,0))*CAPA!$B$14,"") -> 4421.4195 | H15: =IFERROR(IF('BASE DE DADOS PREÇOS'!$M$71="com",VLOOKUP(CONCATENATE(B15,$H$6),'BASE DE DADOS PREÇOS'!$E:$H,4,0)/(1-SUM($F$1))*VLOOKUP(CAPA!$B$12,'POLITICA DE PREÇO'!#REF!,2,0)*0.95,VLOOKUP(CONCATENATE(B15,$H$6),'BASE DE DADOS PREÇOS'!$E:$H,4,0)/(1-SUM($F$1))*VLOOKUP(CAPA!$B$12,'POLITICA DE PREÇO'!$B$4:$F$100,5,0))*CAPA!$B$14,"") -> 3938.2975 | I15: =IFERROR(IF('BASE DE DADOS PREÇOS'!$M$71="com",VLOOKUP(CONCATENATE(B15,$I$6),'BASE DE DADOS PREÇOS'!$E:$H,4,0)/(1-SUM($F$1))*VLOOKUP(CAPA!$B$12,'POLITICA DE PREÇO'!#REF!,2,0)*0.95,VLOOKUP(CONCATENATE(B15,$I$6),'BASE DE DADOS PREÇOS'!$E:$H,4,0)/(1-SUM($F$1))*VLOOKUP(CAPA!$B$12,'POLITICA DE PREÇO'!$B$4:$F$100,5,0))*CAPA!$B$14,"") -> 5841.4424 | J15: =I15*0.9 -> 5257.2981 | K15: =H15*1.05 -> 4135.2124
B16: Turin Mesa de Cabeceira - 2 Gavetas - 0.6x0.45x0.53 - Acabamentos Customizados | C16: 0.6 | D16: 0.45 | E16: 0.53 | G16: =IFERROR(IF('BASE DE DADOS PREÇOS'!$M$71="com",VLOOKUP(CONCATENATE(B16,$G$6),'BASE DE DADOS PREÇOS'!$E:$H,4,0)/(1-SUM($F$1))*VLOOKUP(CAPA!$B$12,'POLITICA DE PREÇO'!#REF!,2,0)*0.95,VLOOKUP(CONCATENATE(B16,$G$6),'BASE DE DADOS PREÇOS'!$E:$H,4,0)/(1-SUM($F$1))*VLOOKUP(CAPA!$B$12,'POLITICA DE PREÇO'!$B$4:$F$100,5,0))*CAPA!$B$14,"") -> 3237.7186 | H16: =IFERROR(IF('BASE DE DADOS PREÇOS'!$M$71="com",VLOOKUP(CONCATENATE(B16,$H$6),'BASE DE DADOS PREÇOS'!$E:$H,4,0)/(1-SUM($F$1))*VLOOKUP(CAPA!$B$12,'POLITICA DE PREÇO'!#REF!,2,0)*0.95,VLOOKUP(CONCATENATE(B16,$H$6),'BASE DE DADOS PREÇOS'!$E:$H,4,0)/(1-SUM($F$1))*VLOOKUP(CAPA!$B$12,'POLITICA DE PREÇO'!$B$4:$F$100,5,0))*CAPA!$B$14,"") -> 3039.0139 | I16: =IFERROR(IF('BASE DE DADOS PREÇOS'!$M$71="com",VLOOKUP(CONCATENATE(B16,$I$6),'BASE DE DADOS PREÇOS'!$E:$H,4,0)/(1-SUM($F$1))*VLOOKUP(CAPA!$B$12,'POLITICA DE PREÇO'!#REF!,2,0)*0.95,VLOOKUP(CONCATENATE(B16,$I$6),'BASE DE DADOS PREÇOS'!$E:$H,4,0)/(1-SUM($F$1))*VLOOKUP(CAPA!$B$12,'POLITICA DE PREÇO'!$B$4:$F$100,5,0))*CAPA!$B$14,"") -> 4150.0273 | J16: =I16*0.9 -> 3735.0245 | K16: =H16*1.05 -> 3190.9646
B17: Turin Mesa de Cabeceira - 2 Gavetas - 0.7x0.45x0.53 - Acabamentos Customizados | C17: 0.7 | D17: 0.45 | E17: 0.53 | G17: =IFERROR(IF('BASE DE DADOS PREÇOS'!$M$71="com",VLOOKUP(CONCATENATE(B17,$G$6),'BASE DE DADOS PREÇOS'!$E:$H,4,0)/(1-SUM($F$1))*VLOOKUP(CAPA!$B$12,'POLITICA DE PREÇO'!#REF!,2,0)*0.95,VLOOKUP(CONCATENATE(B17,$G$6),'BASE DE DADOS PREÇOS'!$E:$H,4,0)/(1-SUM($F$1))*VLOOKUP(CAPA!$B$12,'POLITICA DE PREÇO'!$B$4:$F$100,5,0))*CAPA!$B$14,"") -> 3561.4905 | H17: =IFERROR(IF('BASE DE DADOS PREÇOS'!$M$71="com",VLOOKUP(CONCATENATE(B17,$H$6),'BASE DE DADOS PREÇOS'!$E:$H,4,0)/(1-SUM($F$1))*VLOOKUP(CAPA!$B$12,'POLITICA DE PREÇO'!#REF!,2,0)*0.95,VLOOKUP(CONCATENATE(B17,$H$6),'BASE DE DADOS PREÇOS'!$E:$H,4,0)/(1-SUM($F$1))*VLOOKUP(CAPA!$B$12,'POLITICA DE PREÇO'!$B$4:$F$100,5,0))*CAPA!$B$14,"") -> 3342.9153 | I17: =IFERROR(IF('BASE DE DADOS PREÇOS'!$M$71="com",VLOOKUP(CONCATENATE(B17,$I$6),'BASE DE DADOS PREÇOS'!$E:$H,4,0)/(1-SUM($F$1))*VLOOKUP(CAPA!$B$12,'POLITICA DE PREÇO'!#REF!,2,0)*0.95,VLOOKUP(CONCATENATE(B17,$I$6),'BASE DE DADOS PREÇOS'!$E:$H,4,0)/(1-SUM($F$1))*VLOOKUP(CAPA!$B$12,'POLITICA DE PREÇO'!$B$4:$F$100,5,0))*CAPA!$B$14,"") -> 4565.03 | J17: =I17*0.9 -> 4108.527 | K17: =H17*1.05 -> 3510.061
B18: Turin Mesa de Cabeceira - 2 Gavetas - 0.8x0.45x0.53 - Acabamentos Customizados | C18: 0.8 | D18: 0.45 | E18: 0.53 | G18: =IFERROR(IF('BASE DE DADOS PREÇOS'!$M$71="com",VLOOKUP(CONCATENATE(B18,$G$6),'BASE DE DADOS PREÇOS'!$E:$H,4,0)/(1-SUM($F$1))*VLOOKUP(CAPA!$B$12,'POLITICA DE PREÇO'!#REF!,2,0)*0.95,VLOOKUP(CONCATENATE(B18,$G$6),'BASE DE DADOS PREÇOS'!$E:$H,4,0)/(1-SUM($F$1))*VLOOKUP(CAPA!$B$12,'POLITICA DE PREÇO'!$B$4:$F$100,5,0))*CAPA!$B$14,"") -> 3748.9374 | H18: =IFERROR(IF('BASE DE DADOS PREÇOS'!$M$71="com",VLOOKUP(CONCATENATE(B18,$H$6),'BASE DE DADOS PREÇOS'!$E:$H,4,0)/(1-SUM($F$1))*VLOOKUP(CAPA!$B$12,'POLITICA DE PREÇO'!#REF!,2,0)*0.95,VLOOKUP(CONCATENATE(B18,$H$6),'BASE DE DADOS PREÇOS'!$E:$H,4,0)/(1-SUM($F$1))*VLOOKUP(CAPA!$B$12,'POLITICA DE PREÇO'!$B$4:$F$100,5,0))*CAPA!$B$14,"") -> 3518.8582 | I18: =IFERROR(IF('BASE DE DADOS PREÇOS'!$M$71="com",VLOOKUP(CONCATENATE(B18,$I$6),'BASE DE DADOS PREÇOS'!$E:$H,4,0)/(1-SUM($F$1))*VLOOKUP(CAPA!$B$12,'POLITICA DE PREÇO'!#REF!,2,0)*0.95,VLOOKUP(CONCATENATE(B18,$I$6),'BASE DE DADOS PREÇOS'!$E:$H,4,0)/(1-SUM($F$1))*VLOOKUP(CAPA!$B$12,'POLITICA DE PREÇO'!$B$4:$F$100,5,0))*CAPA!$B$14,"") -> 4805.2947 | J18: =I18*0.9 -> 4324.7652 | K18: =H18*1.05 -> 3694.8011
B19: Turin Mesa de Cabeceira - 2 Gavetas - 0.9x0.45x0.53 - Acabamentos Customizados | C19: 0.9 | D19: 0.45 | E19: 0.53 | G19: =IFERROR(IF('BASE DE DADOS PREÇOS'!$M$71="com",VLOOKUP(CONCATENATE(B19,$G$6),'BASE DE DADOS PREÇOS'!$E:$H,4,0)/(1-SUM($F$1))*VLOOKUP(CAPA!$B$12,'POLITICA DE PREÇO'!#REF!,2,0)*0.95,VLOOKUP(CONCATENATE(B19,$G$6),'BASE DE DADOS PREÇOS'!$E:$H,4,0)/(1-SUM($F$1))*VLOOKUP(CAPA!$B$12,'POLITICA DE PREÇO'!$B$4:$F$100,5,0))*CAPA!$B$14,"") -> 3946.2499 | H19: =IFERROR(IF('BASE DE DADOS PREÇOS'!$M$71="com",VLOOKUP(CONCATENATE(B19,$H$6),'BASE DE DADOS PREÇOS'!$E:$H,4,0)/(1-SUM($F$1))*VLOOKUP(CAPA!$B$12,'POLITICA DE PREÇO'!#REF!,2,0)*0.95,VLOOKUP(CONCATENATE(B19,$H$6),'BASE DE DADOS PREÇOS'!$E:$H,4,0)/(1-SUM($F$1))*VLOOKUP(CAPA!$B$12,'POLITICA DE PREÇO'!$B$4:$F$100,5,0))*CAPA!$B$14,"") -> 3704.0612 | I19: =IFERROR(IF('BASE DE DADOS PREÇOS'!$M$71="com",VLOOKUP(CONCATENATE(B19,$I$6),'BASE DE DADOS PREÇOS'!$E:$H,4,0)/(1-SUM($F$1))*VLOOKUP(CAPA!$B$12,'POLITICA DE PREÇO'!#REF!,2,0)*0.95,VLOOKUP(CONCATENATE(B19,$I$6),'BASE DE DADOS PREÇOS'!$E:$H,4,0)/(1-SUM($F$1))*VLOOKUP(CAPA!$B$12,'POLITICA DE PREÇO'!$B$4:$F$100,5,0))*CAPA!$B$14,"") -> 5058.205 | J19: =I19*0.9 -> 4552.3845 | K19: =H19*1.05 -> 3889.2643
... B25: Turin Mesa de Cabeceira - 3 Gavetas - 1x0.45x0.6 - Acabamentos Customizados | C25: 1 | D25: 0.45 | E25: 0.6 | G25: =IFERROR(IF('BASE DE DADOS PREÇOS'!$M$71="com",VLOOKUP(CONCATENATE(B25,$G$6),'BASE DE DADOS PREÇOS'!$E:$H,4,0)/(1-SUM($F$1))*VLOOKUP(CAPA!$B$12,'POLITICA DE PREÇO'!#REF!,2,0)*0.95,VLOOKUP(CONCATENATE(B25,$G$6),'BASE DE DADOS PREÇOS'!$E:$H,4,0)/(1-SUM($F$1))*VLOOKUP(CAPA!$B$12,'POLITICA DE PREÇO'!$B$4:$F$100,5,0))*CAPA!$B$14,"") -> 4937.8582 | H25: =IFERROR(IF('BASE DE DADOS PREÇOS'!$M$71="com",VLOOKUP(CONCATENATE(B25,$H$6),'BASE DE DADOS PREÇOS'!$E:$H,4,0)/(1-SUM($F$1))*VLOOKUP(CAPA!$B$12,'POLITICA DE PREÇO'!#REF!,2,0)*0.95,VLOOKUP(CONCATENATE(B25,$H$6),'BASE DE DADOS PREÇOS'!$E:$H,4,0)/(1-SUM($F$1))*VLOOKUP(CAPA!$B$12,'POLITICA DE PREÇO'!$B$4:$F$100,5,0))*CAPA!$B$14,"") -> 4634.8127 | I25: =IFERROR(IF('BASE DE DADOS PREÇOS'!$M$71="com",VLOOKUP(CONCATENATE(B25,$I$6),'BASE DE DADOS PREÇOS'!$E:$H,4,0)/(1-SUM($F$1))*VLOOKUP(CAPA!$B$12,'POLITICA DE PREÇO'!#REF!,2,0)*0.95,VLOOKUP(CONCATENATE(B25,$I$6),'BASE DE DADOS PREÇOS'!$E:$H,4,0)/(1-SUM($F$1))*VLOOKUP(CAPA!$B$12,'POLITICA DE PREÇO'!$B$4:$F$100,5,0))*CAPA!$B$14,"") -> 6211.0943 | J25: =I25*0.9 -> 5589.9849 | K25: =H25*1.05 -> 4866.5534

Sheet MESA DE CENTRO
B1: TABELA DE PREÇO CENTURY | MADEIRA
C5: Dimensoes (metros)
A6: Imagem | B6: Nome | C6: C | D6: L | E6: A | G6: Tampo: Espelho Bronze, Fume, Prata, Vidro Fosco ou Clear Corpo: Laca ou Lamina | H6: Tampo: Laca ou Lamina com ou sem Vidro Normal Pintado Corpo: Laca ou Lamina | I6: Tampo: Mármore ou Porcelana Especial Corpo: Laca ou Lamina | J6: Tampo: Mármore ou Porcelana Normal Corpo: Laca ou Lamina | K6: Tampo ou Base em Recoro
B7: Atlas Mesa de Centro - 1.3x0.8x0.28 - Acabamentos Customizados | C7: 1.3 | D7: 0.8 | E7: 0.28 | G7: =IFERROR(IF('BASE DE DADOS PREÇOS'!$M$71="com",VLOOKUP(CONCATENATE(B7,$G$6),'BASE DE DADOS PREÇOS'!$E:$H,4,0)/(1-SUM($F$1))*VLOOKUP(CAPA!$B$12,'POLITICA DE PREÇO'!#REF!,2,0)*0.95,VLOOKUP(CONCATENATE(B7,$G$6),'BASE DE DADOS PREÇOS'!$E:$H,4,0)/(1-SUM($F$1))*VLOOKUP(CAPA!$B$12,'POLITICA DE PREÇO'!$B$4:$F$100,5,0))*CAPA!$B$14,"") -> 3185.219 | H7: =IFERROR(IF('BASE DE DADOS PREÇOS'!$M$71="com",VLOOKUP(CONCATENATE(B7,$H$6),'BASE DE DADOS PREÇOS'!$E:$H,4,0)/(1-SUM($F$1))*VLOOKUP(CAPA!$B$12,'POLITICA DE PREÇO'!#REF!,2,0)*0.95,VLOOKUP(CONCATENATE(B7,$H$6),'BASE DE DADOS PREÇOS'!$E:$H,4,0)/(1-SUM($F$1))*VLOOKUP(CAPA!$B$12,'POLITICA DE PREÇO'!$B$4:$F$100,5,0))*CAPA!$B$14,"") -> 2478.4087 | I7: =IFERROR(IF('BASE DE DADOS PREÇOS'!$M$71="com",VLOOKUP(CONCATENATE(B7,$I$6),'BASE DE DADOS PREÇOS'!$E:$H,4,0)/(1-SUM($F$1))*VLOOKUP(CAPA!$B$12,'POLITICA DE PREÇO'!#REF!,2,0)*0.95,VLOOKUP(CONCATENATE(B7,$I$6),'BASE DE DADOS PREÇOS'!$E:$H,4,0)/(1-SUM($F$1))*VLOOKUP(CAPA!$B$12,'POLITICA DE PREÇO'!$B$4:$F$100,5,0))*CAPA!$B$14,"") -> 7567.2207 | J7: =I7*0.9 -> 6810.4986 | K7: =H7*1.05 -> 2602.3291
B8: Atlas Mesa de Centro - 1.3x0.8x0.35 - Acabamentos Customizados | C8: 1.3 | D8: 0.8 | E8: 0.35 | G8: =IFERROR(IF('BASE DE DADOS PREÇOS'!$M$71="com",VLOOKUP(CONCATENATE(B8,$G$6),'BASE DE DADOS PREÇOS'!$E:$H,4,0)/(1-SUM($F$1))*VLOOKUP(CAPA!$B$12,'POLITICA DE PREÇO'!#REF!,2,0)*0.95,VLOOKUP(CONCATENATE(B8,$G$6),'BASE DE DADOS PREÇOS'!$E:$H,4,0)/(1-SUM($F$1))*VLOOKUP(CAPA!$B$12,'POLITICA DE PREÇO'!$B$4:$F$100,5,0))*CAPA!$B$14,"") -> 3250.4407 | H8: =IFERROR(IF('BASE DE DADOS PREÇOS'!$M$71="com",VLOOKUP(CONCATENATE(B8,$H$6),'BASE DE DADOS PREÇOS'!$E:$H,4,0)/(1-SUM($F$1))*VLOOKUP(CAPA!$B$12,'POLITICA DE PREÇO'!#REF!,2,0)*0.95,VLOOKUP(CONCATENATE(B8,$H$6),'BASE DE DADOS PREÇOS'!$E:$H,4,0)/(1-SUM($F$1))*VLOOKUP(CAPA!$B$12,'POLITICA DE PREÇO'!$B$4:$F$100,5,0))*CAPA!$B$14,"") -> 2543.6304 | I8: =IFERROR(IF('BASE DE DADOS PREÇOS'!$M$71="com",VLOOKUP(CONCATENATE(B8,$I$6),'BASE DE DADOS PREÇOS'!$E:$H,4,0)/(1-SUM($F$1))*VLOOKUP(CAPA!$B$12,'POLITICA DE PREÇO'!#REF!,2,0)*0.95,VLOOKUP(CONCATENATE(B8,$I$6),'BASE DE DADOS PREÇOS'!$E:$H,4,0)/(1-SUM($F$1))*VLOOKUP(CAPA!$B$12,'POLITICA DE PREÇO'!$B$4:$F$100,5,0))*CAPA!$B$14,"") -> 7632.4424 | J8: =I8*0.9 -> 6869.1982 | K8: =H8*1.05 -> 2670.8119
B9: Atlas Mesa de Centro - 1.6x0.8x0.28 - Acabamentos Customizados | C9: 1.6 | D9: 0.8 | E9: 0.28 | G9: =IFERROR(IF('BASE DE DADOS PREÇOS'!$M$71="com",VLOOKUP(CONCATENATE(B9,$G$6),'BASE DE DADOS PREÇOS'!$E:$H,4,0)/(1-SUM($F$1))*VLOOKUP(CAPA!$B$12,'POLITICA DE PREÇO'!#REF!,2,0)*0.95,VLOOKUP(CONCATENATE(B9,$G$6),'BASE DE DADOS PREÇOS'!$E:$H,4,0)/(1-SUM($F$1))*VLOOKUP(CAPA!$B$12,'POLITICA DE PREÇO'!$B$4:$F$100,5,0))*CAPA!$B$14,"") -> 3476.9858 | H9: =IFERROR(IF('BASE DE DADOS PREÇOS'!$M$71="com",VLOOKUP(CONCATENATE(B9,$H$6),'BASE DE DADOS PREÇOS'!$E:$H,4,0)/(1-SUM($F$1))*VLOOKUP(CAPA!$B$12,'POLITICA DE PREÇO'!#REF!,2,0)*0.95,VLOOKUP(CONCATENATE(B9,$H$6),'BASE DE DADOS PREÇOS'!$E:$H,4,0)/(1-SUM($F$1))*VLOOKUP(CAPA!$B$12,'POLITICA DE PREÇO'!$B$4:$F$100,5,0))*CAPA!$B$14,"") -> 2585.0285 | I9: =IFERROR(IF('BASE DE DADOS PREÇOS'!$M$71="com",VLOOKUP(CONCATENATE(B9,$I$6),'BASE DE DADOS PREÇOS'!$E:$H,4,0)/(1-SUM($F$1))*VLOOKUP(CAPA!$B$12,'POLITICA DE PREÇO'!#REF!,2,0)*0.95,VLOOKUP(CONCATENATE(B9,$I$6),'BASE DE DADOS PREÇOS'!$E:$H,4,0)/(1-SUM($F$1))*VLOOKUP(CAPA!$B$12,'POLITICA DE PREÇO'!$B$4:$F$100,5,0))*CAPA!$B$14,"") -> 8415.2698 | J9: =I9*0.9 -> 7573.7428 | K9: =H9*1.05 -> 2714.2799
B10: Atlas Mesa de Centro - 1.6x0.8x0.35 - Acabamentos Customizados | C10: 1.6 | D10: 0.8 | E10: 0.35 | G10: =IFERROR(IF('BASE DE DADOS PREÇOS'!$M$71="com",VLOOKUP(CONCATENATE(B10,$G$6),'BASE DE DADOS PREÇOS'!$E:$H,4,0)/(1-SUM($F$1))*VLOOKUP(CAPA!$B$12,'POLITICA DE PREÇO'!#REF!,2,0)*0.95,VLOOKUP(CONCATENATE(B10,$G$6),'BASE DE DADOS PREÇOS'!$E:$H,4,0)/(1-SUM($F$1))*VLOOKUP(CAPA!$B$12,'POLITICA DE PREÇO'!$B$4:$F$100,5,0))*CAPA!$B$14,"") -> 3542.2075 | H10: =IFERROR(IF('BASE DE DADOS PREÇOS'!$M$71="com",VLOOKUP(CONCATENATE(B10,$H$6),'BASE DE DADOS PREÇOS'!$E:$H,4,0)/(1-SUM($F$1))*VLOOKUP(CAPA!$B$12,'POLITICA DE PREÇO'!#REF!,2,0)*0.95,VLOOKUP(CONCATENATE(B10,$H$6),'BASE DE DADOS PREÇOS'!$E:$H,4,0)/(1-SUM($F$1))*VLOOKUP(CAPA!$B$12,'POLITICA DE PREÇO'!$B$4:$F$100,5,0))*CAPA!$B$14,"") -> 2650.2502 | I10: =IFERROR(IF('BASE DE DADOS PREÇOS'!$M$71="com",VLOOKUP(CONCATENATE(B10,$I$6),'BASE DE DADOS PREÇOS'!$E:$H,4,0)/(1-SUM($F$1))*VLOOKUP(CAPA!$B$12,'POLITICA DE PREÇO'!#REF!,2,0)*0.95,VLOOKUP(CONCATENATE(B10,$I$6),'BASE DE DADOS PREÇOS'!$E:$H,4,0)/(1-SUM($F$1))*VLOOKUP(CAPA!$B$12,'POLITICA DE PREÇO'!$B$4:$F$100,5,0))*CAPA!$B$14,"") -> 8480.4915 | J10: =I10*0.9 -> 7632.4424 | K10: =H10*1.05 -> 2782.7628
B11: Bradan Mesa de Centro - 0.91x0.76x0.33 - Acabamentos Customizados | C11: 0.91 | D11: 0.76 | E11: 0.33 | H11: =IFERROR(IF('BASE DE DADOS PREÇOS'!$M$71="com",VLOOKUP(CONCATENATE(B11,$H$6),'BASE DE DADOS PREÇOS'!$E:$H,4,0)/(1-SUM($F$1))*VLOOKUP(CAPA!$B$12,'POLITICA DE PREÇO'!#REF!,2,0)*0.95,VLOOKUP(CONCATENATE(B11,$H$6),'BASE DE DADOS PREÇOS'!$E:$H,4,0)/(1-SUM($F$1))*VLOOKUP(CAPA!$B$12,'POLITICA DE PREÇO'!$B$4:$F$100,5,0))*CAPA!$B$14,"") -> 2538.6496
B12: Bradan Mesa de Centro - 0.91x0.76x0.4 - Acabamentos Customizados | C12: 0.91 | D12: 0.76 | E12: 0.4 | G12: =IFERROR(IF('BASE DE DADOS PREÇOS'!$M$71="com",VLOOKUP(CONCATENATE(B12,$G$6),'BASE DE DADOS PREÇOS'!$E:$H,4,0)/(1-SUM($F$1))*VLOOKUP(CAPA!$B$12,'POLITICA DE PREÇO'!#REF!,2,0)*0.95,VLOOKUP(CONCATENATE(B12,$G$6),'BASE DE DADOS PREÇOS'!$E:$H,4,0)/(1-SUM($F$1))*VLOOKUP(CAPA!$B$12,'POLITICA DE PREÇO'!$B$4:$F$100,5,0))*CAPA!$B$14,"") | H12: =IFERROR(IF('BASE DE DADOS PREÇOS'!$M$71="com",VLOOKUP(CONCATENATE(B12,$H$6),'BASE DE DADOS PREÇOS'!$E:$H,4,0)/(1-SUM($F$1))*VLOOKUP(CAPA!$B$12,'POLITICA DE PREÇO'!#REF!,2,0)*0.95,VLOOKUP(CONCATENATE(B12,$H$6),'BASE DE DADOS PREÇOS'!$E:$H,4,0)/(1-SUM($F$1))*VLOOKUP(CAPA!$B$12,'POLITICA DE PREÇO'!$B$4:$F$100,5,0))*CAPA!$B$14,"") -> 2665.5821 | I12: =IFERROR(IF('BASE DE DADOS PREÇOS'!$M$71="com",VLOOKUP(CONCATENATE(B12,$I$6),'BASE DE DADOS PREÇOS'!$E:$H,4,0)/(1-SUM($F$1))*VLOOKUP(CAPA!$B$12,'POLITICA DE PREÇO'!#REF!,2,0)*0.95,VLOOKUP(CONCATENATE(B12,$I$6),'BASE DE DADOS PREÇOS'!$E:$H,4,0)/(1-SUM($F$1))*VLOOKUP(CAPA!$B$12,'POLITICA DE PREÇO'!$B$4:$F$100,5,0))*CAPA!$B$14,"")
B13: Bradan Mesa de Centro - 1.1x0.71x0.33 - Acabamentos Customizados | C13: 1.1 | D13: 0.71 | E13: 0.33 | H13: =IFERROR(IF('BASE DE DADOS PREÇOS'!$M$71="com",VLOOKUP(CONCATENATE(B13,$H$6),'BASE DE DADOS PREÇOS'!$E:$H,4,0)/(1-SUM($F$1))*VLOOKUP(CAPA!$B$12,'POLITICA DE PREÇO'!#REF!,2,0)*0.95,VLOOKUP(CONCATENATE(B13,$H$6),'BASE DE DADOS PREÇOS'!$E:$H,4,0)/(1-SUM($F$1))*VLOOKUP(CAPA!$B$12,'POLITICA DE PREÇO'!$B$4:$F$100,5,0))*CAPA!$B$14,"") -> 2581.3782
B14: Bradan Mesa de Centro - 1.1x0.71x0.4 - Acabamentos Customizados | C14: 1.1 | D14: 0.71 | E14: 0.33 | G14: =IFERROR(IF('BASE DE DADOS PREÇOS'!$M$71="com",VLOOKUP(CONCATENATE(B14,$G$6),'BASE DE DADOS PREÇOS'!$E:$H,4,0)/(1-SUM($F$1))*VLOOKUP(CAPA!$B$12,'POLITICA DE PREÇO'!#REF!,2,0)*0.95,VLOOKUP(CONCATENATE(B14,$G$6),'BASE DE DADOS PREÇOS'!$E:$H,4,0)/(1-SUM($F$1))*VLOOKUP(CAPA!$B$12,'POLITICA DE PREÇO'!$B$4:$F$100,5,0))*CAPA!$B$14,"") | H14: =IFERROR(IF('BASE DE DADOS PREÇOS'!$M$71="com",VLOOKUP(CONCATENATE(B14,$H$6),'BASE DE DADOS PREÇOS'!$E:$H,4,0)/(1-SUM($F$1))*VLOOKUP(CAPA!$B$12,'POLITICA DE PREÇO'!#REF!,2,0)*0.95,VLOOKUP(CONCATENATE(B14,$H$6),'BASE DE DADOS PREÇOS'!$E:$H,4,0)/(1-SUM($F$1))*VLOOKUP(CAPA!$B$12,'POLITICA DE PREÇO'!$B$4:$F$100,5,0))*CAPA!$B$14,"") -> 2710.4471 | I14: =IFERROR(IF('BASE DE DADOS PREÇOS'!$M$71="com",VLOOKUP(CONCATENATE(B14,$I$6),'BASE DE DADOS PREÇOS'!$E:$H,4,0)/(1-SUM($F$1))*VLOOKUP(CAPA!$B$12,'POLITICA DE PREÇO'!#REF!,2,0)*0.95,VLOOKUP(CONCATENATE(B14,$I$6),'BASE DE DADOS PREÇOS'!$E:$H,4,0)/(1-SUM($F$1))*VLOOKUP(CAPA!$B$12,'POLITICA DE PREÇO'!$B$4:$F$100,5,0))*CAPA!$B$14,"")
B15: Bradan Mesa de Centro - 1.52x0.91x0.26 - Acabamentos Customizados | C15: 1.52 | D15: 0.91 | E15: 0.26 | H15: =IFERROR(IF('BASE DE DADOS PREÇOS'!$M$71="com",VLOOKUP(CONCATENATE(B15,$H$6),'BASE DE DADOS PREÇOS'!$E:$H,4,0)/(1-SUM($F$1))*VLOOKUP(CAPA!$B$12,'POLITICA DE PREÇO'!#REF!,2,0)*0.95,VLOOKUP(CONCATENATE(B15,$H$6),'BASE DE DADOS PREÇOS'!$E:$H,4,0)/(1-SUM($F$1))*VLOOKUP(CAPA!$B$12,'POLITICA DE PREÇO'!$B$4:$F$100,5,0))*CAPA!$B$14,"") -> 2807.6155
B16: Bradan Mesa de Centro - 1.52x0.91x0.33 - Acabamentos Customizados | C16: 1.52 | D16: 0.91 | E16: 0.33 | G16: =IFERROR(IF('BASE DE DADOS PREÇOS'!$M$71="com",VLOOKUP(CONCATENATE(B16,$G$6),'BASE DE DADOS PREÇOS'!$E:$H,4,0)/(1-SUM($F$1))*VLOOKUP(CAPA!$B$12,'POLITICA DE PREÇO'!#REF!,2,0)*0.95,VLOOKUP(CONCATENATE(B16,$G$6),'BASE DE DADOS PREÇOS'!$E:$H,4,0)/(1-SUM($F$1))*VLOOKUP(CAPA!$B$12,'POLITICA DE PREÇO'!$B$4:$F$100,5,0))*CAPA!$B$14,"") | H16: =IFERROR(IF('BASE DE DADOS PREÇOS'!$M$71="com",VLOOKUP(CONCATENATE(B16,$H$6),'BASE DE DADOS PREÇOS'!$E:$H,4,0)/(1-SUM($F$1))*VLOOKUP(CAPA!$B$12,'POLITICA DE PREÇO'!#REF!,2,0)*0.95,VLOOKUP(CONCATENATE(B16,$H$6),'BASE DE DADOS PREÇOS'!$E:$H,4,0)/(1-SUM($F$1))*VLOOKUP(CAPA!$B$12,'POLITICA DE PREÇO'!$B$4:$F$100,5,0))*CAPA!$B$14,"") -> 2947.9963
B17: Bradan Mesa de Centro - 1.8x1x0.26 - Acabamentos Customizados | C17: 1.8 | D17: 1 | E17: 0.26 | H17: =IFERROR(IF('BASE DE DADOS PREÇOS'!$M$71="com",VLOOKUP(CONCATENATE(B17,$H$6),'BASE DE DADOS PREÇOS'!$E:$H,4,0)/(1-SUM($F$1))*VLOOKUP(CAPA!$B$12,'POLITICA DE PREÇO'!#REF!,2,0)*0.95,VLOOKUP(CONCATENATE(B17,$H$6),'BASE DE DADOS PREÇOS'!$E:$H,4,0)/(1-SUM($F$1))*VLOOKUP(CAPA!$B$12,'POLITICA DE PREÇO'!$B$4:$F$100,5,0))*CAPA!$B$14,"") -> 3762.8775
B18: Bradan Mesa de Centro - 1.8x1x0.33 - Acabamentos Customizados | C18: 1.8 | D18: 1 | E18: 0.33 | G18: =IFERROR(IF('BASE DE DADOS PREÇOS'!$M$71="com",VLOOKUP(CONCATENATE(B18,$G$6),'BASE DE DADOS PREÇOS'!$E:$H,4,0)/(1-SUM($F$1))*VLOOKUP(CAPA!$B$12,'POLITICA DE PREÇO'!#REF!,2,0)*0.95,VLOOKUP(CONCATENATE(B18,$G$6),'BASE DE DADOS PREÇOS'!$E:$H,4,0)/(1-SUM($F$1))*VLOOKUP(CAPA!$B$12,'POLITICA DE PREÇO'!$B$4:$F$100,5,0))*CAPA!$B$14,"") | H18: =IFERROR(IF('BASE DE DADOS PREÇOS'!$M$71="com",VLOOKUP(CONCATENATE(B18,$H$6),'BASE DE DADOS PREÇOS'!$E:$H,4,0)/(1-SUM($F$1))*VLOOKUP(CAPA!$B$12,'POLITICA DE PREÇO'!#REF!,2,0)*0.95,VLOOKUP(CONCATENATE(B18,$H$6),'BASE DE DADOS PREÇOS'!$E:$H,4,0)/(1-SUM($F$1))*VLOOKUP(CAPA!$B$12,'POLITICA DE PREÇO'!$B$4:$F$100,5,0))*CAPA!$B$14,"") -> 3951.0214
B19: Gem Mesa de Centro - 1x1x0.26 - Acabamentos Customizados | C19: 1 | D19: 1 | E19: 0.26 | G19: =IFERROR(IF('BASE DE DADOS PREÇOS'!$M$71="com",VLOOKUP(CONCATENATE(B19,$G$6),'BASE DE DADOS PREÇOS'!$E:$H,4,0)/(1-SUM($F$1))*VLOOKUP(CAPA!$B$12,'POLITICA DE PREÇO'!#REF!,2,0)*0.95,VLOOKUP(CONCATENATE(B19,$G$6),'BASE DE DADOS PREÇOS'!$E:$H,4,0)/(1-SUM($F$1))*VLOOKUP(CAPA!$B$12,'POLITICA DE PREÇO'!$B$4:$F$100,5,0))*CAPA!$B$14,"") -> 4698.8633 | H19: =IFERROR(IF('BASE DE DADOS PREÇOS'!$M$71="com",VLOOKUP(CONCATENATE(B19,$H$6),'BASE DE DADOS PREÇOS'!$E:$H,4,0)/(1-SUM($F$1))*VLOOKUP(CAPA!$B$12,'POLITICA DE PREÇO'!#REF!,2,0)*0.95,VLOOKUP(CONCATENATE(B19,$H$6),'BASE DE DADOS PREÇOS'!$E:$H,4,0)/(1-SUM($F$1))*VLOOKUP(CAPA!$B$12,'POLITICA DE PREÇO'!$B$4:$F$100,5,0))*CAPA!$B$14,"") -> 3580.0864 | I19: =IFERROR(IF('BASE DE DADOS PREÇOS'!$M$71="com",VLOOKUP(CONCATENATE(B19,$I$6),'BASE DE DADOS PREÇOS'!$E:$H,4,0)/(1-SUM($F$1))*VLOOKUP(CAPA!$B$12,'POLITICA DE PREÇO'!#REF!,2,0)*0.95,VLOOKUP(CONCATENATE(B19,$I$6),'BASE DE DADOS PREÇOS'!$E:$H,4,0)/(1-SUM($F$1))*VLOOKUP(CAPA!$B$12,'POLITICA DE PREÇO'!$B$4:$F$100,5,0))*CAPA!$B$14,"")
B20: Gem Mesa de Centro - 1.2x0.6x0.26 - Acabamentos Customizados | C20: 1.2 | D20: 0.6 | E20: 0.26 | G20: =IFERROR(IF('BASE DE DADOS PREÇOS'!$M$71="com",VLOOKUP(CONCATENATE(B20,$G$6),'BASE DE DADOS PREÇOS'!$E:$H,4,0)/(1-SUM($F$1))*VLOOKUP(CAPA!$B$12,'POLITICA DE PREÇO'!#REF!,2,0)*0.95,VLOOKUP(CONCATENATE(B20,$G$6),'BASE DE DADOS PREÇOS'!$E:$H,4,0)/(1-SUM($F$1))*VLOOKUP(CAPA!$B$12,'POLITICA DE PREÇO'!$B$4:$F$100,5,0))*CAPA!$B$14,"") -> 4385.5027 | H20: =IFERROR(IF('BASE DE DADOS PREÇOS'!$M$71="com",VLOOKUP(CONCATENATE(B20,$H$6),'BASE DE DADOS PREÇOS'!$E:$H,4,0)/(1-SUM($F$1))*VLOOKUP(CAPA!$B$12,'POLITICA DE PREÇO'!#REF!,2,0)*0.95,VLOOKUP(CONCATENATE(B20,$H$6),'BASE DE DADOS PREÇOS'!$E:$H,4,0)/(1-SUM($F$1))*VLOOKUP(CAPA!$B$12,'POLITICA DE PREÇO'!$B$4:$F$100,5,0))*CAPA!$B$14,"") -> 3508.4022 | I20: =IFERROR(IF('BASE DE DADOS PREÇOS'!$M$71="com",VLOOKUP(CONCATENATE(B20,$I$6),'BASE DE DADOS PREÇOS'!$E:$H,4,0)/(1-SUM($F$1))*VLOOKUP(CAPA!$B$12,'POLITICA DE PREÇO'!#REF!,2,0)*0.95,VLOOKUP(CONCATENATE(B20,$I$6),'BASE DE DADOS PREÇOS'!$E:$H,4,0)/(1-SUM($F$1))*VLOOKUP(CAPA!$B$12,'POLITICA DE PREÇO'!$B$4:$F$100,5,0))*CAPA!$B$14,"")
B21: Gem Mesa de Centro - 1.6x1x0.26 - Acabamentos Customizados | C21: 1.6 | D21: 1 | E21: 0.26 | G21: =IFERROR(IF('BASE DE DADOS PREÇOS'!$M$71="com",VLOOKUP(CONCATENATE(B21,$G$6),'BASE DE DADOS PREÇOS'!$E:$H,4,0)/(1-SUM($F$1))*VLOOKUP(CAPA!$B$12,'POLITICA DE PREÇO'!#REF!,2,0)*0.95,VLOOKUP(CONCATENATE(B21,$G$6),'BASE DE DADOS PREÇOS'!$E:$H,4,0)/(1-SUM($F$1))*VLOOKUP(CAPA!$B$12,'POLITICA DE PREÇO'!$B$4:$F$100,5,0))*CAPA!$B$14,"") -> 5358.1489 | H21: =IFERROR(IF('BASE DE DADOS PREÇOS'!$M$71="com",VLOOKUP(CONCATENATE(B21,$H$6),'BASE DE DADOS PREÇOS'!$E:$H,4,0)/(1-SUM($F$1))*VLOOKUP(CAPA!$B$12,'POLITICA DE PREÇO'!#REF!,2,0)*0.95,VLOOKUP(CONCATENATE(B21,$H$6),'BASE DE DADOS PREÇOS'!$E:$H,4,0)/(1-SUM($F$1))*VLOOKUP(CAPA!$B$12,'POLITICA DE PREÇO'!$B$4:$F$100,5,0))*CAPA!$B$14,"") -> 4000.7512 | I21: =IFERROR(IF('BASE DE DADOS PREÇOS'!$M$71="com",VLOOKUP(CONCATENATE(B21,$I$6),'BASE DE DADOS PREÇOS'!$E:$H,4,0)/(1-SUM($F$1))*VLOOKUP(CAPA!$B$12,'POLITICA DE PREÇO'!#REF!,2,0)*0.95,VLOOKUP(CONCATENATE(B21,$I$6),'BASE DE DADOS PREÇOS'!$E:$H,4,0)/(1-SUM($F$1))*VLOOKUP(CAPA!$B$12,'POLITICA DE PREÇO'!$B$4:$F$100,5,0))*CAPA!$B$14,"")
B22: Gem Mesa de Centro - 1.8x0.8x0.26 - Acabamentos Customizados | C22: 1.8 | D22: 0.8 | E22: 0.26 | G22: =IFERROR(IF('BASE DE DADOS PREÇOS'!$M$71="com",VLOOKUP(CONCATENATE(B22,$G$6),'BASE DE DADOS PREÇOS'!$E:$H,4,0)/(1-SUM($F$1))*VLOOKUP(CAPA!$B$12,'POLITICA DE PREÇO'!#REF!,2,0)*0.95,VLOOKUP(CONCATENATE(B22,$G$6),'BASE DE DADOS PREÇOS'!$E:$H,4,0)/(1-SUM($F$1))*VLOOKUP(CAPA!$B$12,'POLITICA DE PREÇO'!$B$4:$F$100,5,0))*CAPA!$B$14,"") -> 5893.9638 | H22: =IFERROR(IF('BASE DE DADOS PREÇOS'!$M$71="com",VLOOKUP(CONCATENATE(B22,$H$6),'BASE DE DADOS PREÇOS'!$E:$H,4,0)/(1-SUM($F$1))*VLOOKUP(CAPA!$B$12,'POLITICA DE PREÇO'!#REF!,2,0)*0.95,VLOOKUP(CONCATENATE(B22,$H$6),'BASE DE DADOS PREÇOS'!$E:$H,4,0)/(1-SUM($F$1))*VLOOKUP(CAPA!$B$12,'POLITICA DE PREÇO'!$B$4:$F$100,5,0))*CAPA!$B$14,"") -> 4400.8263 | I22: =IFERROR(IF('BASE DE DADOS PREÇOS'!$M$71="com",VLOOKUP(CONCATENATE(B22,$I$6),'BASE DE DADOS PREÇOS'!$E:$H,4,0)/(1-SUM($F$1))*VLOOKUP(CAPA!$B$12,'POLITICA DE PREÇO'!#REF!,2,0)*0.95,VLOOKUP(CONCATENATE(B22,$I$6),'BASE DE DADOS PREÇOS'!$E:$H,4,0)/(1-SUM($F$1))*VLOOKUP(CAPA!$B$12,'POLITICA DE PREÇO'!$B$4:$F$100,5,0))*CAPA!$B$14,"")
B23: Hazel Mesa de Centro - 1.3x0.8x0.26 - Acabamentos Customizados | C23: 1.3 | D23: 0.8 | E23: 0.26 | G23: =IFERROR(IF('BASE DE DADOS PREÇOS'!$M$71="com",VLOOKUP(CONCATENATE(B23,$G$6),'BASE DE DADOS PREÇOS'!$E:$H,4,0)/(1-SUM($F$1))*VLOOKUP(CAPA!$B$12,'POLITICA DE PREÇO'!#REF!,2,0)*0.95,VLOOKUP(CONCATENATE(B23,$G$6),'BASE DE DADOS PREÇOS'!$E:$H,4,0)/(1-SUM($F$1))*VLOOKUP(CAPA!$B$12,'POLITICA DE PREÇO'!$B$4:$F$100,5,0))*CAPA!$B$14,"") -> 4392.0861 | H23: =IFERROR(IF('BASE DE DADOS PREÇOS'!$M$71="com",VLOOKUP(CONCATENATE(B23,$H$6),'BASE DE DADOS PREÇOS'!$E:$H,4,0)/(1-SUM($F$1))*VLOOKUP(CAPA!$B$12,'POLITICA DE PREÇO'!#REF!,2,0)*0.95,VLOOKUP(CONCATENATE(B23,$H$6),'BASE DE DADOS PREÇOS'!$E:$H,4,0)/(1-SUM($F$1))*VLOOKUP(CAPA!$B$12,'POLITICA DE PREÇO'!$B$4:$F$100,5,0))*CAPA!$B$14,"") -> 2518.201 | I23: =IFERROR(IF('BASE DE DADOS PREÇOS'!$M$71="com",VLOOKUP(CONCATENATE(B23,$I$6),'BASE DE DADOS PREÇOS'!$E:$H,4,0)/(1-SUM($F$1))*VLOOKUP(CAPA!$B$12,'POLITICA DE PREÇO'!#REF!,2,0)*0.95,VLOOKUP(CONCATENATE(B23,$I$6),'BASE DE DADOS PREÇOS'!$E:$H,4,0)/(1-SUM($F$1))*VLOOKUP(CAPA!$B$12,'POLITICA DE PREÇO'!$B$4:$F$100,5,0))*CAPA!$B$14,"") -> 7916.4008 | J23: =I23*0.9 -> 7124.7607
B24: Hazel Mesa de Centro - 1.3x0.8x0.33 - Acabamentos Customizados | C24: 1.3 | D24: 0.8 | E24: 0.33 | G24: =IFERROR(IF('BASE DE DADOS PREÇOS'!$M$71="com",VLOOKUP(CONCATENATE(B24,$G$6),'BASE DE DADOS PREÇOS'!$E:$H,4,0)/(1-SUM($F$1))*VLOOKUP(CAPA!$B$12,'POLITICA DE PREÇO'!#REF!,2,0)*0.95,VLOOKUP(CONCATENATE(B24,$G$6),'BASE DE DADOS PREÇOS'!$E:$H,4,0)/(1-SUM($F$1))*VLOOKUP(CAPA!$B$12,'POLITICA DE PREÇO'!$B$4:$F$100,5,0))*CAPA!$B$14,"") -> 4623.2486 | H24: =IFERROR(IF('BASE DE DADOS PREÇOS'!$M$71="com",VLOOKUP(CONCATENATE(B24,$H$6),'BASE DE DADOS PREÇOS'!$E:$H,4,0)/(1-SUM($F$1))*VLOOKUP(CAPA!$B$12,'POLITICA DE PREÇO'!#REF!,2,0)*0.95,VLOOKUP(CONCATENATE(B24,$H$6),'BASE DE DADOS PREÇOS'!$E:$H,4,0)/(1-SUM($F$1))*VLOOKUP(CAPA!$B$12,'POLITICA DE PREÇO'!$B$4:$F$100,5,0))*CAPA!$B$14,"") -> 2650.7379 | I24: =IFERROR(IF('BASE DE DADOS PREÇOS'!$M$71="com",VLOOKUP(CONCATENATE(B24,$I$6),'BASE DE DADOS PREÇOS'!$E:$H,4,0)/(1-SUM($F$1))*VLOOKUP(CAPA!$B$12,'POLITICA DE PREÇO'!#REF!,2,0)*0.95,VLOOKUP(CONCATENATE(B24,$I$6),'BASE DE DADOS PREÇOS'!$E:$H,4,0)/(1-SUM($F$1))*VLOOKUP(CAPA!$B$12,'POLITICA DE PREÇO'!$B$4:$F$100,5,0))*CAPA!$B$14,"") -> 8333.0534 | J24: =I24*0.9 -> 7499.7481
B25: Metro Mesa de Centro - 1.8x0.8x0.26 - Acabamentos Customizados | C25: 1.8 | D25: 0.8 | E25: 0.26 | G25: =IFERROR(IF('BASE DE DADOS PREÇOS'!$M$71="com",VLOOKUP(CONCATENATE(B25,$G$6),'BASE DE DADOS PREÇOS'!$E:$H,4,0)/(1-SUM($F$1))*VLOOKUP(CAPA!$B$12,'POLITICA DE PREÇO'!#REF!,2,0)*0.95,VLOOKUP(CONCATENATE(B25,$G$6),'BASE DE DADOS PREÇOS'!$E:$H,4,0)/(1-SUM($F$1))*VLOOKUP(CAPA!$B$12,'POLITICA DE PREÇO'!$B$4:$F$100,5,0))*CAPA!$B$14,"") -> 4397.6772 | H25: =IFERROR(IF('BASE DE DADOS PREÇOS'!$M$71="com",VLOOKUP(CONCATENATE(B25,$H$6),'BASE DE DADOS PREÇOS'!$E:$H,4,0)/(1-SUM($F$1))*VLOOKUP(CAPA!$B$12,'POLITICA DE PREÇO'!#REF!,2,0)*0.95,VLOOKUP(CONCATENATE(B25,$H$6),'BASE DE DADOS PREÇOS'!$E:$H,4,0)/(1-SUM($F$1))*VLOOKUP(CAPA!$B$12,'POLITICA DE PREÇO'!$B$4:$F$100,5,0))*CAPA!$B$14,"") -> 3407.0331 | I25: =IFERROR(IF('BASE DE DADOS PREÇOS'!$M$71="com",VLOOKUP(CONCATENATE(B25,$I$6),'BASE DE DADOS PREÇOS'!$E:$H,4,0)/(1-SUM($F$1))*VLOOKUP(CAPA!$B$12,'POLITICA DE PREÇO'!#REF!,2,0)*0.95,VLOOKUP(CONCATENATE(B25,$I$6),'BASE DE DADOS PREÇOS'!$E:$H,4,0)/(1-SUM($F$1))*VLOOKUP(CAPA!$B$12,'POLITICA DE PREÇO'!$B$4:$F$100,5,0))*CAPA!$B$14,"") -> 9662.9234 | J25: =I25*0.9 -> 8696.6311
B26: Metro Mesa de Centro - 1.6x1.0x0.26 - Acabamentos Customizados | C26: 1.6 | D26: 1 | E26: 0.26 | G26: =IFERROR(IF('BASE DE DADOS PREÇOS'!$M$71="com",VLOOKUP(CONCATENATE(B26,$G$6),'BASE DE DADOS PREÇOS'!$E:$H,4,0)/(1-SUM($F$1))*VLOOKUP(CAPA!$B$12,'POLITICA DE PREÇO'!#REF!,2,0)*0.95,VLOOKUP(CONCATENATE(B26,$G$6),'BASE DE DADOS PREÇOS'!$E:$H,4,0)/(1-SUM($F$1))*VLOOKUP(CAPA!$B$12,'POLITICA DE PREÇO'!$B$4:$F$100,5,0))*CAPA!$B$14,"") -> 4886.308 | H26: =IFERROR(IF('BASE DE DADOS PREÇOS'!$M$71="com",VLOOKUP(CONCATENATE(B26,$H$6),'BASE DE DADOS PREÇOS'!$E:$H,4,0)/(1-SUM($F$1))*VLOOKUP(CAPA!$B$12,'POLITICA DE PREÇO'!#REF!,2,0)*0.95,VLOOKUP(CONCATENATE(B26,$H$6),'BASE DE DADOS PREÇOS'!$E:$H,4,0)/(1-SUM($F$1))*VLOOKUP(CAPA!$B$12,'POLITICA DE PREÇO'!$B$4:$F$100,5,0))*CAPA!$B$14,"") -> 3785.5924 | I26: =IFERROR(IF('BASE DE DADOS PREÇOS'!$M$71="com",VLOOKUP(CONCATENATE(B26,$I$6),'BASE DE DADOS PREÇOS'!$E:$H,4,0)/(1-SUM($F$1))*VLOOKUP(CAPA!$B$12,'POLITICA DE PREÇO'!#REF!,2,0)*0.95,VLOOKUP(CONCATENATE(B26,$I$6),'BASE DE DADOS PREÇOS'!$E:$H,4,0)/(1-SUM($F$1))*VLOOKUP(CAPA!$B$12,'POLITICA DE PREÇO'!$B$4:$F$100,5,0))*CAPA!$B$14,"") -> 10736.582 | J26: =I26*0.9 -> 9662.9234
B27: Minos Mesa de Centro - 0.9x0.9x0.26 - Acabamentos Customizados | C27: 0.9 | D27: 0.9 | E27: 0.26 | G27: =IFERROR(IF('BASE DE DADOS PREÇOS'!$M$71="com",VLOOKUP(CONCATENATE(B27,$G$6),'BASE DE DADOS PREÇOS'!$E:$H,4,0)/(1-SUM($F$1))*VLOOKUP(CAPA!$B$12,'POLITICA DE PREÇO'!#REF!,2,0)*0.95,VLOOKUP(CONCATENATE(B27,$G$6),'BASE DE DADOS PREÇOS'!$E:$H,4,0)/(1-SUM($F$1))*VLOOKUP(CAPA!$B$12,'POLITICA DE PREÇO'!$B$4:$F$100,5,0))*CAPA!$B$14,"") -> 3776.3875 | H27: =IFERROR(IF('BASE DE DADOS PREÇOS'!$M$71="com",VLOOKUP(CONCATENATE(B27,$H$6),'BASE DE DADOS PREÇOS'!$E:$H,4,0)/(1-SUM($F$1))*VLOOKUP(CAPA!$B$12,'POLITICA DE PREÇO'!#REF!,2,0)*0.95,VLOOKUP(CONCATENATE(B27,$H$6),'BASE DE DADOS PREÇOS'!$E:$H,4,0)/(1-SUM($F$1))*VLOOKUP(CAPA!$B$12,'POLITICA DE PREÇO'!$B$4:$F$100,5,0))*CAPA!$B$14,"") -> 3057.8358 | I27: =IFERROR(IF('BASE DE DADOS PREÇOS'!$M$71="com",VLOOKUP(CONCATENATE(B27,$I$6),'BASE DE DADOS PREÇOS'!$E:$H,4,0)/(1-SUM($F$1))*VLOOKUP(CAPA!$B$12,'POLITICA DE PREÇO'!#REF!,2,0)*0.95,VLOOKUP(CONCATENATE(B27,$I$6),'BASE DE DADOS PREÇOS'!$E:$H,4,0)/(1-SUM($F$1))*VLOOKUP(CAPA!$B$12,'POLITICA DE PREÇO'!$B$4:$F$100,5,0))*CAPA!$B$14,"") -> 6247.8053 | J27: =I27*0.9 -> 5623.0248
B28: Minos Mesa de Centro - 1x1x0.26 - Acabamentos Customizados | C28: 1 | D28: 1 | E28: 0.26 | G28: =IFERROR(IF('BASE DE DADOS PREÇOS'!$M$71="com",VLOOKUP(CONCATENATE(B28,$G$6),'BASE DE DADOS PREÇOS'!$E:$H,4,0)/(1-SUM($F$1))*VLOOKUP(CAPA!$B$12,'POLITICA DE PREÇO'!#REF!,2,0)*0.95,VLOOKUP(CONCATENATE(B28,$G$6),'BASE DE DADOS PREÇOS'!$E:$H,4,0)/(1-SUM($F$1))*VLOOKUP(CAPA!$B$12,'POLITICA DE PREÇO'!$B$4:$F$100,5,0))*CAPA!$B$14,"") -> 4255.1818 | H28: =IFERROR(IF('BASE DE DADOS PREÇOS'!$M$71="com",VLOOKUP(CONCATENATE(B28,$H$6),'BASE DE DADOS PREÇOS'!$E:$H,4,0)/(1-SUM($F$1))*VLOOKUP(CAPA!$B$12,'POLITICA DE PREÇO'!#REF!,2,0)*0.95,VLOOKUP(CONCATENATE(B28,$H$6),'BASE DE DADOS PREÇOS'!$E:$H,4,0)/(1-SUM($F$1))*VLOOKUP(CAPA!$B$12,'POLITICA DE PREÇO'!$B$4:$F$100,5,0))*CAPA!$B$14,"") -> 3303.2177 | I28: =IFERROR(IF('BASE DE DADOS PREÇOS'!$M$71="com",VLOOKUP(CONCATENATE(B28,$I$6),'BASE DE DADOS PREÇOS'!$E:$H,4,0)/(1-SUM($F$1))*VLOOKUP(CAPA!$B$12,'POLITICA DE PREÇO'!#REF!,2,0)*0.95,VLOOKUP(CONCATENATE(B28,$I$6),'BASE DE DADOS PREÇOS'!$E:$H,4,0)/(1-SUM($F$1))*VLOOKUP(CAPA!$B$12,'POLITICA DE PREÇO'!$B$4:$F$100,5,0))*CAPA!$B$14,"") -> 7026.6095 | J28: =I28*0.9 -> 6323.9485
B29: Minos Mesa de Centro - 1.4x0.7x0.26 - Acabamentos Customizados | C29: 1.4 | D29: 0.7 | E29: 0.26 | G29: =IFERROR(IF('BASE DE DADOS PREÇOS'!$M$71="com",VLOOKUP(CONCATENATE(B29,$G$6),'BASE DE DADOS PREÇOS'!$E:$H,4,0)/(1-SUM($F$1))*VLOOKUP(CAPA!$B$12,'POLITICA DE PREÇO'!#REF!,2,0)*0.95,VLOOKUP(CONCATENATE(B29,$G$6),'BASE DE DADOS PREÇOS'!$E:$H,4,0)/(1-SUM($F$1))*VLOOKUP(CAPA!$B$12,'POLITICA DE PREÇO'!$B$4:$F$100,5,0))*CAPA!$B$14,"") -> 4170.0781 | H29: =IFERROR(IF('BASE DE DADOS PREÇOS'!$M$71="com",VLOOKUP(CONCATENATE(B29,$H$6),'BASE DE DADOS PREÇOS'!$E:$H,4,0)/(1-SUM($F$1))*VLOOKUP(CAPA!$B$12,'POLITICA DE PREÇO'!#REF!,2,0)*0.95,VLOOKUP(CONCATENATE(B29,$H$6),'BASE DE DADOS PREÇOS'!$E:$H,4,0)/(1-SUM($F$1))*VLOOKUP(CAPA!$B$12,'POLITICA DE PREÇO'!$B$4:$F$100,5,0))*CAPA!$B$14,"") -> 3237.1533 | I29: =IFERROR(IF('BASE DE DADOS PREÇOS'!$M$71="com",VLOOKUP(CONCATENATE(B29,$I$6),'BASE DE DADOS PREÇOS'!$E:$H,4,0)/(1-SUM($F$1))*VLOOKUP(CAPA!$B$12,'POLITICA DE PREÇO'!#REF!,2,0)*0.95,VLOOKUP(CONCATENATE(B29,$I$6),'BASE DE DADOS PREÇOS'!$E:$H,4,0)/(1-SUM($F$1))*VLOOKUP(CAPA!$B$12,'POLITICA DE PREÇO'!$B$4:$F$100,5,0))*CAPA!$B$14,"") -> 7417.7821 | J29: =I29*0.9 -> 6676.0038
B30: Minos Mesa de Centro - 1.6x1x0.26 - Acabamentos Customizados | C30: 1.6 | D30: 1 | E30: 0.26 | G30: =IFERROR(IF('BASE DE DADOS PREÇOS'!$M$71="com",VLOOKUP(CONCATENATE(B30,$G$6),'BASE DE DADOS PREÇOS'!$E:$H,4,0)/(1-SUM($F$1))*VLOOKUP(CAPA!$B$12,'POLITICA DE PREÇO'!#REF!,2,0)*0.95,VLOOKUP(CONCATENATE(B30,$G$6),'BASE DE DADOS PREÇOS'!$E:$H,4,0)/(1-SUM($F$1))*VLOOKUP(CAPA!$B$12,'POLITICA DE PREÇO'!$B$4:$F$100,5,0))*CAPA!$B$14,"") -> 5195.9666 | H30: =IFERROR(IF('BASE DE DADOS PREÇOS'!$M$71="com",VLOOKUP(CONCATENATE(B30,$H$6),'BASE DE DADOS PREÇOS'!$E:$H,4,0)/(1-SUM($F$1))*VLOOKUP(CAPA!$B$12,'POLITICA DE PREÇO'!#REF!,2,0)*0.95,VLOOKUP(CONCATENATE(B30,$H$6),'BASE DE DADOS PREÇOS'!$E:$H,4,0)/(1-SUM($F$1))*VLOOKUP(CAPA!$B$12,'POLITICA DE PREÇO'!$B$4:$F$100,5,0))*CAPA!$B$14,"") -> 3826.1209 | I30: =IFERROR(IF('BASE DE DADOS PREÇOS'!$M$71="com",VLOOKUP(CONCATENATE(B30,$I$6),'BASE DE DADOS PREÇOS'!$E:$H,4,0)/(1-SUM($F$1))*VLOOKUP(CAPA!$B$12,'POLITICA DE PREÇO'!#REF!,2,0)*0.95,VLOOKUP(CONCATENATE(B30,$I$6),'BASE DE DADOS PREÇOS'!$E:$H,4,0)/(1-SUM($F$1))*VLOOKUP(CAPA!$B$12,'POLITICA DE PREÇO'!$B$4:$F$100,5,0))*CAPA!$B$14,"") -> 9919.653 | J30: =I30*0.9 -> 8927.6877
B31: Minos Mesa de Centro - 1.8x0.8x0.26 - Acabamentos Customizados | C31: 1.8 | D31: 0.8 | E31: 0.26 | G31: =IFERROR(IF('BASE DE DADOS PREÇOS'!$M$71="com",VLOOKUP(CONCATENATE(B31,$G$6),'BASE DE DADOS PREÇOS'!$E:$H,4,0)/(1-SUM($F$1))*VLOOKUP(CAPA!$B$12,'POLITICA DE PREÇO'!#REF!,2,0)*0.95,VLOOKUP(CONCATENATE(B31,$G$6),'BASE DE DADOS PREÇOS'!$E:$H,4,0)/(1-SUM($F$1))*VLOOKUP(CAPA!$B$12,'POLITICA DE PREÇO'!$B$4:$F$100,5,0))*CAPA!$B$14,"") -> 4676.37 | H31: =IFERROR(IF('BASE DE DADOS PREÇOS'!$M$71="com",VLOOKUP(CONCATENATE(B31,$H$6),'BASE DE DADOS PREÇOS'!$E:$H,4,0)/(1-SUM($F$1))*VLOOKUP(CAPA!$B$12,'POLITICA DE PREÇO'!#REF!,2,0)*0.95,VLOOKUP(CONCATENATE(B31,$H$6),'BASE DE DADOS PREÇOS'!$E:$H,4,0)/(1-SUM($F$1))*VLOOKUP(CAPA!$B$12,'POLITICA DE PREÇO'!$B$4:$F$100,5,0))*CAPA!$B$14,"") -> 3826.1209 | I31: =IFERROR(IF('BASE DE DADOS PREÇOS'!$M$71="com",VLOOKUP(CONCATENATE(B31,$I$6),'BASE DE DADOS PREÇOS'!$E:$H,4,0)/(1-SUM($F$1))*VLOOKUP(CAPA!$B$12,'POLITICA DE PREÇO'!#REF!,2,0)*0.95,VLOOKUP(CONCATENATE(B31,$I$6),'BASE DE DADOS PREÇOS'!$E:$H,4,0)/(1-SUM($F$1))*VLOOKUP(CAPA!$B$12,'POLITICA DE PREÇO'!$B$4:$F$100,5,0))*CAPA!$B$14,"") -> 9715.1241 | J31: =I31*0.9 -> 8743.6117
B32: Moon Mesa de Centro - Øx0.9x0.26 - Acabamentos Customizados | C32: Ø | D32: 0.9 | E32: 0.26 | G32: =IFERROR(IF('BASE DE DADOS PREÇOS'!$M$71="com",VLOOKUP(CONCATENATE(B32,$G$6),'BASE DE DADOS PREÇOS'!$E:$H,4,0)/(1-SUM($F$1))*VLOOKUP(CAPA!$B$12,'POLITICA DE PREÇO'!#REF!,2,0)*0.95,VLOOKUP(CONCATENATE(B32,$G$6),'BASE DE DADOS PREÇOS'!$E:$H,4,0)/(1-SUM($F$1))*VLOOKUP(CAPA!$B$12,'POLITICA DE PREÇO'!$B$4:$F$100,5,0))*CAPA!$B$14,"") -> 3562.6955 | H32: =IFERROR(IF('BASE DE DADOS PREÇOS'!$M$71="com",VLOOKUP(CONCATENATE(B32,$H$6),'BASE DE DADOS PREÇOS'!$E:$H,4,0)/(1-SUM($F$1))*VLOOKUP(CAPA!$B$12,'POLITICA DE PREÇO'!#REF!,2,0)*0.95,VLOOKUP(CONCATENATE(B32,$H$6),'BASE DE DADOS PREÇOS'!$E:$H,4,0)/(1-SUM($F$1))*VLOOKUP(CAPA!$B$12,'POLITICA DE PREÇO'!$B$4:$F$100,5,0))*CAPA!$B$14,"") -> 2048.1893 | I32: =IFERROR(IF('BASE DE DADOS PREÇOS'!$M$71="com",VLOOKUP(CONCATENATE(B32,$I$6),'BASE DE DADOS PREÇOS'!$E:$H,4,0)/(1-SUM($F$1))*VLOOKUP(CAPA!$B$12,'POLITICA DE PREÇO'!#REF!,2,0)*0.95,VLOOKUP(CONCATENATE(B32,$I$6),'BASE DE DADOS PREÇOS'!$E:$H,4,0)/(1-SUM($F$1))*VLOOKUP(CAPA!$B$12,'POLITICA DE PREÇO'!$B$4:$F$100,5,0))*CAPA!$B$14,"") -> 5468.6413 | J32: =I32*0.9 -> 4921.7771
B33: Moon Mesa de Centro - Øx1x0.26 - Acabamentos Customizados | C33: Ø | D33: 1 | E33: 0.26 | G33: =IFERROR(IF('BASE DE DADOS PREÇOS'!$M$71="com",VLOOKUP(CONCATENATE(B33,$G$6),'BASE DE DADOS PREÇOS'!$E:$H,4,0)/(1-SUM($F$1))*VLOOKUP(CAPA!$B$12,'POLITICA DE PREÇO'!#REF!,2,0)*0.95,VLOOKUP(CONCATENATE(B33,$G$6),'BASE DE DADOS PREÇOS'!$E:$H,4,0)/(1-SUM($F$1))*VLOOKUP(CAPA!$B$12,'POLITICA DE PREÇO'!$B$4:$F$100,5,0))*CAPA!$B$14,"") -> 4398.3895 | H33: =IFERROR(IF('BASE DE DADOS PREÇOS'!$M$71="com",VLOOKUP(CONCATENATE(B33,$H$6),'BASE DE DADOS PREÇOS'!$E:$H,4,0)/(1-SUM($F$1))*VLOOKUP(CAPA!$B$12,'POLITICA DE PREÇO'!#REF!,2,0)*0.95,VLOOKUP(CONCATENATE(B33,$H$6),'BASE DE DADOS PREÇOS'!$E:$H,4,0)/(1-SUM($F$1))*VLOOKUP(CAPA!$B$12,'POLITICA DE PREÇO'!$B$4:$F$100,5,0))*CAPA!$B$14,"") -> 2528.6288 | I33: =IFERROR(IF('BASE DE DADOS PREÇOS'!$M$71="com",VLOOKUP(CONCATENATE(B33,$I$6),'BASE DE DADOS PREÇOS'!$E:$H,4,0)/(1-SUM($F$1))*VLOOKUP(CAPA!$B$12,'POLITICA DE PREÇO'!#REF!,2,0)*0.95,VLOOKUP(CONCATENATE(B33,$I$6),'BASE DE DADOS PREÇOS'!$E:$H,4,0)/(1-SUM($F$1))*VLOOKUP(CAPA!$B$12,'POLITICA DE PREÇO'!$B$4:$F$100,5,0))*CAPA!$B$14,"") -> 6751.409 | J33: =I33*0.9 -> 6076.2681
B34: Moon Mesa de Centro - Øx1.1x0.26 - Acabamentos Customizados | C34: Ø | D34: 1.1 | E34: 0.26 | G34: =IFERROR(IF('BASE DE DADOS PREÇOS'!$M$71="com",VLOOKUP(CONCATENATE(B34,$G$6),'BASE DE DADOS PREÇOS'!$E:$H,4,0)/(1-SUM($F$1))*VLOOKUP(CAPA!$B$12,'POLITICA DE PREÇO'!#REF!,2,0)*0.95,VLOOKUP(CONCATENATE(B34,$G$6),'BASE DE DADOS PREÇOS'!$E:$H,4,0)/(1-SUM($F$1))*VLOOKUP(CAPA!$B$12,'POLITICA DE PREÇO'!$B$4:$F$100,5,0))*CAPA!$B$14,"") -> 4973.5635 | H34: =IFERROR(IF('BASE DE DADOS PREÇOS'!$M$71="com",VLOOKUP(CONCATENATE(B34,$H$6),'BASE DE DADOS PREÇOS'!$E:$H,4,0)/(1-SUM($F$1))*VLOOKUP(CAPA!$B$12,'POLITICA DE PREÇO'!#REF!,2,0)*0.95,VLOOKUP(CONCATENATE(B34,$H$6),'BASE DE DADOS PREÇOS'!$E:$H,4,0)/(1-SUM($F$1))*VLOOKUP(CAPA!$B$12,'POLITICA DE PREÇO'!$B$4:$F$100,5,0))*CAPA!$B$14,"") -> 2679.9904 | I34: =IFERROR(IF('BASE DE DADOS PREÇOS'!$M$71="com",VLOOKUP(CONCATENATE(B34,$I$6),'BASE DE DADOS PREÇOS'!$E:$H,4,0)/(1-SUM($F$1))*VLOOKUP(CAPA!$B$12,'POLITICA DE PREÇO'!#REF!,2,0)*0.95,VLOOKUP(CONCATENATE(B34,$I$6),'BASE DE DADOS PREÇOS'!$E:$H,4,0)/(1-SUM($F$1))*VLOOKUP(CAPA!$B$12,'POLITICA DE PREÇO'!$B$4:$F$100,5,0))*CAPA!$B$14,"") -> 7793.8495 | J34: =I34*0.9 -> 7014.4646
B35: Moon Mesa de Centro - Øx1.2x0.26 - Acabamentos Customizados | C35: Ø | D35: 1.2 | E35: 0.26 | G35: =IFERROR(IF('BASE DE DADOS PREÇOS'!$M$71="com",VLOOKUP(CONCATENATE(B35,$G$6),'BASE DE DADOS PREÇOS'!$E:$H,4,0)/(1-SUM($F$1))*VLOOKUP(CAPA!$B$12,'POLITICA DE PREÇO'!#REF!,2,0)*0.95,VLOOKUP(CONCATENATE(B35,$G$6),'BASE DE DADOS PREÇOS'!$E:$H,4,0)/(1-SUM($F$1))*VLOOKUP(CAPA!$B$12,'POLITICA DE PREÇO'!$B$4:$F$100,5,0))*CAPA!$B$14,"") -> 5918.9516 | H35: =IFERROR(IF('BASE DE DADOS PREÇOS'!$M$71="com",VLOOKUP(CONCATENATE(B35,$H$6),'BASE DE DADOS PREÇOS'!$E:$H,4,0)/(1-SUM($F$1))*VLOOKUP(CAPA!$B$12,'POLITICA DE PREÇO'!#REF!,2,0)*0.95,VLOOKUP(CONCATENATE(B35,$H$6),'BASE DE DADOS PREÇOS'!$E:$H,4,0)/(1-SUM($F$1))*VLOOKUP(CAPA!$B$12,'POLITICA DE PREÇO'!$B$4:$F$100,5,0))*CAPA!$B$14,"") -> 3226.4962 | I35: =IFERROR(IF('BASE DE DADOS PREÇOS'!$M$71="com",VLOOKUP(CONCATENATE(B35,$I$6),'BASE DE DADOS PREÇOS'!$E:$H,4,0)/(1-SUM($F$1))*VLOOKUP(CAPA!$B$12,'POLITICA DE PREÇO'!#REF!,2,0)*0.95,VLOOKUP(CONCATENATE(B35,$I$6),'BASE DE DADOS PREÇOS'!$E:$H,4,0)/(1-SUM($F$1))*VLOOKUP(CAPA!$B$12,'POLITICA DE PREÇO'!$B$4:$F$100,5,0))*CAPA!$B$14,"") -> 9275.3251 | J35: =I35*0.9 -> 8347.7926
B36: Mush Mesa de Centro - Øx0.8x0.33 - Acabamentos Customizados | C36: Ø | D36: 0.8 | E36: 0.33 | G36: =IFERROR(IF('BASE DE DADOS PREÇOS'!$M$71="com",VLOOKUP(CONCATENATE(B36,$G$6),'BASE DE DADOS PREÇOS'!$E:$H,4,0)/(1-SUM($F$1))*VLOOKUP(CAPA!$B$12,'POLITICA DE PREÇO'!#REF!,2,0)*0.95,VLOOKUP(CONCATENATE(B36,$G$6),'BASE DE DADOS PREÇOS'!$E:$H,4,0)/(1-SUM($F$1))*VLOOKUP(CAPA!$B$12,'POLITICA DE PREÇO'!$B$4:$F$100,5,0))*CAPA!$B$14,"") -> 3160.4838 | H36: =IFERROR(IF('BASE DE DADOS PREÇOS'!$M$71="com",VLOOKUP(CONCATENATE(B36,$H$6),'BASE DE DADOS PREÇOS'!$E:$H,4,0)/(1-SUM($F$1))*VLOOKUP(CAPA!$B$12,'POLITICA DE PREÇO'!#REF!,2,0)*0.95,VLOOKUP(CONCATENATE(B36,$H$6),'BASE DE DADOS PREÇOS'!$E:$H,4,0)/(1-SUM($F$1))*VLOOKUP(CAPA!$B$12,'POLITICA DE PREÇO'!$B$4:$F$100,5,0))*CAPA!$B$14,"") -> 2472.6661 | I36: =IFERROR(IF('BASE DE DADOS PREÇOS'!$M$71="com",VLOOKUP(CONCATENATE(B36,$I$6),'BASE DE DADOS PREÇOS'!$E:$H,4,0)/(1-SUM($F$1))*VLOOKUP(CAPA!$B$12,'POLITICA DE PREÇO'!#REF!,2,0)*0.95,VLOOKUP(CONCATENATE(B36,$I$6),'BASE DE DADOS PREÇOS'!$E:$H,4,0)/(1-SUM($F$1))*VLOOKUP(CAPA!$B$12,'POLITICA DE PREÇO'!$B$4:$F$100,5,0))*CAPA!$B$14,"") -> 5111.0573 | J36: =I36*0.9 -> 4599.9515
B37: Mush Mesa de Centro - Øx0.8x0.4 - Acabamentos Customizados | C37: Ø | D37: 0.8 | E37: 0.4 | G37: =IFERROR(IF('BASE DE DADOS PREÇOS'!$M$71="com",VLOOKUP(CONCATENATE(B37,$G$6),'BASE DE DADOS PREÇOS'!$E:$H,4,0)/(1-SUM($F$1))*VLOOKUP(CAPA!$B$12,'POLITICA DE PREÇO'!#REF!,2,0)*0.95,VLOOKUP(CONCATENATE(B37,$G$6),'BASE DE DADOS PREÇOS'!$E:$H,4,0)/(1-SUM($F$1))*VLOOKUP(CAPA!$B$12,'POLITICA DE PREÇO'!$B$4:$F$100,5,0))*CAPA!$B$14,"") -> 3318.508 | H37: =IFERROR(IF('BASE DE DADOS PREÇOS'!$M$71="com",VLOOKUP(CONCATENATE(B37,$H$6),'BASE DE DADOS PREÇOS'!$E:$H,4,0)/(1-SUM($F$1))*VLOOKUP(CAPA!$B$12,'POLITICA DE PREÇO'!#REF!,2,0)*0.95,VLOOKUP(CONCATENATE(B37,$H$6),'BASE DE DADOS PREÇOS'!$E:$H,4,0)/(1-SUM($F$1))*VLOOKUP(CAPA!$B$12,'POLITICA DE PREÇO'!$B$4:$F$100,5,0))*CAPA!$B$14,"") -> 2596.2994 | I37: =IFERROR(IF('BASE DE DADOS PREÇOS'!$M$71="com",VLOOKUP(CONCATENATE(B37,$I$6),'BASE DE DADOS PREÇOS'!$E:$H,4,0)/(1-SUM($F$1))*VLOOKUP(CAPA!$B$12,'POLITICA DE PREÇO'!#REF!,2,0)*0.95,VLOOKUP(CONCATENATE(B37,$I$6),'BASE DE DADOS PREÇOS'!$E:$H,4,0)/(1-SUM($F$1))*VLOOKUP(CAPA!$B$12,'POLITICA DE PREÇO'!$B$4:$F$100,5,0))*CAPA!$B$14,"") -> 5366.6101 | J37: =I37*0.9 -> 4829.9491
B38: Mush Mesa de Centro - Øx0.9x0.26 - Acabamentos Customizados | C38: Ø | D38: 0.9 | E38: 0.26 | G38: =IFERROR(IF('BASE DE DADOS PREÇOS'!$M$71="com",VLOOKUP(CONCATENATE(B38,$G$6),'BASE DE DADOS PREÇOS'!$E:$H,4,0)/(1-SUM($F$1))*VLOOKUP(CAPA!$B$12,'POLITICA DE PREÇO'!#REF!,2,0)*0.95,VLOOKUP(CONCATENATE(B38,$G$6),'BASE DE DADOS PREÇOS'!$E:$H,4,0)/(1-SUM($F$1))*VLOOKUP(CAPA!$B$12,'POLITICA DE PREÇO'!$B$4:$F$100,5,0))*CAPA!$B$14,"") -> 3081.161 | H38: =IFERROR(IF('BASE DE DADOS PREÇOS'!$M$71="com",VLOOKUP(CONCATENATE(B38,$H$6),'BASE DE DADOS PREÇOS'!$E:$H,4,0)/(1-SUM($F$1))*VLOOKUP(CAPA!$B$12,'POLITICA DE PREÇO'!#REF!,2,0)*0.95,VLOOKUP(CONCATENATE(B38,$H$6),'BASE DE DADOS PREÇOS'!$E:$H,4,0)/(1-SUM($F$1))*VLOOKUP(CAPA!$B$12,'POLITICA DE PREÇO'!$B$4:$F$100,5,0))*CAPA!$B$14,"") -> 2412.1364 | I38: =IFERROR(IF('BASE DE DADOS PREÇOS'!$M$71="com",VLOOKUP(CONCATENATE(B38,$I$6),'BASE DE DADOS PREÇOS'!$E:$H,4,0)/(1-SUM($F$1))*VLOOKUP(CAPA!$B$12,'POLITICA DE PREÇO'!#REF!,2,0)*0.95,VLOOKUP(CONCATENATE(B38,$I$6),'BASE DE DADOS PREÇOS'!$E:$H,4,0)/(1-SUM($F$1))*VLOOKUP(CAPA!$B$12,'POLITICA DE PREÇO'!$B$4:$F$100,5,0))*CAPA!$B$14,"") -> 5296.0215 | J38: =I38*0.9 -> 4766.4194
B39: Mush Mesa de Centro - Øx0.9x0.33 - Acabamentos Customizados | C39: Ø | D39: 0.9 | E39: 0.33 | G39: =IFERROR(IF('BASE DE DADOS PREÇOS'!$M$71="com",VLOOKUP(CONCATENATE(B39,$G$6),'BASE DE DADOS PREÇOS'!$E:$H,4,0)/(1-SUM($F$1))*VLOOKUP(CAPA!$B$12,'POLITICA DE PREÇO'!#REF!,2,0)*0.95,VLOOKUP(CONCATENATE(B39,$G$6),'BASE DE DADOS PREÇOS'!$E:$H,4,0)/(1-SUM($F$1))*VLOOKUP(CAPA!$B$12,'POLITICA DE PREÇO'!$B$4:$F$100,5,0))*CAPA!$B$14,"") -> 3235.219 | H39: =IFERROR(IF('BASE DE DADOS PREÇOS'!$M$71="com",VLOOKUP(CONCATENATE(B39,$H$6),'BASE DE DADOS PREÇOS'!$E:$H,4,0)/(1-SUM($F$1))*VLOOKUP(CAPA!$B$12,'POLITICA DE PREÇO'!#REF!,2,0)*0.95,VLOOKUP(CONCATENATE(B39,$H$6),'BASE DE DADOS PREÇOS'!$E:$H,4,0)/(1-SUM($F$1))*VLOOKUP(CAPA!$B$12,'POLITICA DE PREÇO'!$B$4:$F$100,5,0))*CAPA!$B$14,"") -> 2532.7432 | I39: =IFERROR(IF('BASE DE DADOS PREÇOS'!$M$71="com",VLOOKUP(CONCATENATE(B39,$I$6),'BASE DE DADOS PREÇOS'!$E:$H,4,0)/(1-SUM($F$1))*VLOOKUP(CAPA!$B$12,'POLITICA DE PREÇO'!#REF!,2,0)*0.95,VLOOKUP(CONCATENATE(B39,$I$6),'BASE DE DADOS PREÇOS'!$E:$H,4,0)/(1-SUM($F$1))*VLOOKUP(CAPA!$B$12,'POLITICA DE PREÇO'!$B$4:$F$100,5,0))*CAPA!$B$14,"") -> 5560.8226 | J39: =I39*0.9 -> 5004.7403
B40: Mush Mesa de Centro - Øx0.9x0.4 - Acabamentos Customizados | C40: Ø | D40: 0.9 | E40: 0.4 | G40: =IFERROR(IF('BASE DE DADOS PREÇOS'!$M$71="com",VLOOKUP(CONCATENATE(B40,$G$6),'BASE DE DADOS PREÇOS'!$E:$H,4,0)/(1-SUM($F$1))*VLOOKUP(CAPA!$B$12,'POLITICA DE PREÇO'!#REF!,2,0)*0.95,VLOOKUP(CONCATENATE(B40,$G$6),'BASE DE DADOS PREÇOS'!$E:$H,4,0)/(1-SUM($F$1))*VLOOKUP(CAPA!$B$12,'POLITICA DE PREÇO'!$B$4:$F$100,5,0))*CAPA!$B$14,"") -> 3396.98 | H40: =IFERROR(IF('BASE DE DADOS PREÇOS'!$M$71="com",VLOOKUP(CONCATENATE(B40,$H$6),'BASE DE DADOS PREÇOS'!$E:$H,4,0)/(1-SUM($F$1))*VLOOKUP(CAPA!$B$12,'POLITICA DE PREÇO'!#REF!,2,0)*0.95,VLOOKUP(CONCATENATE(B40,$H$6),'BASE DE DADOS PREÇOS'!$E:$H,4,0)/(1-SUM($F$1))*VLOOKUP(CAPA!$B$12,'POLITICA DE PREÇO'!$B$4:$F$100,5,0))*CAPA!$B$14,"") -> 2659.3804 | I40: =IFERROR(IF('BASE DE DADOS PREÇOS'!$M$71="com",VLOOKUP(CONCATENATE(B40,$I$6),'BASE DE DADOS PREÇOS'!$E:$H,4,0)/(1-SUM($F$1))*VLOOKUP(CAPA!$B$12,'POLITICA DE PREÇO'!#REF!,2,0)*0.95,VLOOKUP(CONCATENATE(B40,$I$6),'BASE DE DADOS PREÇOS'!$E:$H,4,0)/(1-SUM($F$1))*VLOOKUP(CAPA!$B$12,'POLITICA DE PREÇO'!$B$4:$F$100,5,0))*CAPA!$B$14,"") -> 5838.8637 | J40: =I40*0.9 -> 5254.9774
B41: Mush Mesa de Centro - Øx1x0.26 - Acabamentos Customizados | C41: Ø | D41: 1 | E41: 0.26 | G41: =IFERROR(IF('BASE DE DADOS PREÇOS'!$M$71="com",VLOOKUP(CONCATENATE(B41,$G$6),'BASE DE DADOS PREÇOS'!$E:$H,4,0)/(1-SUM($F$1))*VLOOKUP(CAPA!$B$12,'POLITICA DE PREÇO'!#REF!,2,0)*0.95,VLOOKUP(CONCATENATE(B41,$G$6),'BASE DE DADOS PREÇOS'!$E:$H,4,0)/(1-SUM($F$1))*VLOOKUP(CAPA!$B$12,'POLITICA DE PREÇO'!$B$4:$F$100,5,0))*CAPA!$B$14,"") -> 3535.3265 | H41: =IFERROR(IF('BASE DE DADOS PREÇOS'!$M$71="com",VLOOKUP(CONCATENATE(B41,$H$6),'BASE DE DADOS PREÇOS'!$E:$H,4,0)/(1-SUM($F$1))*VLOOKUP(CAPA!$B$12,'POLITICA DE PREÇO'!#REF!,2,0)*0.95,VLOOKUP(CONCATENATE(B41,$H$6),'BASE DE DADOS PREÇOS'!$E:$H,4,0)/(1-SUM($F$1))*VLOOKUP(CAPA!$B$12,'POLITICA DE PREÇO'!$B$4:$F$100,5,0))*CAPA!$B$14,"") -> 2713.8605 | I41: =IFERROR(IF('BASE DE DADOS PREÇOS'!$M$71="com",VLOOKUP(CONCATENATE(B41,$I$6),'BASE DE DADOS PREÇOS'!$E:$H,4,0)/(1-SUM($F$1))*VLOOKUP(CAPA!$B$12,'POLITICA DE PREÇO'!#REF!,2,0)*0.95,VLOOKUP(CONCATENATE(B41,$I$6),'BASE DE DADOS PREÇOS'!$E:$H,4,0)/(1-SUM($F$1))*VLOOKUP(CAPA!$B$12,'POLITICA DE PREÇO'!$B$4:$F$100,5,0))*CAPA!$B$14,"") -> 6585.0836 | J41: =I41*0.9 -> 5926.5752
B42: Mush Mesa de Centro - Øx1x0.33 - Acabamentos Customizados | C42: Ø | D42: 1 | E42: 0.33 | G42: =IFERROR(IF('BASE DE DADOS PREÇOS'!$M$71="com",VLOOKUP(CONCATENATE(B42,$G$6),'BASE DE DADOS PREÇOS'!$E:$H,4,0)/(1-SUM($F$1))*VLOOKUP(CAPA!$B$12,'POLITICA DE PREÇO'!#REF!,2,0)*0.95,VLOOKUP(CONCATENATE(B42,$G$6),'BASE DE DADOS PREÇOS'!$E:$H,4,0)/(1-SUM($F$1))*VLOOKUP(CAPA!$B$12,'POLITICA DE PREÇO'!$B$4:$F$100,5,0))*CAPA!$B$14,"") -> 3721.3963 | H42: =IFERROR(IF('BASE DE DADOS PREÇOS'!$M$71="com",VLOOKUP(CONCATENATE(B42,$H$6),'BASE DE DADOS PREÇOS'!$E:$H,4,0)/(1-SUM($F$1))*VLOOKUP(CAPA!$B$12,'POLITICA DE PREÇO'!#REF!,2,0)*0.95,VLOOKUP(CONCATENATE(B42,$H$6),'BASE DE DADOS PREÇOS'!$E:$H,4,0)/(1-SUM($F$1))*VLOOKUP(CAPA!$B$12,'POLITICA DE PREÇO'!$B$4:$F$100,5,0))*CAPA!$B$14,"") -> 2856.6952 | I42: =IFERROR(IF('BASE DE DADOS PREÇOS'!$M$71="com",VLOOKUP(CONCATENATE(B42,$I$6),'BASE DE DADOS PREÇOS'!$E:$H,4,0)/(1-SUM($F$1))*VLOOKUP(CAPA!$B$12,'POLITICA DE PREÇO'!#REF!,2,0)*0.95,VLOOKUP(CONCATENATE(B42,$I$6),'BASE DE DADOS PREÇOS'!$E:$H,4,0)/(1-SUM($F$1))*VLOOKUP(CAPA!$B$12,'POLITICA DE PREÇO'!$B$4:$F$100,5,0))*CAPA!$B$14,"") -> 6931.6669 | J42: =I42*0.9 -> 6238.5002
B43: Mush Mesa de Centro - Øx1.1x0.26 - Acabamentos Customizados | C43: Ø | D43: 1.1 | E43: 0.26 | G43: =IFERROR(IF('BASE DE DADOS PREÇOS'!$M$71="com",VLOOKUP(CONCATENATE(B43,$G$6),'BASE DE DADOS PREÇOS'!$E:$H,4,0)/(1-SUM($F$1))*VLOOKUP(CAPA!$B$12,'POLITICA DE PREÇO'!#REF!,2,0)*0.95,VLOOKUP(CONCATENATE(B43,$G$6),'BASE DE DADOS PREÇOS'!$E:$H,4,0)/(1-SUM($F$1))*VLOOKUP(CAPA!$B$12,'POLITICA DE PREÇO'!$B$4:$F$100,5,0))*CAPA!$B$14,"") -> 3868.4113 | H43: =IFERROR(IF('BASE DE DADOS PREÇOS'!$M$71="com",VLOOKUP(CONCATENATE(B43,$H$6),'BASE DE DADOS PREÇOS'!$E:$H,4,0)/(1-SUM($F$1))*VLOOKUP(CAPA!$B$12,'POLITICA DE PREÇO'!#REF!,2,0)*0.95,VLOOKUP(CONCATENATE(B43,$H$6),'BASE DE DADOS PREÇOS'!$E:$H,4,0)/(1-SUM($F$1))*VLOOKUP(CAPA!$B$12,'POLITICA DE PREÇO'!$B$4:$F$100,5,0))*CAPA!$B$14,"") -> 2902.7796 | I43: =IFERROR(IF('BASE DE DADOS PREÇOS'!$M$71="com",VLOOKUP(CONCATENATE(B43,$I$6),'BASE DE DADOS PREÇOS'!$E:$H,4,0)/(1-SUM($F$1))*VLOOKUP(CAPA!$B$12,'POLITICA DE PREÇO'!#REF!,2,0)*0.95,VLOOKUP(CONCATENATE(B43,$I$6),'BASE DE DADOS PREÇOS'!$E:$H,4,0)/(1-SUM($F$1))*VLOOKUP(CAPA!$B$12,'POLITICA DE PREÇO'!$B$4:$F$100,5,0))*CAPA!$B$14,"") -> 7998.9264 | J43: =I43*0.9 -> 7199.0337
... B51: Picasso Mesa de Centro - Øx1.2x0.4 - Acabamentos Customizados | C51: Ø | D51: 1.2 | E51: 0.4 | G51: =IFERROR(IF('BASE DE DADOS PREÇOS'!$M$71="com",VLOOKUP(CONCATENATE(B51,$G$6),'BASE DE DADOS PREÇOS'!$E:$H,4,0)/(1-SUM($F$1))*VLOOKUP(CAPA!$B$12,'POLITICA DE PREÇO'!#REF!,2,0)*0.95,VLOOKUP(CONCATENATE(B51,$G$6),'BASE DE DADOS PREÇOS'!$E:$H,4,0)/(1-SUM($F$1))*VLOOKUP(CAPA!$B$12,'POLITICA DE PREÇO'!$B$4:$F$100,5,0))*CAPA!$B$14,"") -> 5001.9591 | H51: =IFERROR(IF('BASE DE DADOS PREÇOS'!$M$71="com",VLOOKUP(CONCATENATE(B51,$H$6),'BASE DE DADOS PREÇOS'!$E:$H,4,0)/(1-SUM($F$1))*VLOOKUP(CAPA!$B$12,'POLITICA DE PREÇO'!#REF!,2,0)*0.95,VLOOKUP(CONCATENATE(B51,$H$6),'BASE DE DADOS PREÇOS'!$E:$H,4,0)/(1-SUM($F$1))*VLOOKUP(CAPA!$B$12,'POLITICA DE PREÇO'!$B$4:$F$100,5,0))*CAPA!$B$14,"") -> 3519.6293 | I51: =IFERROR(IF('BASE DE DADOS PREÇOS'!$M$71="com",VLOOKUP(CONCATENATE(B51,$I$6),'BASE DE DADOS PREÇOS'!$E:$H,4,0)/(1-SUM($F$1))*VLOOKUP(CAPA!$B$12,'POLITICA DE PREÇO'!#REF!,2,0)*0.95,VLOOKUP(CONCATENATE(B51,$I$6),'BASE DE DADOS PREÇOS'!$E:$H,4,0)/(1-SUM($F$1))*VLOOKUP(CAPA!$B$12,'POLITICA DE PREÇO'!$B$4:$F$100,5,0))*CAPA!$B$14,"") -> 9172.3118 | J51: =I51*0.9 -> 8255.0806
B52: Picasso Mesa de Centro - 1.6x0.9x0.26 - Acabamentos Customizados | C52: 1.6 | D52: 0.9 | E52: 0.26 | G52: =IFERROR(IF('BASE DE DADOS PREÇOS'!$M$71="com",VLOOKUP(CONCATENATE(B52,$G$6),'BASE DE DADOS PREÇOS'!$E:$H,4,0)/(1-SUM($F$1))*VLOOKUP(CAPA!$B$12,'POLITICA DE PREÇO'!#REF!,2,0)*0.95,VLOOKUP(CONCATENATE(B52,$G$6),'BASE DE DADOS PREÇOS'!$E:$H,4,0)/(1-SUM($F$1))*VLOOKUP(CAPA!$B$12,'POLITICA DE PREÇO'!$B$4:$F$100,5,0))*CAPA!$B$14,"") -> 4611.3095 | H52: =IFERROR(IF('BASE DE DADOS PREÇOS'!$M$71="com",VLOOKUP(CONCATENATE(B52,$H$6),'BASE DE DADOS PREÇOS'!$E:$H,4,0)/(1-SUM($F$1))*VLOOKUP(CAPA!$B$12,'POLITICA DE PREÇO'!#REF!,2,0)*0.95,VLOOKUP(CONCATENATE(B52,$H$6),'BASE DE DADOS PREÇOS'!$E:$H,4,0)/(1-SUM($F$1))*VLOOKUP(CAPA!$B$12,'POLITICA DE PREÇO'!$B$4:$F$100,5,0))*CAPA!$B$14,"") -> 3276.5587 | I52: =IFERROR(IF('BASE DE DADOS PREÇOS'!$M$71="com",VLOOKUP(CONCATENATE(B52,$I$6),'BASE DE DADOS PREÇOS'!$E:$H,4,0)/(1-SUM($F$1))*VLOOKUP(CAPA!$B$12,'POLITICA DE PREÇO'!#REF!,2,0)*0.95,VLOOKUP(CONCATENATE(B52,$I$6),'BASE DE DADOS PREÇOS'!$E:$H,4,0)/(1-SUM($F$1))*VLOOKUP(CAPA!$B$12,'POLITICA DE PREÇO'!$B$4:$F$100,5,0))*CAPA!$B$14,"") -> 8069.2153 | J52: =I52*0.9 -> 7262.2938
B53: Picasso Mesa de Centro - 1.6x0.9x0.33 - Acabamentos Customizados | C53: 1.6 | D53: 0.9 | E53: 0.33 | G53: =IFERROR(IF('BASE DE DADOS PREÇOS'!$M$71="com",VLOOKUP(CONCATENATE(B53,$G$6),'BASE DE DADOS PREÇOS'!$E:$H,4,0)/(1-SUM($F$1))*VLOOKUP(CAPA!$B$12,'POLITICA DE PREÇO'!#REF!,2,0)*0.95,VLOOKUP(CONCATENATE(B53,$G$6),'BASE DE DADOS PREÇOS'!$E:$H,4,0)/(1-SUM($F$1))*VLOOKUP(CAPA!$B$12,'POLITICA DE PREÇO'!$B$4:$F$100,5,0))*CAPA!$B$14,"") -> 4887.9881 | H53: =IFERROR(IF('BASE DE DADOS PREÇOS'!$M$71="com",VLOOKUP(CONCATENATE(B53,$H$6),'BASE DE DADOS PREÇOS'!$E:$H,4,0)/(1-SUM($F$1))*VLOOKUP(CAPA!$B$12,'POLITICA DE PREÇO'!#REF!,2,0)*0.95,VLOOKUP(CONCATENATE(B53,$H$6),'BASE DE DADOS PREÇOS'!$E:$H,4,0)/(1-SUM($F$1))*VLOOKUP(CAPA!$B$12,'POLITICA DE PREÇO'!$B$4:$F$100,5,0))*CAPA!$B$14,"") -> 3473.1522 | I53: =IFERROR(IF('BASE DE DADOS PREÇOS'!$M$71="com",VLOOKUP(CONCATENATE(B53,$I$6),'BASE DE DADOS PREÇOS'!$E:$H,4,0)/(1-SUM($F$1))*VLOOKUP(CAPA!$B$12,'POLITICA DE PREÇO'!#REF!,2,0)*0.95,VLOOKUP(CONCATENATE(B53,$I$6),'BASE DE DADOS PREÇOS'!$E:$H,4,0)/(1-SUM($F$1))*VLOOKUP(CAPA!$B$12,'POLITICA DE PREÇO'!$B$4:$F$100,5,0))*CAPA!$B$14,"") -> 8553.3683 | J53: =I53*0.9 -> 7698.0314
B54: Picasso Mesa de Centro - 1.6x0.9x0.4 - Acabamentos Customizados | C54: 1.6 | D54: 0.9 | E54: 0.4 | G54: =IFERROR(IF('BASE DE DADOS PREÇOS'!$M$71="com",VLOOKUP(CONCATENATE(B54,$G$6),'BASE DE DADOS PREÇOS'!$E:$H,4,0)/(1-SUM($F$1))*VLOOKUP(CAPA!$B$12,'POLITICA DE PREÇO'!#REF!,2,0)*0.95,VLOOKUP(CONCATENATE(B54,$G$6),'BASE DE DADOS PREÇOS'!$E:$H,4,0)/(1-SUM($F$1))*VLOOKUP(CAPA!$B$12,'POLITICA DE PREÇO'!$B$4:$F$100,5,0))*CAPA!$B$14,"") -> 5091.6543 | H54: =IFERROR(IF('BASE DE DADOS PREÇOS'!$M$71="com",VLOOKUP(CONCATENATE(B54,$H$6),'BASE DE DADOS PREÇOS'!$E:$H,4,0)/(1-SUM($F$1))*VLOOKUP(CAPA!$B$12,'POLITICA DE PREÇO'!#REF!,2,0)*0.95,VLOOKUP(CONCATENATE(B54,$H$6),'BASE DE DADOS PREÇOS'!$E:$H,4,0)/(1-SUM($F$1))*VLOOKUP(CAPA!$B$12,'POLITICA DE PREÇO'!$B$4:$F$100,5,0))*CAPA!$B$14,"") -> 3617.8669 | I54: =IFERROR(IF('BASE DE DADOS PREÇOS'!$M$71="com",VLOOKUP(CONCATENATE(B54,$I$6),'BASE DE DADOS PREÇOS'!$E:$H,4,0)/(1-SUM($F$1))*VLOOKUP(CAPA!$B$12,'POLITICA DE PREÇO'!#REF!,2,0)*0.95,VLOOKUP(CONCATENATE(B54,$I$6),'BASE DE DADOS PREÇOS'!$E:$H,4,0)/(1-SUM($F$1))*VLOOKUP(CAPA!$B$12,'POLITICA DE PREÇO'!$B$4:$F$100,5,0))*CAPA!$B$14,"") -> 8909.7586 | J54: =I54*0.9 -> 8018.7827
B55: Picasso Mesa de Centro - 1.65x0.75x0.26 - Acabamentos Customizados | C55: 1.65 | D55: 0.75 | E55: 0.26 | G55: =IFERROR(IF('BASE DE DADOS PREÇOS'!$M$71="com",VLOOKUP(CONCATENATE(B55,$G$6),'BASE DE DADOS PREÇOS'!$E:$H,4,0)/(1-SUM($F$1))*VLOOKUP(CAPA!$B$12,'POLITICA DE PREÇO'!#REF!,2,0)*0.95,VLOOKUP(CONCATENATE(B55,$G$6),'BASE DE DADOS PREÇOS'!$E:$H,4,0)/(1-SUM($F$1))*VLOOKUP(CAPA!$B$12,'POLITICA DE PREÇO'!$B$4:$F$100,5,0))*CAPA!$B$14,"") -> 4467.5889 | H55: =IFERROR(IF('BASE DE DADOS PREÇOS'!$M$71="com",VLOOKUP(CONCATENATE(B55,$H$6),'BASE DE DADOS PREÇOS'!$E:$H,4,0)/(1-SUM($F$1))*VLOOKUP(CAPA!$B$12,'POLITICA DE PREÇO'!#REF!,2,0)*0.95,VLOOKUP(CONCATENATE(B55,$H$6),'BASE DE DADOS PREÇOS'!$E:$H,4,0)/(1-SUM($F$1))*VLOOKUP(CAPA!$B$12,'POLITICA DE PREÇO'!$B$4:$F$100,5,0))*CAPA!$B$14,"") -> 3262.1866 | I55: =IFERROR(IF('BASE DE DADOS PREÇOS'!$M$71="com",VLOOKUP(CONCATENATE(B55,$I$6),'BASE DE DADOS PREÇOS'!$E:$H,4,0)/(1-SUM($F$1))*VLOOKUP(CAPA!$B$12,'POLITICA DE PREÇO'!#REF!,2,0)*0.95,VLOOKUP(CONCATENATE(B55,$I$6),'BASE DE DADOS PREÇOS'!$E:$H,4,0)/(1-SUM($F$1))*VLOOKUP(CAPA!$B$12,'POLITICA DE PREÇO'!$B$4:$F$100,5,0))*CAPA!$B$14,"") -> 7572.7789 | J55: =I55*0.9 -> 6815.501
B56: Picasso Mesa de Centro - 1.65x0.75x0.33 - Acabamentos Customizados | C56: 1.65 | D56: 0.75 | E56: 0.33 | G56: =IFERROR(IF('BASE DE DADOS PREÇOS'!$M$71="com",VLOOKUP(CONCATENATE(B56,$G$6),'BASE DE DADOS PREÇOS'!$E:$H,4,0)/(1-SUM($F$1))*VLOOKUP(CAPA!$B$12,'POLITICA DE PREÇO'!#REF!,2,0)*0.95,VLOOKUP(CONCATENATE(B56,$G$6),'BASE DE DADOS PREÇOS'!$E:$H,4,0)/(1-SUM($F$1))*VLOOKUP(CAPA!$B$12,'POLITICA DE PREÇO'!$B$4:$F$100,5,0))*CAPA!$B$14,"") -> 4735.6442 | H56: =IFERROR(IF('BASE DE DADOS PREÇOS'!$M$71="com",VLOOKUP(CONCATENATE(B56,$H$6),'BASE DE DADOS PREÇOS'!$E:$H,4,0)/(1-SUM($F$1))*VLOOKUP(CAPA!$B$12,'POLITICA DE PREÇO'!#REF!,2,0)*0.95,VLOOKUP(CONCATENATE(B56,$H$6),'BASE DE DADOS PREÇOS'!$E:$H,4,0)/(1-SUM($F$1))*VLOOKUP(CAPA!$B$12,'POLITICA DE PREÇO'!$B$4:$F$100,5,0))*CAPA!$B$14,"") -> 3457.9178 | I56: =IFERROR(IF('BASE DE DADOS PREÇOS'!$M$71="com",VLOOKUP(CONCATENATE(B56,$I$6),'BASE DE DADOS PREÇOS'!$E:$H,4,0)/(1-SUM($F$1))*VLOOKUP(CAPA!$B$12,'POLITICA DE PREÇO'!#REF!,2,0)*0.95,VLOOKUP(CONCATENATE(B56,$I$6),'BASE DE DADOS PREÇOS'!$E:$H,4,0)/(1-SUM($F$1))*VLOOKUP(CAPA!$B$12,'POLITICA DE PREÇO'!$B$4:$F$100,5,0))*CAPA!$B$14,"") -> 8027.1456 | J56: =I56*0.9 -> 7224.431
B57: Saturnia Mesa de Centro - 0.91x0.76x0.33 - Acabamentos Customizados | C57: 0.91 | D57: 0.76 | E57: 0.33 | G57: =IFERROR(IF('BASE DE DADOS PREÇOS'!$M$71="com",VLOOKUP(CONCATENATE(B57,$G$6),'BASE DE DADOS PREÇOS'!$E:$H,4,0)/(1-SUM($F$1))*VLOOKUP(CAPA!$B$12,'POLITICA DE PREÇO'!#REF!,2,0)*0.95,VLOOKUP(CONCATENATE(B57,$G$6),'BASE DE DADOS PREÇOS'!$E:$H,4,0)/(1-SUM($F$1))*VLOOKUP(CAPA!$B$12,'POLITICA DE PREÇO'!$B$4:$F$100,5,0))*CAPA!$B$14,"") -> 3094.6861 | H57: =IFERROR(IF('BASE DE DADOS PREÇOS'!$M$71="com",VLOOKUP(CONCATENATE(B57,$H$6),'BASE DE DADOS PREÇOS'!$E:$H,4,0)/(1-SUM($F$1))*VLOOKUP(CAPA!$B$12,'POLITICA DE PREÇO'!#REF!,2,0)*0.95,VLOOKUP(CONCATENATE(B57,$H$6),'BASE DE DADOS PREÇOS'!$E:$H,4,0)/(1-SUM($F$1))*VLOOKUP(CAPA!$B$12,'POLITICA DE PREÇO'!$B$4:$F$100,5,0))*CAPA!$B$14,"") -> 2357.9382 | I57: =IFERROR(IF('BASE DE DADOS PREÇOS'!$M$71="com",VLOOKUP(CONCATENATE(B57,$I$6),'BASE DE DADOS PREÇOS'!$E:$H,4,0)/(1-SUM($F$1))*VLOOKUP(CAPA!$B$12,'POLITICA DE PREÇO'!#REF!,2,0)*0.95,VLOOKUP(CONCATENATE(B57,$I$6),'BASE DE DADOS PREÇOS'!$E:$H,4,0)/(1-SUM($F$1))*VLOOKUP(CAPA!$B$12,'POLITICA DE PREÇO'!$B$4:$F$100,5,0))*CAPA!$B$14,"") -> 5256.1704 | J57: =I57*0.9 -> 4730.5533
B58: Saturnia Mesa de Centro - 0.91x0.76x0.4 - Acabamentos Customizados | C58: 0.91 | D58: 0.76 | E58: 0.4 | G58: =IFERROR(IF('BASE DE DADOS PREÇOS'!$M$71="com",VLOOKUP(CONCATENATE(B58,$G$6),'BASE DE DADOS PREÇOS'!$E:$H,4,0)/(1-SUM($F$1))*VLOOKUP(CAPA!$B$12,'POLITICA DE PREÇO'!#REF!,2,0)*0.95,VLOOKUP(CONCATENATE(B58,$G$6),'BASE DE DADOS PREÇOS'!$E:$H,4,0)/(1-SUM($F$1))*VLOOKUP(CAPA!$B$12,'POLITICA DE PREÇO'!$B$4:$F$100,5,0))*CAPA!$B$14,"") -> 3280.3673 | H58: =IFERROR(IF('BASE DE DADOS PREÇOS'!$M$71="com",VLOOKUP(CONCATENATE(B58,$H$6),'BASE DE DADOS PREÇOS'!$E:$H,4,0)/(1-SUM($F$1))*VLOOKUP(CAPA!$B$12,'POLITICA DE PREÇO'!#REF!,2,0)*0.95,VLOOKUP(CONCATENATE(B58,$H$6),'BASE DE DADOS PREÇOS'!$E:$H,4,0)/(1-SUM($F$1))*VLOOKUP(CAPA!$B$12,'POLITICA DE PREÇO'!$B$4:$F$100,5,0))*CAPA!$B$14,"") -> 2499.4145 | I58: =IFERROR(IF('BASE DE DADOS PREÇOS'!$M$71="com",VLOOKUP(CONCATENATE(B58,$I$6),'BASE DE DADOS PREÇOS'!$E:$H,4,0)/(1-SUM($F$1))*VLOOKUP(CAPA!$B$12,'POLITICA DE PREÇO'!#REF!,2,0)*0.95,VLOOKUP(CONCATENATE(B58,$I$6),'BASE DE DADOS PREÇOS'!$E:$H,4,0)/(1-SUM($F$1))*VLOOKUP(CAPA!$B$12,'POLITICA DE PREÇO'!$B$4:$F$100,5,0))*CAPA!$B$14,"") -> 5571.5406 | J58: =I58*0.9 -> 5014.3865
B59: Saturnia Mesa de Centro - 1.1x0.71x0.33 - Acabamentos Customizados | C59: 1.1 | D59: 0.71 | E59: 0.33 | G59: =IFERROR(IF('BASE DE DADOS PREÇOS'!$M$71="com",VLOOKUP(CONCATENATE(B59,$G$6),'BASE DE DADOS PREÇOS'!$E:$H,4,0)/(1-SUM($F$1))*VLOOKUP(CAPA!$B$12,'POLITICA DE PREÇO'!#REF!,2,0)*0.95,VLOOKUP(CONCATENATE(B59,$G$6),'BASE DE DADOS PREÇOS'!$E:$H,4,0)/(1-SUM($F$1))*VLOOKUP(CAPA!$B$12,'POLITICA DE PREÇO'!$B$4:$F$100,5,0))*CAPA!$B$14,"") -> 3497.714 | H59: =IFERROR(IF('BASE DE DADOS PREÇOS'!$M$71="com",VLOOKUP(CONCATENATE(B59,$H$6),'BASE DE DADOS PREÇOS'!$E:$H,4,0)/(1-SUM($F$1))*VLOOKUP(CAPA!$B$12,'POLITICA DE PREÇO'!#REF!,2,0)*0.95,VLOOKUP(CONCATENATE(B59,$H$6),'BASE DE DADOS PREÇOS'!$E:$H,4,0)/(1-SUM($F$1))*VLOOKUP(CAPA!$B$12,'POLITICA DE PREÇO'!$B$4:$F$100,5,0))*CAPA!$B$14,"") -> 2431.8876 | I59: =IFERROR(IF('BASE DE DADOS PREÇOS'!$M$71="com",VLOOKUP(CONCATENATE(B59,$I$6),'BASE DE DADOS PREÇOS'!$E:$H,4,0)/(1-SUM($F$1))*VLOOKUP(CAPA!$B$12,'POLITICA DE PREÇO'!#REF!,2,0)*0.95,VLOOKUP(CONCATENATE(B59,$I$6),'BASE DE DADOS PREÇOS'!$E:$H,4,0)/(1-SUM($F$1))*VLOOKUP(CAPA!$B$12,'POLITICA DE PREÇO'!$B$4:$F$100,5,0))*CAPA!$B$14,"") -> 6271.9718 | J59: =I59*0.9 -> 5644.7746
B60: Saturnia Mesa de Centro - 1.1x0.71x0.4 - Acabamentos Customizados | C60: 1.1 | D60: 0.71 | E60: 0.4 | G60: =IFERROR(IF('BASE DE DADOS PREÇOS'!$M$71="com",VLOOKUP(CONCATENATE(B60,$G$6),'BASE DE DADOS PREÇOS'!$E:$H,4,0)/(1-SUM($F$1))*VLOOKUP(CAPA!$B$12,'POLITICA DE PREÇO'!#REF!,2,0)*0.95,VLOOKUP(CONCATENATE(B60,$G$6),'BASE DE DADOS PREÇOS'!$E:$H,4,0)/(1-SUM($F$1))*VLOOKUP(CAPA!$B$12,'POLITICA DE PREÇO'!$B$4:$F$100,5,0))*CAPA!$B$14,"") -> 3707.5769 | H60: =IFERROR(IF('BASE DE DADOS PREÇOS'!$M$71="com",VLOOKUP(CONCATENATE(B60,$H$6),'BASE DE DADOS PREÇOS'!$E:$H,4,0)/(1-SUM($F$1))*VLOOKUP(CAPA!$B$12,'POLITICA DE PREÇO'!#REF!,2,0)*0.95,VLOOKUP(CONCATENATE(B60,$H$6),'BASE DE DADOS PREÇOS'!$E:$H,4,0)/(1-SUM($F$1))*VLOOKUP(CAPA!$B$12,'POLITICA DE PREÇO'!$B$4:$F$100,5,0))*CAPA!$B$14,"") -> 2577.8009 | I60: =IFERROR(IF('BASE DE DADOS PREÇOS'!$M$71="com",VLOOKUP(CONCATENATE(B60,$I$6),'BASE DE DADOS PREÇOS'!$E:$H,4,0)/(1-SUM($F$1))*VLOOKUP(CAPA!$B$12,'POLITICA DE PREÇO'!#REF!,2,0)*0.95,VLOOKUP(CONCATENATE(B60,$I$6),'BASE DE DADOS PREÇOS'!$E:$H,4,0)/(1-SUM($F$1))*VLOOKUP(CAPA!$B$12,'POLITICA DE PREÇO'!$B$4:$F$100,5,0))*CAPA!$B$14,"") -> 6648.2901 | J60: =I60*0.9 -> 5983.4611
B61: Saturnia Mesa de Centro - 1.52x0.91x0.26 - Acabamentos Customizados | C61: 1.52 | D61: 0.91 | E61: 0.26 | G61: =IFERROR(IF('BASE DE DADOS PREÇOS'!$M$71="com",VLOOKUP(CONCATENATE(B61,$G$6),'BASE DE DADOS PREÇOS'!$E:$H,4,0)/(1-SUM($F$1))*VLOOKUP(CAPA!$B$12,'POLITICA DE PREÇO'!#REF!,2,0)*0.95,VLOOKUP(CONCATENATE(B61,$G$6),'BASE DE DADOS PREÇOS'!$E:$H,4,0)/(1-SUM($F$1))*VLOOKUP(CAPA!$B$12,'POLITICA DE PREÇO'!$B$4:$F$100,5,0))*CAPA!$B$14,"") -> 4063.0768 | H61: =IFERROR(IF('BASE DE DADOS PREÇOS'!$M$71="com",VLOOKUP(CONCATENATE(B61,$H$6),'BASE DE DADOS PREÇOS'!$E:$H,4,0)/(1-SUM($F$1))*VLOOKUP(CAPA!$B$12,'POLITICA DE PREÇO'!#REF!,2,0)*0.95,VLOOKUP(CONCATENATE(B61,$H$6),'BASE DE DADOS PREÇOS'!$E:$H,4,0)/(1-SUM($F$1))*VLOOKUP(CAPA!$B$12,'POLITICA DE PREÇO'!$B$4:$F$100,5,0))*CAPA!$B$14,"") -> 2576.5616 | I61: =IFERROR(IF('BASE DE DADOS PREÇOS'!$M$71="com",VLOOKUP(CONCATENATE(B61,$I$6),'BASE DE DADOS PREÇOS'!$E:$H,4,0)/(1-SUM($F$1))*VLOOKUP(CAPA!$B$12,'POLITICA DE PREÇO'!#REF!,2,0)*0.95,VLOOKUP(CONCATENATE(B61,$I$6),'BASE DE DADOS PREÇOS'!$E:$H,4,0)/(1-SUM($F$1))*VLOOKUP(CAPA!$B$12,'POLITICA DE PREÇO'!$B$4:$F$100,5,0))*CAPA!$B$14,"") -> 7853.876 | J61: =I61*0.9 -> 7068.4884
B62: Saturnia Mesa de Centro - 1.52x0.91x0.33 - Acabamentos Customizados | C62: 1.52 | D62: 0.91 | E62: 0.33 | G62: =IFERROR(IF('BASE DE DADOS PREÇOS'!$M$71="com",VLOOKUP(CONCATENATE(B62,$G$6),'BASE DE DADOS PREÇOS'!$E:$H,4,0)/(1-SUM($F$1))*VLOOKUP(CAPA!$B$12,'POLITICA DE PREÇO'!#REF!,2,0)*0.95,VLOOKUP(CONCATENATE(B62,$G$6),'BASE DE DADOS PREÇOS'!$E:$H,4,0)/(1-SUM($F$1))*VLOOKUP(CAPA!$B$12,'POLITICA DE PREÇO'!$B$4:$F$100,5,0))*CAPA!$B$14,"") -> 4306.8614 | H62: =IFERROR(IF('BASE DE DADOS PREÇOS'!$M$71="com",VLOOKUP(CONCATENATE(B62,$H$6),'BASE DE DADOS PREÇOS'!$E:$H,4,0)/(1-SUM($F$1))*VLOOKUP(CAPA!$B$12,'POLITICA DE PREÇO'!#REF!,2,0)*0.95,VLOOKUP(CONCATENATE(B62,$H$6),'BASE DE DADOS PREÇOS'!$E:$H,4,0)/(1-SUM($F$1))*VLOOKUP(CAPA!$B$12,'POLITICA DE PREÇO'!$B$4:$F$100,5,0))*CAPA!$B$14,"") -> 2731.1553 | I62: =IFERROR(IF('BASE DE DADOS PREÇOS'!$M$71="com",VLOOKUP(CONCATENATE(B62,$I$6),'BASE DE DADOS PREÇOS'!$E:$H,4,0)/(1-SUM($F$1))*VLOOKUP(CAPA!$B$12,'POLITICA DE PREÇO'!#REF!,2,0)*0.95,VLOOKUP(CONCATENATE(B62,$I$6),'BASE DE DADOS PREÇOS'!$E:$H,4,0)/(1-SUM($F$1))*VLOOKUP(CAPA!$B$12,'POLITICA DE PREÇO'!$B$4:$F$100,5,0))*CAPA!$B$14,"") -> 8325.1085 | J62: =I62*0.9 -> 7492.5977
B63: Saturnia Mesa de Centro - 1.8x1x0.26 - Acabamentos Customizados | C63: 1.8 | D63: 1 | E63: 0.26 | G63: =IFERROR(IF('BASE DE DADOS PREÇOS'!$M$71="com",VLOOKUP(CONCATENATE(B63,$G$6),'BASE DE DADOS PREÇOS'!$E:$H,4,0)/(1-SUM($F$1))*VLOOKUP(CAPA!$B$12,'POLITICA DE PREÇO'!#REF!,2,0)*0.95,VLOOKUP(CONCATENATE(B63,$G$6),'BASE DE DADOS PREÇOS'!$E:$H,4,0)/(1-SUM($F$1))*VLOOKUP(CAPA!$B$12,'POLITICA DE PREÇO'!$B$4:$F$100,5,0))*CAPA!$B$14,"") -> 5762.867 | H63: =IFERROR(IF('BASE DE DADOS PREÇOS'!$M$71="com",VLOOKUP(CONCATENATE(B63,$H$6),'BASE DE DADOS PREÇOS'!$E:$H,4,0)/(1-SUM($F$1))*VLOOKUP(CAPA!$B$12,'POLITICA DE PREÇO'!#REF!,2,0)*0.95,VLOOKUP(CONCATENATE(B63,$H$6),'BASE DE DADOS PREÇOS'!$E:$H,4,0)/(1-SUM($F$1))*VLOOKUP(CAPA!$B$12,'POLITICA DE PREÇO'!$B$4:$F$100,5,0))*CAPA!$B$14,"") -> 3604.4344 | I63: =IFERROR(IF('BASE DE DADOS PREÇOS'!$M$71="com",VLOOKUP(CONCATENATE(B63,$I$6),'BASE DE DADOS PREÇOS'!$E:$H,4,0)/(1-SUM($F$1))*VLOOKUP(CAPA!$B$12,'POLITICA DE PREÇO'!#REF!,2,0)*0.95,VLOOKUP(CONCATENATE(B63,$I$6),'BASE DE DADOS PREÇOS'!$E:$H,4,0)/(1-SUM($F$1))*VLOOKUP(CAPA!$B$12,'POLITICA DE PREÇO'!$B$4:$F$100,5,0))*CAPA!$B$14,"") -> 11915.671 | J63: =I63*0.9 -> 10724.104
B64: Saturnia Mesa de Centro - 1.8x1x0.33 - Acabamentos Customizados | C64: 1.8 | D64: 1 | E64: 0.33 | G64: =IFERROR(IF('BASE DE DADOS PREÇOS'!$M$71="com",VLOOKUP(CONCATENATE(B64,$G$6),'BASE DE DADOS PREÇOS'!$E:$H,4,0)/(1-SUM($F$1))*VLOOKUP(CAPA!$B$12,'POLITICA DE PREÇO'!#REF!,2,0)*0.95,VLOOKUP(CONCATENATE(B64,$G$6),'BASE DE DADOS PREÇOS'!$E:$H,4,0)/(1-SUM($F$1))*VLOOKUP(CAPA!$B$12,'POLITICA DE PREÇO'!$B$4:$F$100,5,0))*CAPA!$B$14,"") -> 5867.9576 | H64: =IFERROR(IF('BASE DE DADOS PREÇOS'!$M$71="com",VLOOKUP(CONCATENATE(B64,$H$6),'BASE DE DADOS PREÇOS'!$E:$H,4,0)/(1-SUM($F$1))*VLOOKUP(CAPA!$B$12,'POLITICA DE PREÇO'!#REF!,2,0)*0.95,VLOOKUP(CONCATENATE(B64,$H$6),'BASE DE DADOS PREÇOS'!$E:$H,4,0)/(1-SUM($F$1))*VLOOKUP(CAPA!$B$12,'POLITICA DE PREÇO'!$B$4:$F$100,5,0))*CAPA!$B$14,"") -> 3709.5277 | I64: =IFERROR(IF('BASE DE DADOS PREÇOS'!$M$71="com",VLOOKUP(CONCATENATE(B64,$I$6),'BASE DE DADOS PREÇOS'!$E:$H,4,0)/(1-SUM($F$1))*VLOOKUP(CAPA!$B$12,'POLITICA DE PREÇO'!#REF!,2,0)*0.95,VLOOKUP(CONCATENATE(B64,$I$6),'BASE DE DADOS PREÇOS'!$E:$H,4,0)/(1-SUM($F$1))*VLOOKUP(CAPA!$B$12,'POLITICA DE PREÇO'!$B$4:$F$100,5,0))*CAPA!$B$14,"") -> 12032.443 | J64: =I64*0.9 -> 10829.199
B65: Tressa Mesa de Centro Orgânico I Tampo inteiro - 1.2x0.8x0.26 - Acabamentos Customizados | C65: 1.2 | D65: 0.8 | E65: 0.26 | G65: =IFERROR(IF('BASE DE DADOS PREÇOS'!$M$71="com",VLOOKUP(CONCATENATE(B65,$G$6),'BASE DE DADOS PREÇOS'!$E:$H,4,0)/(1-SUM($F$1))*VLOOKUP(CAPA!$B$12,'POLITICA DE PREÇO'!#REF!,2,0)*0.95,VLOOKUP(CONCATENATE(B65,$G$6),'BASE DE DADOS PREÇOS'!$E:$H,4,0)/(1-SUM($F$1))*VLOOKUP(CAPA!$B$12,'POLITICA DE PREÇO'!$B$4:$F$100,5,0))*CAPA!$B$14,"") -> 3489.0584 | H65: =IFERROR(IF('BASE DE DADOS PREÇOS'!$M$71="com",VLOOKUP(CONCATENATE(B65,$H$6),'BASE DE DADOS PREÇOS'!$E:$H,4,0)/(1-SUM($F$1))*VLOOKUP(CAPA!$B$12,'POLITICA DE PREÇO'!#REF!,2,0)*0.95,VLOOKUP(CONCATENATE(B65,$H$6),'BASE DE DADOS PREÇOS'!$E:$H,4,0)/(1-SUM($F$1))*VLOOKUP(CAPA!$B$12,'POLITICA DE PREÇO'!$B$4:$F$100,5,0))*CAPA!$B$14,"") -> 3091.8605 | I65: =IFERROR(IF('BASE DE DADOS PREÇOS'!$M$71="com",VLOOKUP(CONCATENATE(B65,$I$6),'BASE DE DADOS PREÇOS'!$E:$H,4,0)/(1-SUM($F$1))*VLOOKUP(CAPA!$B$12,'POLITICA DE PREÇO'!#REF!,2,0)*0.95,VLOOKUP(CONCATENATE(B65,$I$6),'BASE DE DADOS PREÇOS'!$E:$H,4,0)/(1-SUM($F$1))*VLOOKUP(CAPA!$B$12,'POLITICA DE PREÇO'!$B$4:$F$100,5,0))*CAPA!$B$14,"") -> 6046.4551 | J65: =I65*0.9 -> 5441.8096 | K65: =H65*1.05 -> 3246.4536
B66: Tressa Mesa de Centro Orgânico II Tampo inteiro - 1.2x0.8x0.26 - Acabamentos Customizados | C66: 1.2 | D66: 0.8 | E66: 0.26 | G66: =IFERROR(IF('BASE DE DADOS PREÇOS'!$M$71="com",VLOOKUP(CONCATENATE(B66,$G$6),'BASE DE DADOS PREÇOS'!$E:$H,4,0)/(1-SUM($F$1))*VLOOKUP(CAPA!$B$12,'POLITICA DE PREÇO'!#REF!,2,0)*0.95,VLOOKUP(CONCATENATE(B66,$G$6),'BASE DE DADOS PREÇOS'!$E:$H,4,0)/(1-SUM($F$1))*VLOOKUP(CAPA!$B$12,'POLITICA DE PREÇO'!$B$4:$F$100,5,0))*CAPA!$B$14,"") -> 3584.1779 | H66: =IFERROR(IF('BASE DE DADOS PREÇOS'!$M$71="com",VLOOKUP(CONCATENATE(B66,$H$6),'BASE DE DADOS PREÇOS'!$E:$H,4,0)/(1-SUM($F$1))*VLOOKUP(CAPA!$B$12,'POLITICA DE PREÇO'!#REF!,2,0)*0.95,VLOOKUP(CONCATENATE(B66,$H$6),'BASE DE DADOS PREÇOS'!$E:$H,4,0)/(1-SUM($F$1))*VLOOKUP(CAPA!$B$12,'POLITICA DE PREÇO'!$B$4:$F$100,5,0))*CAPA!$B$14,"") -> 3196.039 | I66: =IFERROR(IF('BASE DE DADOS PREÇOS'!$M$71="com",VLOOKUP(CONCATENATE(B66,$I$6),'BASE DE DADOS PREÇOS'!$E:$H,4,0)/(1-SUM($F$1))*VLOOKUP(CAPA!$B$12,'POLITICA DE PREÇO'!#REF!,2,0)*0.95,VLOOKUP(CONCATENATE(B66,$I$6),'BASE DE DADOS PREÇOS'!$E:$H,4,0)/(1-SUM($F$1))*VLOOKUP(CAPA!$B$12,'POLITICA DE PREÇO'!$B$4:$F$100,5,0))*CAPA!$B$14,"") -> 6123.1082 | J66: =I66*0.9 -> 5510.7974 | K66: =H66*1.05 -> 3355.841
B67: Tressa Mesa de Centro Orgânico I Tampo inteiro - 1.2x0.8x0.33 - Acabamentos Customizados | C67: 1.2 | D67: 0.8 | E67: 0.33 | G67: =IFERROR(IF('BASE DE DADOS PREÇOS'!$M$71="com",VLOOKUP(CONCATENATE(B67,$G$6),'BASE DE DADOS PREÇOS'!$E:$H,4,0)/(1-SUM($F$1))*VLOOKUP(CAPA!$B$12,'POLITICA DE PREÇO'!#REF!,2,0)*0.95,VLOOKUP(CONCATENATE(B67,$G$6),'BASE DE DADOS PREÇOS'!$E:$H,4,0)/(1-SUM($F$1))*VLOOKUP(CAPA!$B$12,'POLITICA DE PREÇO'!$B$4:$F$100,5,0))*CAPA!$B$14,"") -> 3584.1779 | H67: =IFERROR(IF('BASE DE DADOS PREÇOS'!$M$71="com",VLOOKUP(CONCATENATE(B67,$H$6),'BASE DE DADOS PREÇOS'!$E:$H,4,0)/(1-SUM($F$1))*VLOOKUP(CAPA!$B$12,'POLITICA DE PREÇO'!#REF!,2,0)*0.95,VLOOKUP(CONCATENATE(B67,$H$6),'BASE DE DADOS PREÇOS'!$E:$H,4,0)/(1-SUM($F$1))*VLOOKUP(CAPA!$B$12,'POLITICA DE PREÇO'!$B$4:$F$100,5,0))*CAPA!$B$14,"") -> 3196.039 | I67: =IFERROR(IF('BASE DE DADOS PREÇOS'!$M$71="com",VLOOKUP(CONCATENATE(B67,$I$6),'BASE DE DADOS PREÇOS'!$E:$H,4,0)/(1-SUM($F$1))*VLOOKUP(CAPA!$B$12,'POLITICA DE PREÇO'!#REF!,2,0)*0.95,VLOOKUP(CONCATENATE(B67,$I$6),'BASE DE DADOS PREÇOS'!$E:$H,4,0)/(1-SUM($F$1))*VLOOKUP(CAPA!$B$12,'POLITICA DE PREÇO'!$B$4:$F$100,5,0))*CAPA!$B$14,"") -> 6123.1082 | J67: =I67*0.9 -> 5510.7974 | K67: =H67*1.05 -> 3355.841
B68: Tressa Mesa de Centro Orgânico II Tampo inteiro - 1.2x0.8x0.33 - Acabamentos Customizados | C68: 1.2 | D68: 0.8 | E68: 0.33 | G68: =IFERROR(IF('BASE DE DADOS PREÇOS'!$M$71="com",VLOOKUP(CONCATENATE(B68,$G$6),'BASE DE DADOS PREÇOS'!$E:$H,4,0)/(1-SUM($F$1))*VLOOKUP(CAPA!$B$12,'POLITICA DE PREÇO'!#REF!,2,0)*0.95,VLOOKUP(CONCATENATE(B68,$G$6),'BASE DE DADOS PREÇOS'!$E:$H,4,0)/(1-SUM($F$1))*VLOOKUP(CAPA!$B$12,'POLITICA DE PREÇO'!$B$4:$F$100,5,0))*CAPA!$B$14,"") -> 3679.2974 | H68: =IFERROR(IF('BASE DE DADOS PREÇOS'!$M$71="com",VLOOKUP(CONCATENATE(B68,$H$6),'BASE DE DADOS PREÇOS'!$E:$H,4,0)/(1-SUM($F$1))*VLOOKUP(CAPA!$B$12,'POLITICA DE PREÇO'!#REF!,2,0)*0.95,VLOOKUP(CONCATENATE(B68,$H$6),'BASE DE DADOS PREÇOS'!$E:$H,4,0)/(1-SUM($F$1))*VLOOKUP(CAPA!$B$12,'POLITICA DE PREÇO'!$B$4:$F$100,5,0))*CAPA!$B$14,"") -> 3300.2175 | I68: =IFERROR(IF('BASE DE DADOS PREÇOS'!$M$71="com",VLOOKUP(CONCATENATE(B68,$I$6),'BASE DE DADOS PREÇOS'!$E:$H,4,0)/(1-SUM($F$1))*VLOOKUP(CAPA!$B$12,'POLITICA DE PREÇO'!#REF!,2,0)*0.95,VLOOKUP(CONCATENATE(B68,$I$6),'BASE DE DADOS PREÇOS'!$E:$H,4,0)/(1-SUM($F$1))*VLOOKUP(CAPA!$B$12,'POLITICA DE PREÇO'!$B$4:$F$100,5,0))*CAPA!$B$14,"") -> 6199.7613 | J68: =I68*0.9 -> 5579.7852 | K68: =H68*1.05 -> 3465.2284
B69: Tressa Mesa de Centro Orgânico I Tampo Centro - 1.2x0.8x0.26 - Acabamentos Customizados | C69: 1.2 | D69: 0.8 | E69: 0.26 | G69: =IFERROR(IF('BASE DE DADOS PREÇOS'!$M$71="com",VLOOKUP(CONCATENATE(B69,$G$6),'BASE DE DADOS PREÇOS'!$E:$H,4,0)/(1-SUM($F$1))*VLOOKUP(CAPA!$B$12,'POLITICA DE PREÇO'!#REF!,2,0)*0.95,VLOOKUP(CONCATENATE(B69,$G$6),'BASE DE DADOS PREÇOS'!$E:$H,4,0)/(1-SUM($F$1))*VLOOKUP(CAPA!$B$12,'POLITICA DE PREÇO'!$B$4:$F$100,5,0))*CAPA!$B$14,"") -> 3455.906 | H69: =IFERROR(IF('BASE DE DADOS PREÇOS'!$M$71="com",VLOOKUP(CONCATENATE(B69,$H$6),'BASE DE DADOS PREÇOS'!$E:$H,4,0)/(1-SUM($F$1))*VLOOKUP(CAPA!$B$12,'POLITICA DE PREÇO'!#REF!,2,0)*0.95,VLOOKUP(CONCATENATE(B69,$H$6),'BASE DE DADOS PREÇOS'!$E:$H,4,0)/(1-SUM($F$1))*VLOOKUP(CAPA!$B$12,'POLITICA DE PREÇO'!$B$4:$F$100,5,0))*CAPA!$B$14,"") -> 3134.243 | I69: =IFERROR(IF('BASE DE DADOS PREÇOS'!$M$71="com",VLOOKUP(CONCATENATE(B69,$I$6),'BASE DE DADOS PREÇOS'!$E:$H,4,0)/(1-SUM($F$1))*VLOOKUP(CAPA!$B$12,'POLITICA DE PREÇO'!#REF!,2,0)*0.95,VLOOKUP(CONCATENATE(B69,$I$6),'BASE DE DADOS PREÇOS'!$E:$H,4,0)/(1-SUM($F$1))*VLOOKUP(CAPA!$B$12,'POLITICA DE PREÇO'!$B$4:$F$100,5,0))*CAPA!$B$14,"") -> 5205.2613 | J69: =I69*0.9 -> 4684.7351 | K69: =H69*1.05 -> 3290.9551
B70: Tressa Mesa de Centro Orgânico II Tampo Centro - 1.2x0.8x0.26 - Acabamentos Customizados | C70: 1.2 | D70: 0.8 | E70: 0.26 | G70: =IFERROR(IF('BASE DE DADOS PREÇOS'!$M$71="com",VLOOKUP(CONCATENATE(B70,$G$6),'BASE DE DADOS PREÇOS'!$E:$H,4,0)/(1-SUM($F$1))*VLOOKUP(CAPA!$B$12,'POLITICA DE PREÇO'!#REF!,2,0)*0.95,VLOOKUP(CONCATENATE(B70,$G$6),'BASE DE DADOS PREÇOS'!$E:$H,4,0)/(1-SUM($F$1))*VLOOKUP(CAPA!$B$12,'POLITICA DE PREÇO'!$B$4:$F$100,5,0))*CAPA!$B$14,"") -> 3393.9389 | H70: =IFERROR(IF('BASE DE DADOS PREÇOS'!$M$71="com",VLOOKUP(CONCATENATE(B70,$H$6),'BASE DE DADOS PREÇOS'!$E:$H,4,0)/(1-SUM($F$1))*VLOOKUP(CAPA!$B$12,'POLITICA DE PREÇO'!#REF!,2,0)*0.95,VLOOKUP(CONCATENATE(B70,$H$6),'BASE DE DADOS PREÇOS'!$E:$H,4,0)/(1-SUM($F$1))*VLOOKUP(CAPA!$B$12,'POLITICA DE PREÇO'!$B$4:$F$100,5,0))*CAPA!$B$14,"") -> 3247.4805 | I70: =IFERROR(IF('BASE DE DADOS PREÇOS'!$M$71="com",VLOOKUP(CONCATENATE(B70,$I$6),'BASE DE DADOS PREÇOS'!$E:$H,4,0)/(1-SUM($F$1))*VLOOKUP(CAPA!$B$12,'POLITICA DE PREÇO'!#REF!,2,0)*0.95,VLOOKUP(CONCATENATE(B70,$I$6),'BASE DE DADOS PREÇOS'!$E:$H,4,0)/(1-SUM($F$1))*VLOOKUP(CAPA!$B$12,'POLITICA DE PREÇO'!$B$4:$F$100,5,0))*CAPA!$B$14,"") -> 5278.0817 | J70: =I70*0.9 -> 4750.2735 | K70: =H70*1.05 -> 3409.8545
B71: Tressa Mesa de Centro Orgânico I Tampo Centro - 1.2x0.8x0.33 - Acabamentos Customizados | C71: 1.2 | D71: 0.8 | E71: 0.33 | G71: =IFERROR(IF('BASE DE DADOS PREÇOS'!$M$71="com",VLOOKUP(CONCATENATE(B71,$G$6),'BASE DE DADOS PREÇOS'!$E:$H,4,0)/(1-SUM($F$1))*VLOOKUP(CAPA!$B$12,'POLITICA DE PREÇO'!#REF!,2,0)*0.95,VLOOKUP(CONCATENATE(B71,$G$6),'BASE DE DADOS PREÇOS'!$E:$H,4,0)/(1-SUM($F$1))*VLOOKUP(CAPA!$B$12,'POLITICA DE PREÇO'!$B$4:$F$100,5,0))*CAPA!$B$14,"") -> 3489.0584 | H71: =IFERROR(IF('BASE DE DADOS PREÇOS'!$M$71="com",VLOOKUP(CONCATENATE(B71,$H$6),'BASE DE DADOS PREÇOS'!$E:$H,4,0)/(1-SUM($F$1))*VLOOKUP(CAPA!$B$12,'POLITICA DE PREÇO'!#REF!,2,0)*0.95,VLOOKUP(CONCATENATE(B71,$H$6),'BASE DE DADOS PREÇOS'!$E:$H,4,0)/(1-SUM($F$1))*VLOOKUP(CAPA!$B$12,'POLITICA DE PREÇO'!$B$4:$F$100,5,0))*CAPA!$B$14,"") -> 3360.718 | I71: =IFERROR(IF('BASE DE DADOS PREÇOS'!$M$71="com",VLOOKUP(CONCATENATE(B71,$I$6),'BASE DE DADOS PREÇOS'!$E:$H,4,0)/(1-SUM($F$1))*VLOOKUP(CAPA!$B$12,'POLITICA DE PREÇO'!#REF!,2,0)*0.95,VLOOKUP(CONCATENATE(B71,$I$6),'BASE DE DADOS PREÇOS'!$E:$H,4,0)/(1-SUM($F$1))*VLOOKUP(CAPA!$B$12,'POLITICA DE PREÇO'!$B$4:$F$100,5,0))*CAPA!$B$14,"") -> 5350.9021 | J71: =I71*0.9 -> 4815.8119 | K71: =H71*1.05 -> 3528.7539
B72: Tressa Mesa de Centro Orgânico II Tampo Centro - 1.2x0.8x0.33 - Acabamentos Customizados | C72: 1.2 | D72: 0.8 | E72: 0.33 | G72: =IFERROR(IF('BASE DE DADOS PREÇOS'!$M$71="com",VLOOKUP(CONCATENATE(B72,$G$6),'BASE DE DADOS PREÇOS'!$E:$H,4,0)/(1-SUM($F$1))*VLOOKUP(CAPA!$B$12,'POLITICA DE PREÇO'!#REF!,2,0)*0.95,VLOOKUP(CONCATENATE(B72,$G$6),'BASE DE DADOS PREÇOS'!$E:$H,4,0)/(1-SUM($F$1))*VLOOKUP(CAPA!$B$12,'POLITICA DE PREÇO'!$B$4:$F$100,5,0))*CAPA!$B$14,"") -> 3584.1779 | H72: =IFERROR(IF('BASE DE DADOS PREÇOS'!$M$71="com",VLOOKUP(CONCATENATE(B72,$H$6),'BASE DE DADOS PREÇOS'!$E:$H,4,0)/(1-SUM($F$1))*VLOOKUP(CAPA!$B$12,'POLITICA DE PREÇO'!#REF!,2,0)*0.95,VLOOKUP(CONCATENATE(B72,$H$6),'BASE DE DADOS PREÇOS'!$E:$H,4,0)/(1-SUM($F$1))*VLOOKUP(CAPA!$B$12,'POLITICA DE PREÇO'!$B$4:$F$100,5,0))*CAPA!$B$14,"") -> 3473.9555 | I72: =IFERROR(IF('BASE DE DADOS PREÇOS'!$M$71="com",VLOOKUP(CONCATENATE(B72,$I$6),'BASE DE DADOS PREÇOS'!$E:$H,4,0)/(1-SUM($F$1))*VLOOKUP(CAPA!$B$12,'POLITICA DE PREÇO'!#REF!,2,0)*0.95,VLOOKUP(CONCATENATE(B72,$I$6),'BASE DE DADOS PREÇOS'!$E:$H,4,0)/(1-SUM($F$1))*VLOOKUP(CAPA!$B$12,'POLITICA DE PREÇO'!$B$4:$F$100,5,0))*CAPA!$B$14,"") -> 5423.7225 | J72: =I72*0.9 -> 4881.3503 | K72: =H72*1.05 -> 3647.6533

Sheet MESA LATERAL
B1: TABELA DE PREÇO CENTURY | MADEIRA
C5: Dimensoes (metros)
A6: Imagem | B6: Nome | C6: C | D6: L | E6: A | G6: Tampo: Espelho Bronze, Fume, Prata, Vidro Fosco ou Clear Corpo: Laca ou Lamina | H6: Tampo: Laca ou Lamina com ou sem Vidro Normal Pintado Corpo: Laca ou Lamina | I6: Tampo: Mármore ou Porcelana Especial Corpo: Laca ou Lamina | J6: Tampo: Mármore Normal Corpo: Laca ou Lamina | K6: Tampo ou Base em Recoro
B7: Petra Mesa Lateral - Øx0.4x0.5 - Acabamentos Customizados | C7: Ø | D7: 0.4 | E7: 0.5 | G7: =IFERROR(IF('BASE DE DADOS PREÇOS'!$M$71="com",VLOOKUP(CONCATENATE(B7,$G$6),'BASE DE DADOS PREÇOS'!$E:$H,4,0)/(1-SUM($F$1))*VLOOKUP(CAPA!$B$12,'POLITICA DE PREÇO'!#REF!,2,0)*0.95,VLOOKUP(CONCATENATE(B7,$G$6),'BASE DE DADOS PREÇOS'!$E:$H,4,0)/(1-SUM($F$1))*VLOOKUP(CAPA!$B$12,'POLITICA DE PREÇO'!$B$4:$F$100,5,0))*CAPA!$B$14,"") -> 2161.9459 | H7: =IFERROR(IF('BASE DE DADOS PREÇOS'!$M$71="com",VLOOKUP(CONCATENATE(B7,$H$6),'BASE DE DADOS PREÇOS'!$E:$H,4,0)/(1-SUM($F$1))*VLOOKUP(CAPA!$B$12,'POLITICA DE PREÇO'!#REF!,2,0)*0.95,VLOOKUP(CONCATENATE(B7,$H$6),'BASE DE DADOS PREÇOS'!$E:$H,4,0)/(1-SUM($F$1))*VLOOKUP(CAPA!$B$12,'POLITICA DE PREÇO'!$B$4:$F$100,5,0))*CAPA!$B$14,"") -> 1898.9757 | I7: =IFERROR(IF('BASE DE DADOS PREÇOS'!$M$71="com",VLOOKUP(CONCATENATE(B7,$I$6),'BASE DE DADOS PREÇOS'!$E:$H,4,0)/(1-SUM($F$1))*VLOOKUP(CAPA!$B$12,'POLITICA DE PREÇO'!#REF!,2,0)*0.95,VLOOKUP(CONCATENATE(B7,$I$6),'BASE DE DADOS PREÇOS'!$E:$H,4,0)/(1-SUM($F$1))*VLOOKUP(CAPA!$B$12,'POLITICA DE PREÇO'!$B$4:$F$100,5,0))*CAPA!$B$14,"") -> 2584.4048 | J7: =I7*0.9 -> 2325.9644
B8: Petra Mesa Lateral - Øx0.45x0.5 - Acabamentos Customizados | C8: Ø | D8: 0.45 | E8: 0.5 | G8: =IFERROR(IF('BASE DE DADOS PREÇOS'!$M$71="com",VLOOKUP(CONCATENATE(B8,$G$6),'BASE DE DADOS PREÇOS'!$E:$H,4,0)/(1-SUM($F$1))*VLOOKUP(CAPA!$B$12,'POLITICA DE PREÇO'!#REF!,2,0)*0.95,VLOOKUP(CONCATENATE(B8,$G$6),'BASE DE DADOS PREÇOS'!$E:$H,4,0)/(1-SUM($F$1))*VLOOKUP(CAPA!$B$12,'POLITICA DE PREÇO'!$B$4:$F$100,5,0))*CAPA!$B$14,"") -> 2275.7325 | H8: =IFERROR(IF('BASE DE DADOS PREÇOS'!$M$71="com",VLOOKUP(CONCATENATE(B8,$H$6),'BASE DE DADOS PREÇOS'!$E:$H,4,0)/(1-SUM($F$1))*VLOOKUP(CAPA!$B$12,'POLITICA DE PREÇO'!#REF!,2,0)*0.95,VLOOKUP(CONCATENATE(B8,$H$6),'BASE DE DADOS PREÇOS'!$E:$H,4,0)/(1-SUM($F$1))*VLOOKUP(CAPA!$B$12,'POLITICA DE PREÇO'!$B$4:$F$100,5,0))*CAPA!$B$14,"") -> 1998.9218 | I8: =IFERROR(IF('BASE DE DADOS PREÇOS'!$M$71="com",VLOOKUP(CONCATENATE(B8,$I$6),'BASE DE DADOS PREÇOS'!$E:$H,4,0)/(1-SUM($F$1))*VLOOKUP(CAPA!$B$12,'POLITICA DE PREÇO'!#REF!,2,0)*0.95,VLOOKUP(CONCATENATE(B8,$I$6),'BASE DE DADOS PREÇOS'!$E:$H,4,0)/(1-SUM($F$1))*VLOOKUP(CAPA!$B$12,'POLITICA DE PREÇO'!$B$4:$F$100,5,0))*CAPA!$B$14,"") -> 2720.4262 | J8: =I8*0.9 -> 2448.3835
B9: Petra Mesa Lateral - Øx0.5x0.4 - Acabamentos Customizados | C9: Ø | D9: 0.5 | E9: 0.4 | G9: =IFERROR(IF('BASE DE DADOS PREÇOS'!$M$71="com",VLOOKUP(CONCATENATE(B9,$G$6),'BASE DE DADOS PREÇOS'!$E:$H,4,0)/(1-SUM($F$1))*VLOOKUP(CAPA!$B$12,'POLITICA DE PREÇO'!#REF!,2,0)*0.95,VLOOKUP(CONCATENATE(B9,$G$6),'BASE DE DADOS PREÇOS'!$E:$H,4,0)/(1-SUM($F$1))*VLOOKUP(CAPA!$B$12,'POLITICA DE PREÇO'!$B$4:$F$100,5,0))*CAPA!$B$14,"") -> 2283.5701 | H9: =IFERROR(IF('BASE DE DADOS PREÇOS'!$M$71="com",VLOOKUP(CONCATENATE(B9,$H$6),'BASE DE DADOS PREÇOS'!$E:$H,4,0)/(1-SUM($F$1))*VLOOKUP(CAPA!$B$12,'POLITICA DE PREÇO'!#REF!,2,0)*0.95,VLOOKUP(CONCATENATE(B9,$H$6),'BASE DE DADOS PREÇOS'!$E:$H,4,0)/(1-SUM($F$1))*VLOOKUP(CAPA!$B$12,'POLITICA DE PREÇO'!$B$4:$F$100,5,0))*CAPA!$B$14,"") -> 1913.1952 | I9: =IFERROR(IF('BASE DE DADOS PREÇOS'!$M$71="com",VLOOKUP(CONCATENATE(B9,$I$6),'BASE DE DADOS PREÇOS'!$E:$H,4,0)/(1-SUM($F$1))*VLOOKUP(CAPA!$B$12,'POLITICA DE PREÇO'!#REF!,2,0)*0.95,VLOOKUP(CONCATENATE(B9,$I$6),'BASE DE DADOS PREÇOS'!$E:$H,4,0)/(1-SUM($F$1))*VLOOKUP(CAPA!$B$12,'POLITICA DE PREÇO'!$B$4:$F$100,5,0))*CAPA!$B$14,"") -> 2828.7309 | J9: =I9*0.9 -> 2545.8578
B10: Petra Mesa Lateral - Øx0.5x0.5 - Acabamentos Customizados | C10: Ø | D10: 0.5 | E10: 0.5 | G10: =IFERROR(IF('BASE DE DADOS PREÇOS'!$M$71="com",VLOOKUP(CONCATENATE(B10,$G$6),'BASE DE DADOS PREÇOS'!$E:$H,4,0)/(1-SUM($F$1))*VLOOKUP(CAPA!$B$12,'POLITICA DE PREÇO'!#REF!,2,0)*0.95,VLOOKUP(CONCATENATE(B10,$G$6),'BASE DE DADOS PREÇOS'!$E:$H,4,0)/(1-SUM($F$1))*VLOOKUP(CAPA!$B$12,'POLITICA DE PREÇO'!$B$4:$F$100,5,0))*CAPA!$B$14,"") -> 2420.5843 | H10: =IFERROR(IF('BASE DE DADOS PREÇOS'!$M$71="com",VLOOKUP(CONCATENATE(B10,$H$6),'BASE DE DADOS PREÇOS'!$E:$H,4,0)/(1-SUM($F$1))*VLOOKUP(CAPA!$B$12,'POLITICA DE PREÇO'!#REF!,2,0)*0.95,VLOOKUP(CONCATENATE(B10,$H$6),'BASE DE DADOS PREÇOS'!$E:$H,4,0)/(1-SUM($F$1))*VLOOKUP(CAPA!$B$12,'POLITICA DE PREÇO'!$B$4:$F$100,5,0))*CAPA!$B$14,"") -> 2027.9869 | I10: =IFERROR(IF('BASE DE DADOS PREÇOS'!$M$71="com",VLOOKUP(CONCATENATE(B10,$I$6),'BASE DE DADOS PREÇOS'!$E:$H,4,0)/(1-SUM($F$1))*VLOOKUP(CAPA!$B$12,'POLITICA DE PREÇO'!#REF!,2,0)*0.95,VLOOKUP(CONCATENATE(B10,$I$6),'BASE DE DADOS PREÇOS'!$E:$H,4,0)/(1-SUM($F$1))*VLOOKUP(CAPA!$B$12,'POLITICA DE PREÇO'!$B$4:$F$100,5,0))*CAPA!$B$14,"") -> 2998.4547 | J10: =I10*0.9 -> 2698.6093
B11: Petra Mesa Lateral - Øx0.6x0.4 - Acabamentos Customizados | C11: Ø | D11: 0.6 | E11: 0.4 | G11: =IFERROR(IF('BASE DE DADOS PREÇOS'!$M$71="com",VLOOKUP(CONCATENATE(B11,$G$6),'BASE DE DADOS PREÇOS'!$E:$H,4,0)/(1-SUM($F$1))*VLOOKUP(CAPA!$B$12,'POLITICA DE PREÇO'!#REF!,2,0)*0.95,VLOOKUP(CONCATENATE(B11,$G$6),'BASE DE DADOS PREÇOS'!$E:$H,4,0)/(1-SUM($F$1))*VLOOKUP(CAPA!$B$12,'POLITICA DE PREÇO'!$B$4:$F$100,5,0))*CAPA!$B$14,"") -> 2415.0955 | H11: =IFERROR(IF('BASE DE DADOS PREÇOS'!$M$71="com",VLOOKUP(CONCATENATE(B11,$H$6),'BASE DE DADOS PREÇOS'!$E:$H,4,0)/(1-SUM($F$1))*VLOOKUP(CAPA!$B$12,'POLITICA DE PREÇO'!#REF!,2,0)*0.95,VLOOKUP(CONCATENATE(B11,$H$6),'BASE DE DADOS PREÇOS'!$E:$H,4,0)/(1-SUM($F$1))*VLOOKUP(CAPA!$B$12,'POLITICA DE PREÇO'!$B$4:$F$100,5,0))*CAPA!$B$14,"") -> 2088.2405 | I11: =IFERROR(IF('BASE DE DADOS PREÇOS'!$M$71="com",VLOOKUP(CONCATENATE(B11,$I$6),'BASE DE DADOS PREÇOS'!$E:$H,4,0)/(1-SUM($F$1))*VLOOKUP(CAPA!$B$12,'POLITICA DE PREÇO'!#REF!,2,0)*0.95,VLOOKUP(CONCATENATE(B11,$I$6),'BASE DE DADOS PREÇOS'!$E:$H,4,0)/(1-SUM($F$1))*VLOOKUP(CAPA!$B$12,'POLITICA DE PREÇO'!$B$4:$F$100,5,0))*CAPA!$B$14,"") -> 3225.3786 | J11: =I11*0.9 -> 2902.8407
A13: Imagem | B13: Nome | C13: C | D13: L | E13: A | G13: Recoro | H13: Laca ou Lamina
B14: Beeh Mesa Lateral 1.05X0.254X0.56 - Acabamentos Customizados | C14: 1.05 | D14: 0.254 | E14: 0.56 | G14: =IFERROR(IF('BASE DE DADOS PREÇOS'!$M$71="com",VLOOKUP(CONCATENATE(B14,$G$13),'BASE DE DADOS PREÇOS'!$E:$H,4,0)/(1-SUM($F$1))*VLOOKUP(CAPA!$B$12,'POLITICA DE PREÇO'!#REF!,2,0)*0.95,VLOOKUP(CONCATENATE(B14,$G$13),'BASE DE DADOS PREÇOS'!$E:$H,4,0)/(1-SUM($F$1))*VLOOKUP(CAPA!$B$12,'POLITICA DE PREÇO'!$B$4:$F$100,5,0))*CAPA!$B$14,"") -> 5177.5152 | H14: =IFERROR(IF('BASE DE DADOS PREÇOS'!$M$71="com",VLOOKUP(CONCATENATE(B14,$H$13),'BASE DE DADOS PREÇOS'!$E:$H,4,0)/(1-SUM($F$1))*VLOOKUP(CAPA!$B$12,'POLITICA DE PREÇO'!#REF!,2,0)*0.95,VLOOKUP(CONCATENATE(B14,$H$13),'BASE DE DADOS PREÇOS'!$E:$H,4,0)/(1-SUM($F$1))*VLOOKUP(CAPA!$B$12,'POLITICA DE PREÇO'!$B$4:$F$100,5,0))*CAPA!$B$14,"") -> 4378.2754

Sheet MESA DE JANTAR
B1: TABELA DE PREÇO CENTURY | MADEIRA
C5: Dimensoes (metros)
A6: Imagem | B6: Nome | C6: C | D6: L | E6: A | G6: Tampo:Vidro Fosco ou Clear Corpo: Laca ou Lamina | H6: Tampo: Laca ou Lamina com ou sem Vidro Normal Pintado Corpo: Laca ou Lamina | I6: Tampo: Mármore Especial Corpo: Laca ou Lamina | J6: Tampo: Mármore Normal Corpo: Laca ou Lamina | K6: Tampo ou Base em Recoro
B7: Belga Mesa de Jantar - 1.8x1.2x0.75 - Acabamentos Customizados | C7: 1.8 | D7: 1.2 | E7: 0.75 | G7: =IFERROR(IF('BASE DE DADOS PREÇOS'!$M$71="com",VLOOKUP(CONCATENATE(B7,$G$6),'BASE DE DADOS PREÇOS'!$E:$H,4,0)/(1-SUM($F$1))*VLOOKUP(CAPA!$B$12,'POLITICA DE PREÇO'!#REF!,2,0)*0.95,VLOOKUP(CONCATENATE(B7,$G$6),'BASE DE DADOS PREÇOS'!$E:$H,4,0)/(1-SUM($F$1))*VLOOKUP(CAPA!$B$12,'POLITICA DE PREÇO'!$B$4:$F$100,5,0))*CAPA!$B$14,"") -> 8690.8567 | H7: =IFERROR(IF('BASE DE DADOS PREÇOS'!$M$71="com",VLOOKUP(CONCATENATE(B7,$H$6),'BASE DE DADOS PREÇOS'!$E:$H,4,0)/(1-SUM($F$1))*VLOOKUP(CAPA!$B$12,'POLITICA DE PREÇO'!#REF!,2,0)*0.95,VLOOKUP(CONCATENATE(B7,$H$6),'BASE DE DADOS PREÇOS'!$E:$H,4,0)/(1-SUM($F$1))*VLOOKUP(CAPA!$B$12,'POLITICA DE PREÇO'!$B$4:$F$100,5,0))*CAPA!$B$14,"") -> 7055.5307 | I7: =IFERROR(IF('BASE DE DADOS PREÇOS'!$M$71="com",VLOOKUP(CONCATENATE(B7,$I$6),'BASE DE DADOS PREÇOS'!$E:$H,4,0)/(1-SUM($F$1))*VLOOKUP(CAPA!$B$12,'POLITICA DE PREÇO'!#REF!,2,0)*0.95,VLOOKUP(CONCATENATE(B7,$I$6),'BASE DE DADOS PREÇOS'!$E:$H,4,0)/(1-SUM($F$1))*VLOOKUP(CAPA!$B$12,'POLITICA DE PREÇO'!$B$4:$F$100,5,0))*CAPA!$B$14,"") -> 15655.078 | J7: =J8-(J9-J8) -> 14089.571
B8: Belga Mesa de Jantar - 2x1.2x0.75 - Acabamentos Customizados | C8: 2 | D8: 1.2 | E8: 0.75 | G8: =IFERROR(IF('BASE DE DADOS PREÇOS'!$M$71="com",VLOOKUP(CONCATENATE(B8,$G$6),'BASE DE DADOS PREÇOS'!$E:$H,4,0)/(1-SUM($F$1))*VLOOKUP(CAPA!$B$12,'POLITICA DE PREÇO'!#REF!,2,0)*0.95,VLOOKUP(CONCATENATE(B8,$G$6),'BASE DE DADOS PREÇOS'!$E:$H,4,0)/(1-SUM($F$1))*VLOOKUP(CAPA!$B$12,'POLITICA DE PREÇO'!$B$4:$F$100,5,0))*CAPA!$B$14,"") -> 9685.1744 | H8: =IFERROR(IF('BASE DE DADOS PREÇOS'!$M$71="com",VLOOKUP(CONCATENATE(B8,$H$6),'BASE DE DADOS PREÇOS'!$E:$H,4,0)/(1-SUM($F$1))*VLOOKUP(CAPA!$B$12,'POLITICA DE PREÇO'!#REF!,2,0)*0.95,VLOOKUP(CONCATENATE(B8,$H$6),'BASE DE DADOS PREÇOS'!$E:$H,4,0)/(1-SUM($F$1))*VLOOKUP(CAPA!$B$12,'POLITICA DE PREÇO'!$B$4:$F$100,5,0))*CAPA!$B$14,"") -> 7293.5819 | I8: =IFERROR(IF('BASE DE DADOS PREÇOS'!$M$71="com",VLOOKUP(CONCATENATE(B8,$I$6),'BASE DE DADOS PREÇOS'!$E:$H,4,0)/(1-SUM($F$1))*VLOOKUP(CAPA!$B$12,'POLITICA DE PREÇO'!#REF!,2,0)*0.95,VLOOKUP(CONCATENATE(B8,$I$6),'BASE DE DADOS PREÇOS'!$E:$H,4,0)/(1-SUM($F$1))*VLOOKUP(CAPA!$B$12,'POLITICA DE PREÇO'!$B$4:$F$100,5,0))*CAPA!$B$14,"") -> 16787.98 | J8: =I8*0.9 -> 15109.182
B9: Belga Mesa de Jantar - 2.2x1.2x0.75 - Acabamentos Customizados | C9: 2.2 | D9: 1.2 | E9: 0.75 | G9: =IFERROR(IF('BASE DE DADOS PREÇOS'!$M$71="com",VLOOKUP(CONCATENATE(B9,$G$6),'BASE DE DADOS PREÇOS'!$E:$H,4,0)/(1-SUM($F$1))*VLOOKUP(CAPA!$B$12,'POLITICA DE PREÇO'!#REF!,2,0)*0.95,VLOOKUP(CONCATENATE(B9,$G$6),'BASE DE DADOS PREÇOS'!$E:$H,4,0)/(1-SUM($F$1))*VLOOKUP(CAPA!$B$12,'POLITICA DE PREÇO'!$B$4:$F$100,5,0))*CAPA!$B$14,"") -> 10679.492 | H9: =IFERROR(IF('BASE DE DADOS PREÇOS'!$M$71="com",VLOOKUP(CONCATENATE(B9,$H$6),'BASE DE DADOS PREÇOS'!$E:$H,4,0)/(1-SUM($F$1))*VLOOKUP(CAPA!$B$12,'POLITICA DE PREÇO'!#REF!,2,0)*0.95,VLOOKUP(CONCATENATE(B9,$H$6),'BASE DE DADOS PREÇOS'!$E:$H,4,0)/(1-SUM($F$1))*VLOOKUP(CAPA!$B$12,'POLITICA DE PREÇO'!$B$4:$F$100,5,0))*CAPA!$B$14,"") -> 7531.633 | I9: =IFERROR(IF('BASE DE DADOS PREÇOS'!$M$71="com",VLOOKUP(CONCATENATE(B9,$I$6),'BASE DE DADOS PREÇOS'!$E:$H,4,0)/(1-SUM($F$1))*VLOOKUP(CAPA!$B$12,'POLITICA DE PREÇO'!#REF!,2,0)*0.95,VLOOKUP(CONCATENATE(B9,$I$6),'BASE DE DADOS PREÇOS'!$E:$H,4,0)/(1-SUM($F$1))*VLOOKUP(CAPA!$B$12,'POLITICA DE PREÇO'!$B$4:$F$100,5,0))*CAPA!$B$14,"") -> 17920.881 | J9: =I9*0.9 -> 16128.793
B10: Belga Mesa de Jantar - 2.4x1.2x0.75 - Acabamentos Customizados | C10: 2.4 | D10: 1.2 | E10: 0.75 | G10: =IFERROR(IF('BASE DE DADOS PREÇOS'!$M$71="com",VLOOKUP(CONCATENATE(B10,$G$6),'BASE DE DADOS PREÇOS'!$E:$H,4,0)/(1-SUM($F$1))*VLOOKUP(CAPA!$B$12,'POLITICA DE PREÇO'!#REF!,2,0)*0.95,VLOOKUP(CONCATENATE(B10,$G$6),'BASE DE DADOS PREÇOS'!$E:$H,4,0)/(1-SUM($F$1))*VLOOKUP(CAPA!$B$12,'POLITICA DE PREÇO'!$B$4:$F$100,5,0))*CAPA!$B$14,"") -> 11673.81 | H10: =IFERROR(IF('BASE DE DADOS PREÇOS'!$M$71="com",VLOOKUP(CONCATENATE(B10,$H$6),'BASE DE DADOS PREÇOS'!$E:$H,4,0)/(1-SUM($F$1))*VLOOKUP(CAPA!$B$12,'POLITICA DE PREÇO'!#REF!,2,0)*0.95,VLOOKUP(CONCATENATE(B10,$H$6),'BASE DE DADOS PREÇOS'!$E:$H,4,0)/(1-SUM($F$1))*VLOOKUP(CAPA!$B$12,'POLITICA DE PREÇO'!$B$4:$F$100,5,0))*CAPA!$B$14,"") -> 7769.6842 | I10: =IFERROR(IF('BASE DE DADOS PREÇOS'!$M$71="com",VLOOKUP(CONCATENATE(B10,$I$6),'BASE DE DADOS PREÇOS'!$E:$H,4,0)/(1-SUM($F$1))*VLOOKUP(CAPA!$B$12,'POLITICA DE PREÇO'!#REF!,2,0)*0.95,VLOOKUP(CONCATENATE(B10,$I$6),'BASE DE DADOS PREÇOS'!$E:$H,4,0)/(1-SUM($F$1))*VLOOKUP(CAPA!$B$12,'POLITICA DE PREÇO'!$B$4:$F$100,5,0))*CAPA!$B$14,"") -> 19053.782 | J10: =I10*0.9 -> 17148.404
B11: Belga Mesa de Jantar - 2.7x1.2x0.75 - Acabamentos Customizados | C11: 2.7 | D11: 1.2 | E11: 0.75 | G11: =IFERROR(IF('BASE DE DADOS PREÇOS'!$M$71="com",VLOOKUP(CONCATENATE(B11,$G$6),'BASE DE DADOS PREÇOS'!$E:$H,4,0)/(1-SUM($F$1))*VLOOKUP(CAPA!$B$12,'POLITICA DE PREÇO'!#REF!,2,0)*0.95,VLOOKUP(CONCATENATE(B11,$G$6),'BASE DE DADOS PREÇOS'!$E:$H,4,0)/(1-SUM($F$1))*VLOOKUP(CAPA!$B$12,'POLITICA DE PREÇO'!$B$4:$F$100,5,0))*CAPA!$B$14,"") -> 12962.859 | H11: =IFERROR(IF('BASE DE DADOS PREÇOS'!$M$71="com",VLOOKUP(CONCATENATE(B11,$H$6),'BASE DE DADOS PREÇOS'!$E:$H,4,0)/(1-SUM($F$1))*VLOOKUP(CAPA!$B$12,'POLITICA DE PREÇO'!#REF!,2,0)*0.95,VLOOKUP(CONCATENATE(B11,$H$6),'BASE DE DADOS PREÇOS'!$E:$H,4,0)/(1-SUM($F$1))*VLOOKUP(CAPA!$B$12,'POLITICA DE PREÇO'!$B$4:$F$100,5,0))*CAPA!$B$14,"") -> 9067.0833 | I11: =IFERROR(IF('BASE DE DADOS PREÇOS'!$M$71="com",VLOOKUP(CONCATENATE(B11,$I$6),'BASE DE DADOS PREÇOS'!$E:$H,4,0)/(1-SUM($F$1))*VLOOKUP(CAPA!$B$12,'POLITICA DE PREÇO'!#REF!,2,0)*0.95,VLOOKUP(CONCATENATE(B11,$I$6),'BASE DE DADOS PREÇOS'!$E:$H,4,0)/(1-SUM($F$1))*VLOOKUP(CAPA!$B$12,'POLITICA DE PREÇO'!$B$4:$F$100,5,0))*CAPA!$B$14,"") -> 22863.7 | J11: =I11*0.9 -> 20577.33
B12: Belga Mesa de Jantar - 3x1.2x0.75 - Acabamentos Customizados | C12: 3 | D12: 1.2 | E12: 0.75 | G12: =IFERROR(IF('BASE DE DADOS PREÇOS'!$M$71="com",VLOOKUP(CONCATENATE(B12,$G$6),'BASE DE DADOS PREÇOS'!$E:$H,4,0)/(1-SUM($F$1))*VLOOKUP(CAPA!$B$12,'POLITICA DE PREÇO'!#REF!,2,0)*0.95,VLOOKUP(CONCATENATE(B12,$G$6),'BASE DE DADOS PREÇOS'!$E:$H,4,0)/(1-SUM($F$1))*VLOOKUP(CAPA!$B$12,'POLITICA DE PREÇO'!$B$4:$F$100,5,0))*CAPA!$B$14,"") -> 14336.013 | H12: =IFERROR(IF('BASE DE DADOS PREÇOS'!$M$71="com",VLOOKUP(CONCATENATE(B12,$H$6),'BASE DE DADOS PREÇOS'!$E:$H,4,0)/(1-SUM($F$1))*VLOOKUP(CAPA!$B$12,'POLITICA DE PREÇO'!#REF!,2,0)*0.95,VLOOKUP(CONCATENATE(B12,$H$6),'BASE DE DADOS PREÇOS'!$E:$H,4,0)/(1-SUM($F$1))*VLOOKUP(CAPA!$B$12,'POLITICA DE PREÇO'!$B$4:$F$100,5,0))*CAPA!$B$14,"") -> 10007.373 | I12: =IFERROR(IF('BASE DE DADOS PREÇOS'!$M$71="com",VLOOKUP(CONCATENATE(B12,$I$6),'BASE DE DADOS PREÇOS'!$E:$H,4,0)/(1-SUM($F$1))*VLOOKUP(CAPA!$B$12,'POLITICA DE PREÇO'!#REF!,2,0)*0.95,VLOOKUP(CONCATENATE(B12,$I$6),'BASE DE DADOS PREÇOS'!$E:$H,4,0)/(1-SUM($F$1))*VLOOKUP(CAPA!$B$12,'POLITICA DE PREÇO'!$B$4:$F$100,5,0))*CAPA!$B$14,"") -> 25234.751 | J12: =I12*0.9 -> 22711.276
B13: FLORA MESA DE JANTAR 2.7X1.2X0.75 - Acabamentos Customizado | C13: 2.7 | D13: 1.2 | E13: 0.75 | G13: =IFERROR(IF('BASE DE DADOS PREÇOS'!$M$71="com",VLOOKUP(CONCATENATE(B13,$G$6),'BASE DE DADOS PREÇOS'!$E:$H,4,0)/(1-SUM($F$1))*VLOOKUP(CAPA!$B$12,'POLITICA DE PREÇO'!#REF!,2,0)*0.95,VLOOKUP(CONCATENATE(B13,$G$6),'BASE DE DADOS PREÇOS'!$E:$H,4,0)/(1-SUM($F$1))*VLOOKUP(CAPA!$B$12,'POLITICA DE PREÇO'!$B$4:$F$100,5,0))*CAPA!$B$14,"") -> 12280.284 | H13: =IFERROR(IF('BASE DE DADOS PREÇOS'!$M$71="com",VLOOKUP(CONCATENATE(B13,$H$6),'BASE DE DADOS PREÇOS'!$E:$H,4,0)/(1-SUM($F$1))*VLOOKUP(CAPA!$B$12,'POLITICA DE PREÇO'!#REF!,2,0)*0.95,VLOOKUP(CONCATENATE(B13,$H$6),'BASE DE DADOS PREÇOS'!$E:$H,4,0)/(1-SUM($F$1))*VLOOKUP(CAPA!$B$12,'POLITICA DE PREÇO'!$B$4:$F$100,5,0))*CAPA!$B$14,"") -> 8086.4516 | I13: =IFERROR(IF('BASE DE DADOS PREÇOS'!$M$71="com",VLOOKUP(CONCATENATE(B13,$I$6),'BASE DE DADOS PREÇOS'!$E:$H,4,0)/(1-SUM($F$1))*VLOOKUP(CAPA!$B$12,'POLITICA DE PREÇO'!#REF!,2,0)*0.95,VLOOKUP(CONCATENATE(B13,$I$6),'BASE DE DADOS PREÇOS'!$E:$H,4,0)/(1-SUM($F$1))*VLOOKUP(CAPA!$B$12,'POLITICA DE PREÇO'!$B$4:$F$100,5,0))*CAPA!$B$14,"") -> 22010.839 | J13: =I13*0.9 -> 19809.755
B14: FLORA MESA DE JANTAR 3X1.2X0.75 - Acabamentos Customizados | C14: 3 | D14: 1.2 | E14: 0.75 | G14: =IFERROR(IF('BASE DE DADOS PREÇOS'!$M$71="com",VLOOKUP(CONCATENATE(B14,$G$6),'BASE DE DADOS PREÇOS'!$E:$H,4,0)/(1-SUM($F$1))*VLOOKUP(CAPA!$B$12,'POLITICA DE PREÇO'!#REF!,2,0)*0.95,VLOOKUP(CONCATENATE(B14,$G$6),'BASE DE DADOS PREÇOS'!$E:$H,4,0)/(1-SUM($F$1))*VLOOKUP(CAPA!$B$12,'POLITICA DE PREÇO'!$B$4:$F$100,5,0))*CAPA!$B$14,"") -> 12816.392 | H14: =IFERROR(IF('BASE DE DADOS PREÇOS'!$M$71="com",VLOOKUP(CONCATENATE(B14,$H$6),'BASE DE DADOS PREÇOS'!$E:$H,4,0)/(1-SUM($F$1))*VLOOKUP(CAPA!$B$12,'POLITICA DE PREÇO'!#REF!,2,0)*0.95,VLOOKUP(CONCATENATE(B14,$H$6),'BASE DE DADOS PREÇOS'!$E:$H,4,0)/(1-SUM($F$1))*VLOOKUP(CAPA!$B$12,'POLITICA DE PREÇO'!$B$4:$F$100,5,0))*CAPA!$B$14,"") -> 8369.9586 | I14: =IFERROR(IF('BASE DE DADOS PREÇOS'!$M$71="com",VLOOKUP(CONCATENATE(B14,$I$6),'BASE DE DADOS PREÇOS'!$E:$H,4,0)/(1-SUM($F$1))*VLOOKUP(CAPA!$B$12,'POLITICA DE PREÇO'!#REF!,2,0)*0.95,VLOOKUP(CONCATENATE(B14,$I$6),'BASE DE DADOS PREÇOS'!$E:$H,4,0)/(1-SUM($F$1))*VLOOKUP(CAPA!$B$12,'POLITICA DE PREÇO'!$B$4:$F$100,5,0))*CAPA!$B$14,"") -> 23793.566 | J14: =I14*0.9 -> 21414.209
B15: Kona Mesa de Jantar Retangular - 2.2x1.2x0.75 - Acabamentos Customizados | C15: 2.2 | D15: 1.2 | E15: 0.75 | G15: =IFERROR(IF('BASE DE DADOS PREÇOS'!$M$71="com",VLOOKUP(CONCATENATE(B15,$G$6),'BASE DE DADOS PREÇOS'!$E:$H,4,0)/(1-SUM($F$1))*VLOOKUP(CAPA!$B$12,'POLITICA DE PREÇO'!#REF!,2,0)*0.95,VLOOKUP(CONCATENATE(B15,$G$6),'BASE DE DADOS PREÇOS'!$E:$H,4,0)/(1-SUM($F$1))*VLOOKUP(CAPA!$B$12,'POLITICA DE PREÇO'!$B$4:$F$100,5,0))*CAPA!$B$14,"") -> 9673.1285 | H15: =IFERROR(IF('BASE DE DADOS PREÇOS'!$M$71="com",VLOOKUP(CONCATENATE(B15,$H$6),'BASE DE DADOS PREÇOS'!$E:$H,4,0)/(1-SUM($F$1))*VLOOKUP(CAPA!$B$12,'POLITICA DE PREÇO'!#REF!,2,0)*0.95,VLOOKUP(CONCATENATE(B15,$H$6),'BASE DE DADOS PREÇOS'!$E:$H,4,0)/(1-SUM($F$1))*VLOOKUP(CAPA!$B$12,'POLITICA DE PREÇO'!$B$4:$F$100,5,0))*CAPA!$B$14,"") -> 6643.0806 | I15: =IFERROR(IF('BASE DE DADOS PREÇOS'!$M$71="com",VLOOKUP(CONCATENATE(B15,$I$6),'BASE DE DADOS PREÇOS'!$E:$H,4,0)/(1-SUM($F$1))*VLOOKUP(CAPA!$B$12,'POLITICA DE PREÇO'!#REF!,2,0)*0.95,VLOOKUP(CONCATENATE(B15,$I$6),'BASE DE DADOS PREÇOS'!$E:$H,4,0)/(1-SUM($F$1))*VLOOKUP(CAPA!$B$12,'POLITICA DE PREÇO'!$B$4:$F$100,5,0))*CAPA!$B$14,"") -> 15433.637 | J15: =I15*0.9 -> 13890.273
B16: Kona Mesa de Jantar Retangular - 2.4x1.2x0.75 - Acabamentos Customizados | C16: 2.4 | D16: 1.2 | E16: 0.75 | G16: =IFERROR(IF('BASE DE DADOS PREÇOS'!$M$71="com",VLOOKUP(CONCATENATE(B16,$G$6),'BASE DE DADOS PREÇOS'!$E:$H,4,0)/(1-SUM($F$1))*VLOOKUP(CAPA!$B$12,'POLITICA DE PREÇO'!#REF!,2,0)*0.95,VLOOKUP(CONCATENATE(B16,$G$6),'BASE DE DADOS PREÇOS'!$E:$H,4,0)/(1-SUM($F$1))*VLOOKUP(CAPA!$B$12,'POLITICA DE PREÇO'!$B$4:$F$100,5,0))*CAPA!$B$14,"") -> 10203.035 | H16: =IFERROR(IF('BASE DE DADOS PREÇOS'!$M$71="com",VLOOKUP(CONCATENATE(B16,$H$6),'BASE DE DADOS PREÇOS'!$E:$H,4,0)/(1-SUM($F$1))*VLOOKUP(CAPA!$B$12,'POLITICA DE PREÇO'!#REF!,2,0)*0.95,VLOOKUP(CONCATENATE(B16,$H$6),'BASE DE DADOS PREÇOS'!$E:$H,4,0)/(1-SUM($F$1))*VLOOKUP(CAPA!$B$12,'POLITICA DE PREÇO'!$B$4:$F$100,5,0))*CAPA!$B$14,"") -> 7522.5597 | I16: =IFERROR(IF('BASE DE DADOS PREÇOS'!$M$71="com",VLOOKUP(CONCATENATE(B16,$I$6),'BASE DE DADOS PREÇOS'!$E:$H,4,0)/(1-SUM($F$1))*VLOOKUP(CAPA!$B$12,'POLITICA DE PREÇO'!#REF!,2,0)*0.95,VLOOKUP(CONCATENATE(B16,$I$6),'BASE DE DADOS PREÇOS'!$E:$H,4,0)/(1-SUM($F$1))*VLOOKUP(CAPA!$B$12,'POLITICA DE PREÇO'!$B$4:$F$100,5,0))*CAPA!$B$14,"") -> 18777.658 | J16: =I16*0.9 -> 16899.893
B17: Kona Mesa de Jantar Retangular - 2.7x1.2x0.75 - Acabamentos Customizados | C17: 2.7 | D17: 1.2 | E17: 0.75 | G17: =IFERROR(IF('BASE DE DADOS PREÇOS'!$M$71="com",VLOOKUP(CONCATENATE(B17,$G$6),'BASE DE DADOS PREÇOS'!$E:$H,4,0)/(1-SUM($F$1))*VLOOKUP(CAPA!$B$12,'POLITICA DE PREÇO'!#REF!,2,0)*0.95,VLOOKUP(CONCATENATE(B17,$G$6),'BASE DE DADOS PREÇOS'!$E:$H,4,0)/(1-SUM($F$1))*VLOOKUP(CAPA!$B$12,'POLITICA DE PREÇO'!$B$4:$F$100,5,0))*CAPA!$B$14,"") -> 11059.92 | H17: =IFERROR(IF('BASE DE DADOS PREÇOS'!$M$71="com",VLOOKUP(CONCATENATE(B17,$H$6),'BASE DE DADOS PREÇOS'!$E:$H,4,0)/(1-SUM($F$1))*VLOOKUP(CAPA!$B$12,'POLITICA DE PREÇO'!#REF!,2,0)*0.95,VLOOKUP(CONCATENATE(B17,$H$6),'BASE DE DADOS PREÇOS'!$E:$H,4,0)/(1-SUM($F$1))*VLOOKUP(CAPA!$B$12,'POLITICA DE PREÇO'!$B$4:$F$100,5,0))*CAPA!$B$14,"") -> 8265.4705 | I17: =IFERROR(IF('BASE DE DADOS PREÇOS'!$M$71="com",VLOOKUP(CONCATENATE(B17,$I$6),'BASE DE DADOS PREÇOS'!$E:$H,4,0)/(1-SUM($F$1))*VLOOKUP(CAPA!$B$12,'POLITICA DE PREÇO'!#REF!,2,0)*0.95,VLOOKUP(CONCATENATE(B17,$I$6),'BASE DE DADOS PREÇOS'!$E:$H,4,0)/(1-SUM($F$1))*VLOOKUP(CAPA!$B$12,'POLITICA DE PREÇO'!$B$4:$F$100,5,0))*CAPA!$B$14,"") -> 20748.126 | J17: =I17*0.9 -> 18673.313
B18: Kona Mesa de Jantar Retangular - 3.0x1.2x0.75 - Acabamentos Customizados | C18: 3 | D18: 1.2 | E18: 0.75 | G18: =IFERROR(IF('BASE DE DADOS PREÇOS'!$M$71="com",VLOOKUP(CONCATENATE(B18,$G$6),'BASE DE DADOS PREÇOS'!$E:$H,4,0)/(1-SUM($F$1))*VLOOKUP(CAPA!$B$12,'POLITICA DE PREÇO'!#REF!,2,0)*0.95,VLOOKUP(CONCATENATE(B18,$G$6),'BASE DE DADOS PREÇOS'!$E:$H,4,0)/(1-SUM($F$1))*VLOOKUP(CAPA!$B$12,'POLITICA DE PREÇO'!$B$4:$F$100,5,0))*CAPA!$B$14,"") -> 12216.26 | H18: =IFERROR(IF('BASE DE DADOS PREÇOS'!$M$71="com",VLOOKUP(CONCATENATE(B18,$H$6),'BASE DE DADOS PREÇOS'!$E:$H,4,0)/(1-SUM($F$1))*VLOOKUP(CAPA!$B$12,'POLITICA DE PREÇO'!#REF!,2,0)*0.95,VLOOKUP(CONCATENATE(B18,$H$6),'BASE DE DADOS PREÇOS'!$E:$H,4,0)/(1-SUM($F$1))*VLOOKUP(CAPA!$B$12,'POLITICA DE PREÇO'!$B$4:$F$100,5,0))*CAPA!$B$14,"") -> 8571.0896 | I18: =IFERROR(IF('BASE DE DADOS PREÇOS'!$M$71="com",VLOOKUP(CONCATENATE(B18,$I$6),'BASE DE DADOS PREÇOS'!$E:$H,4,0)/(1-SUM($F$1))*VLOOKUP(CAPA!$B$12,'POLITICA DE PREÇO'!#REF!,2,0)*0.95,VLOOKUP(CONCATENATE(B18,$I$6),'BASE DE DADOS PREÇOS'!$E:$H,4,0)/(1-SUM($F$1))*VLOOKUP(CAPA!$B$12,'POLITICA DE PREÇO'!$B$4:$F$100,5,0))*CAPA!$B$14,"") -> 22882.071 | J18: =I18*0.9 -> 20593.864
B19: Maria Mesa de Jantar - Øx0.9x0.75 - Acabamentos Customizados | C19: Ø | D19: 0.9 | E19: 0.75 | G19: =IFERROR(IF('BASE DE DADOS PREÇOS'!$M$71="com",VLOOKUP(CONCATENATE(B19,$G$6),'BASE DE DADOS PREÇOS'!$E:$H,4,0)/(1-SUM($F$1))*VLOOKUP(CAPA!$B$12,'POLITICA DE PREÇO'!#REF!,2,0)*0.95,VLOOKUP(CONCATENATE(B19,$G$6),'BASE DE DADOS PREÇOS'!$E:$H,4,0)/(1-SUM($F$1))*VLOOKUP(CAPA!$B$12,'POLITICA DE PREÇO'!$B$4:$F$100,5,0))*CAPA!$B$14,"") -> 4205.7258 | H19: =IFERROR(IF('BASE DE DADOS PREÇOS'!$M$71="com",VLOOKUP(CONCATENATE(B19,$H$6),'BASE DE DADOS PREÇOS'!$E:$H,4,0)/(1-SUM($F$1))*VLOOKUP(CAPA!$B$12,'POLITICA DE PREÇO'!#REF!,2,0)*0.95,VLOOKUP(CONCATENATE(B19,$H$6),'BASE DE DADOS PREÇOS'!$E:$H,4,0)/(1-SUM($F$1))*VLOOKUP(CAPA!$B$12,'POLITICA DE PREÇO'!$B$4:$F$100,5,0))*CAPA!$B$14,"") -> 3347.5138 | I19: =IFERROR(IF('BASE DE DADOS PREÇOS'!$M$71="com",VLOOKUP(CONCATENATE(B19,$I$6),'BASE DE DADOS PREÇOS'!$E:$H,4,0)/(1-SUM($F$1))*VLOOKUP(CAPA!$B$12,'POLITICA DE PREÇO'!#REF!,2,0)*0.95,VLOOKUP(CONCATENATE(B19,$I$6),'BASE DE DADOS PREÇOS'!$E:$H,4,0)/(1-SUM($F$1))*VLOOKUP(CAPA!$B$12,'POLITICA DE PREÇO'!$B$4:$F$100,5,0))*CAPA!$B$14,"") -> 6926.8386 | J19: =I19*0.9 -> 6234.1547
B20: Maria Mesa de Jantar - Øx1x0.75 - Acabamentos Customizados | C20: Ø | D20: 1 | E20: 0.75 | G20: =IFERROR(IF('BASE DE DADOS PREÇOS'!$M$71="com",VLOOKUP(CONCATENATE(B20,$G$6),'BASE DE DADOS PREÇOS'!$E:$H,4,0)/(1-SUM($F$1))*VLOOKUP(CAPA!$B$12,'POLITICA DE PREÇO'!#REF!,2,0)*0.95,VLOOKUP(CONCATENATE(B20,$G$6),'BASE DE DADOS PREÇOS'!$E:$H,4,0)/(1-SUM($F$1))*VLOOKUP(CAPA!$B$12,'POLITICA DE PREÇO'!$B$4:$F$100,5,0))*CAPA!$B$14,"") -> 4883.4832 | H20: =IFERROR(IF('BASE DE DADOS PREÇOS'!$M$71="com",VLOOKUP(CONCATENATE(B20,$H$6),'BASE DE DADOS PREÇOS'!$E:$H,4,0)/(1-SUM($F$1))*VLOOKUP(CAPA!$B$12,'POLITICA DE PREÇO'!#REF!,2,0)*0.95,VLOOKUP(CONCATENATE(B20,$H$6),'BASE DE DADOS PREÇOS'!$E:$H,4,0)/(1-SUM($F$1))*VLOOKUP(CAPA!$B$12,'POLITICA DE PREÇO'!$B$4:$F$100,5,0))*CAPA!$B$14,"") -> 3734.4118 | I20: =IFERROR(IF('BASE DE DADOS PREÇOS'!$M$71="com",VLOOKUP(CONCATENATE(B20,$I$6),'BASE DE DADOS PREÇOS'!$E:$H,4,0)/(1-SUM($F$1))*VLOOKUP(CAPA!$B$12,'POLITICA DE PREÇO'!#REF!,2,0)*0.95,VLOOKUP(CONCATENATE(B20,$I$6),'BASE DE DADOS PREÇOS'!$E:$H,4,0)/(1-SUM($F$1))*VLOOKUP(CAPA!$B$12,'POLITICA DE PREÇO'!$B$4:$F$100,5,0))*CAPA!$B$14,"") -> 9048.8757 | J20: =I20*0.9 -> 8143.9882
B21: Maria Mesa de Jantar - Øx1.2x0.75 - Acabamentos Customizados | C21: Ø | D21: 1.2 | E21: 0.75 | G21: =IFERROR(IF('BASE DE DADOS PREÇOS'!$M$71="com",VLOOKUP(CONCATENATE(B21,$G$6),'BASE DE DADOS PREÇOS'!$E:$H,4,0)/(1-SUM($F$1))*VLOOKUP(CAPA!$B$12,'POLITICA DE PREÇO'!#REF!,2,0)*0.95,VLOOKUP(CONCATENATE(B21,$G$6),'BASE DE DADOS PREÇOS'!$E:$H,4,0)/(1-SUM($F$1))*VLOOKUP(CAPA!$B$12,'POLITICA DE PREÇO'!$B$4:$F$100,5,0))*CAPA!$B$14,"") -> 5737.9055 | H21: =IFERROR(IF('BASE DE DADOS PREÇOS'!$M$71="com",VLOOKUP(CONCATENATE(B21,$H$6),'BASE DE DADOS PREÇOS'!$E:$H,4,0)/(1-SUM($F$1))*VLOOKUP(CAPA!$B$12,'POLITICA DE PREÇO'!#REF!,2,0)*0.95,VLOOKUP(CONCATENATE(B21,$H$6),'BASE DE DADOS PREÇOS'!$E:$H,4,0)/(1-SUM($F$1))*VLOOKUP(CAPA!$B$12,'POLITICA DE PREÇO'!$B$4:$F$100,5,0))*CAPA!$B$14,"") -> 3921.6006 | I21: =IFERROR(IF('BASE DE DADOS PREÇOS'!$M$71="com",VLOOKUP(CONCATENATE(B21,$I$6),'BASE DE DADOS PREÇOS'!$E:$H,4,0)/(1-SUM($F$1))*VLOOKUP(CAPA!$B$12,'POLITICA DE PREÇO'!#REF!,2,0)*0.95,VLOOKUP(CONCATENATE(B21,$I$6),'BASE DE DADOS PREÇOS'!$E:$H,4,0)/(1-SUM($F$1))*VLOOKUP(CAPA!$B$12,'POLITICA DE PREÇO'!$B$4:$F$100,5,0))*CAPA!$B$14,"") -> 11098.665 | J21: =I21*0.9 -> 9988.7987
B22: Maria Mesa de Jantar - Øx1.3x0.75 - Acabamentos Customizados | C22: Ø | D22: 1.3 | E22: 0.75 | G22: =IFERROR(IF('BASE DE DADOS PREÇOS'!$M$71="com",VLOOKUP(CONCATENATE(B22,$G$6),'BASE DE DADOS PREÇOS'!$E:$H,4,0)/(1-SUM($F$1))*VLOOKUP(CAPA!$B$12,'POLITICA DE PREÇO'!#REF!,2,0)*0.95,VLOOKUP(CONCATENATE(B22,$G$6),'BASE DE DADOS PREÇOS'!$E:$H,4,0)/(1-SUM($F$1))*VLOOKUP(CAPA!$B$12,'POLITICA DE PREÇO'!$B$4:$F$100,5,0))*CAPA!$B$14,"") -> 6017.3333 | H22: =IFERROR(IF('BASE DE DADOS PREÇOS'!$M$71="com",VLOOKUP(CONCATENATE(B22,$H$6),'BASE DE DADOS PREÇOS'!$E:$H,4,0)/(1-SUM($F$1))*VLOOKUP(CAPA!$B$12,'POLITICA DE PREÇO'!#REF!,2,0)*0.95,VLOOKUP(CONCATENATE(B22,$H$6),'BASE DE DADOS PREÇOS'!$E:$H,4,0)/(1-SUM($F$1))*VLOOKUP(CAPA!$B$12,'POLITICA DE PREÇO'!$B$4:$F$100,5,0))*CAPA!$B$14,"") -> 3958.737 | I22: =IFERROR(IF('BASE DE DADOS PREÇOS'!$M$71="com",VLOOKUP(CONCATENATE(B22,$I$6),'BASE DE DADOS PREÇOS'!$E:$H,4,0)/(1-SUM($F$1))*VLOOKUP(CAPA!$B$12,'POLITICA DE PREÇO'!#REF!,2,0)*0.95,VLOOKUP(CONCATENATE(B22,$I$6),'BASE DE DADOS PREÇOS'!$E:$H,4,0)/(1-SUM($F$1))*VLOOKUP(CAPA!$B$12,'POLITICA DE PREÇO'!$B$4:$F$100,5,0))*CAPA!$B$14,"") -> 12156.745 | J22: =I22*0.9 -> 10941.071
B23: Maria Mesa de Jantar - Øx1.5x0.75 - Acabamentos Customizados | C23: Ø | D23: 1.5 | E23: 0.75 | G23: =IFERROR(IF('BASE DE DADOS PREÇOS'!$M$71="com",VLOOKUP(CONCATENATE(B23,$G$6),'BASE DE DADOS PREÇOS'!$E:$H,4,0)/(1-SUM($F$1))*VLOOKUP(CAPA!$B$12,'POLITICA DE PREÇO'!#REF!,2,0)*0.95,VLOOKUP(CONCATENATE(B23,$G$6),'BASE DE DADOS PREÇOS'!$E:$H,4,0)/(1-SUM($F$1))*VLOOKUP(CAPA!$B$12,'POLITICA DE PREÇO'!$B$4:$F$100,5,0))*CAPA!$B$14,"") -> 6830.2206 | H23: =IFERROR(IF('BASE DE DADOS PREÇOS'!$M$71="com",VLOOKUP(CONCATENATE(B23,$H$6),'BASE DE DADOS PREÇOS'!$E:$H,4,0)/(1-SUM($F$1))*VLOOKUP(CAPA!$B$12,'POLITICA DE PREÇO'!#REF!,2,0)*0.95,VLOOKUP(CONCATENATE(B23,$H$6),'BASE DE DADOS PREÇOS'!$E:$H,4,0)/(1-SUM($F$1))*VLOOKUP(CAPA!$B$12,'POLITICA DE PREÇO'!$B$4:$F$100,5,0))*CAPA!$B$14,"") -> 4347.2708 | I23: =IFERROR(IF('BASE DE DADOS PREÇOS'!$M$71="com",VLOOKUP(CONCATENATE(B23,$I$6),'BASE DE DADOS PREÇOS'!$E:$H,4,0)/(1-SUM($F$1))*VLOOKUP(CAPA!$B$12,'POLITICA DE PREÇO'!#REF!,2,0)*0.95,VLOOKUP(CONCATENATE(B23,$I$6),'BASE DE DADOS PREÇOS'!$E:$H,4,0)/(1-SUM($F$1))*VLOOKUP(CAPA!$B$12,'POLITICA DE PREÇO'!$B$4:$F$100,5,0))*CAPA!$B$14,"") -> 14616.931 | J23: =I23*0.9 -> 13155.237
B24: Maria Mesa de Jantar - Øx1.6x0.75 - Acabamentos Customizados | C24: Ø | D24: 1.6 | E24: 0.75 | G24: =IFERROR(IF('BASE DE DADOS PREÇOS'!$M$71="com",VLOOKUP(CONCATENATE(B24,$G$6),'BASE DE DADOS PREÇOS'!$E:$H,4,0)/(1-SUM($F$1))*VLOOKUP(CAPA!$B$12,'POLITICA DE PREÇO'!#REF!,2,0)*0.95,VLOOKUP(CONCATENATE(B24,$G$6),'BASE DE DADOS PREÇOS'!$E:$H,4,0)/(1-SUM($F$1))*VLOOKUP(CAPA!$B$12,'POLITICA DE PREÇO'!$B$4:$F$100,5,0))*CAPA!$B$14,"") -> 7131.9937 | H24: =IFERROR(IF('BASE DE DADOS PREÇOS'!$M$71="com",VLOOKUP(CONCATENATE(B24,$H$6),'BASE DE DADOS PREÇOS'!$E:$H,4,0)/(1-SUM($F$1))*VLOOKUP(CAPA!$B$12,'POLITICA DE PREÇO'!#REF!,2,0)*0.95,VLOOKUP(CONCATENATE(B24,$H$6),'BASE DE DADOS PREÇOS'!$E:$H,4,0)/(1-SUM($F$1))*VLOOKUP(CAPA!$B$12,'POLITICA DE PREÇO'!$B$4:$F$100,5,0))*CAPA!$B$14,"") -> 4563.4407 | I24: =IFERROR(IF('BASE DE DADOS PREÇOS'!$M$71="com",VLOOKUP(CONCATENATE(B24,$I$6),'BASE DE DADOS PREÇOS'!$E:$H,4,0)/(1-SUM($F$1))*VLOOKUP(CAPA!$B$12,'POLITICA DE PREÇO'!#REF!,2,0)*0.95,VLOOKUP(CONCATENATE(B24,$I$6),'BASE DE DADOS PREÇOS'!$E:$H,4,0)/(1-SUM($F$1))*VLOOKUP(CAPA!$B$12,'POLITICA DE PREÇO'!$B$4:$F$100,5,0))*CAPA!$B$14,"") -> 15307.894 | J24: =I24*0.9 -> 13777.105
B25: Maria Mesa de Jantar - Øx1.8x0.75 - Acabamentos Customizados | C25: Ø | D25: 1.8 | E25: 0.75 | G25: =IFERROR(IF('BASE DE DADOS PREÇOS'!$M$71="com",VLOOKUP(CONCATENATE(B25,$G$6),'BASE DE DADOS PREÇOS'!$E:$H,4,0)/(1-SUM($F$1))*VLOOKUP(CAPA!$B$12,'POLITICA DE PREÇO'!#REF!,2,0)*0.95,VLOOKUP(CONCATENATE(B25,$G$6),'BASE DE DADOS PREÇOS'!$E:$H,4,0)/(1-SUM($F$1))*VLOOKUP(CAPA!$B$12,'POLITICA DE PREÇO'!$B$4:$F$100,5,0))*CAPA!$B$14,"") -> 8001.0031 | H25: =IFERROR(IF('BASE DE DADOS PREÇOS'!$M$71="com",VLOOKUP(CONCATENATE(B25,$H$6),'BASE DE DADOS PREÇOS'!$E:$H,4,0)/(1-SUM($F$1))*VLOOKUP(CAPA!$B$12,'POLITICA DE PREÇO'!#REF!,2,0)*0.95,VLOOKUP(CONCATENATE(B25,$H$6),'BASE DE DADOS PREÇOS'!$E:$H,4,0)/(1-SUM($F$1))*VLOOKUP(CAPA!$B$12,'POLITICA DE PREÇO'!$B$4:$F$100,5,0))*CAPA!$B$14,"") -> 5016.1386 | I25: =IFERROR(IF('BASE DE DADOS PREÇOS'!$M$71="com",VLOOKUP(CONCATENATE(B25,$I$6),'BASE DE DADOS PREÇOS'!$E:$H,4,0)/(1-SUM($F$1))*VLOOKUP(CAPA!$B$12,'POLITICA DE PREÇO'!#REF!,2,0)*0.95,VLOOKUP(CONCATENATE(B25,$I$6),'BASE DE DADOS PREÇOS'!$E:$H,4,0)/(1-SUM($F$1))*VLOOKUP(CAPA!$B$12,'POLITICA DE PREÇO'!$B$4:$F$100,5,0))*CAPA!$B$14,"") -> 18815.311 | J25: =I25*0.9 -> 16933.78
B26: Pebble Mesa de Jantar - Øx1.5x0.75 - Acabamentos Customizados | C26: Ø | D26: 1.5 | E26: 0.75 | G26: =IFERROR(IF('BASE DE DADOS PREÇOS'!$M$71="com",VLOOKUP(CONCATENATE(B26,$G$6),'BASE DE DADOS PREÇOS'!$E:$H,4,0)/(1-SUM($F$1))*VLOOKUP(CAPA!$B$12,'POLITICA DE PREÇO'!#REF!,2,0)*0.95,VLOOKUP(CONCATENATE(B26,$G$6),'BASE DE DADOS PREÇOS'!$E:$H,4,0)/(1-SUM($F$1))*VLOOKUP(CAPA!$B$12,'POLITICA DE PREÇO'!$B$4:$F$100,5,0))*CAPA!$B$14,"") -> 12438.822 | H26: =IFERROR(IF('BASE DE DADOS PREÇOS'!$M$71="com",VLOOKUP(CONCATENATE(B26,$H$6),'BASE DE DADOS PREÇOS'!$E:$H,4,0)/(1-SUM($F$1))*VLOOKUP(CAPA!$B$12,'POLITICA DE PREÇO'!#REF!,2,0)*0.95,VLOOKUP(CONCATENATE(B26,$H$6),'BASE DE DADOS PREÇOS'!$E:$H,4,0)/(1-SUM($F$1))*VLOOKUP(CAPA!$B$12,'POLITICA DE PREÇO'!$B$4:$F$100,5,0))*CAPA!$B$14,"") -> 9489.6548 | I26: =IFERROR(IF('BASE DE DADOS PREÇOS'!$M$71="com",VLOOKUP(CONCATENATE(B26,$I$6),'BASE DE DADOS PREÇOS'!$E:$H,4,0)/(1-SUM($F$1))*VLOOKUP(CAPA!$B$12,'POLITICA DE PREÇO'!#REF!,2,0)*0.95,VLOOKUP(CONCATENATE(B26,$I$6),'BASE DE DADOS PREÇOS'!$E:$H,4,0)/(1-SUM($F$1))*VLOOKUP(CAPA!$B$12,'POLITICA DE PREÇO'!$B$4:$F$100,5,0))*CAPA!$B$14,"") -> 21920.284 | J26: =I26*0.9 -> 19728.255
B27: Pebble Mesa de Jantar - Øx1.6x0.75 - Acabamentos Customizados | C27: Ø | D27: 1.6 | E27: 0.75 | G27: =IFERROR(IF('BASE DE DADOS PREÇOS'!$M$71="com",VLOOKUP(CONCATENATE(B27,$G$6),'BASE DE DADOS PREÇOS'!$E:$H,4,0)/(1-SUM($F$1))*VLOOKUP(CAPA!$B$12,'POLITICA DE PREÇO'!#REF!,2,0)*0.95,VLOOKUP(CONCATENATE(B27,$G$6),'BASE DE DADOS PREÇOS'!$E:$H,4,0)/(1-SUM($F$1))*VLOOKUP(CAPA!$B$12,'POLITICA DE PREÇO'!$B$4:$F$100,5,0))*CAPA!$B$14,"") -> 12982.813 | H27: =IFERROR(IF('BASE DE DADOS PREÇOS'!$M$71="com",VLOOKUP(CONCATENATE(B27,$H$6),'BASE DE DADOS PREÇOS'!$E:$H,4,0)/(1-SUM($F$1))*VLOOKUP(CAPA!$B$12,'POLITICA DE PREÇO'!#REF!,2,0)*0.95,VLOOKUP(CONCATENATE(B27,$H$6),'BASE DE DADOS PREÇOS'!$E:$H,4,0)/(1-SUM($F$1))*VLOOKUP(CAPA!$B$12,'POLITICA DE PREÇO'!$B$4:$F$100,5,0))*CAPA!$B$14,"") -> 10738.746 | I27: =IFERROR(IF('BASE DE DADOS PREÇOS'!$M$71="com",VLOOKUP(CONCATENATE(B27,$I$6),'BASE DE DADOS PREÇOS'!$E:$H,4,0)/(1-SUM($F$1))*VLOOKUP(CAPA!$B$12,'POLITICA DE PREÇO'!#REF!,2,0)*0.95,VLOOKUP(CONCATENATE(B27,$I$6),'BASE DE DADOS PREÇOS'!$E:$H,4,0)/(1-SUM($F$1))*VLOOKUP(CAPA!$B$12,'POLITICA DE PREÇO'!$B$4:$F$100,5,0))*CAPA!$B$14,"") -> 21990.428 | J27: =I27*0.9 -> 19791.386
B28: Pebble Mesa de Jantar - Øx1.8x0.75 - Acabamentos Customizados | C28: Ø | D28: 1.8 | E28: 0.75 | G28: =IFERROR(IF('BASE DE DADOS PREÇOS'!$M$71="com",VLOOKUP(CONCATENATE(B28,$G$6),'BASE DE DADOS PREÇOS'!$E:$H,4,0)/(1-SUM($F$1))*VLOOKUP(CAPA!$B$12,'POLITICA DE PREÇO'!#REF!,2,0)*0.95,VLOOKUP(CONCATENATE(B28,$G$6),'BASE DE DADOS PREÇOS'!$E:$H,4,0)/(1-SUM($F$1))*VLOOKUP(CAPA!$B$12,'POLITICA DE PREÇO'!$B$4:$F$100,5,0))*CAPA!$B$14,"") -> 15020.61 | H28: =IFERROR(IF('BASE DE DADOS PREÇOS'!$M$71="com",VLOOKUP(CONCATENATE(B28,$H$6),'BASE DE DADOS PREÇOS'!$E:$H,4,0)/(1-SUM($F$1))*VLOOKUP(CAPA!$B$12,'POLITICA DE PREÇO'!#REF!,2,0)*0.95,VLOOKUP(CONCATENATE(B28,$H$6),'BASE DE DADOS PREÇOS'!$E:$H,4,0)/(1-SUM($F$1))*VLOOKUP(CAPA!$B$12,'POLITICA DE PREÇO'!$B$4:$F$100,5,0))*CAPA!$B$14,"") -> 11359.041 | I28: =IFERROR(IF('BASE DE DADOS PREÇOS'!$M$71="com",VLOOKUP(CONCATENATE(B28,$I$6),'BASE DE DADOS PREÇOS'!$E:$H,4,0)/(1-SUM($F$1))*VLOOKUP(CAPA!$B$12,'POLITICA DE PREÇO'!#REF!,2,0)*0.95,VLOOKUP(CONCATENATE(B28,$I$6),'BASE DE DADOS PREÇOS'!$E:$H,4,0)/(1-SUM($F$1))*VLOOKUP(CAPA!$B$12,'POLITICA DE PREÇO'!$B$4:$F$100,5,0))*CAPA!$B$14,"") -> 24699.449 | J28: =I28*0.9 -> 22229.504
B29: Pebble Mesa de Jantar - Øx2.0x0.75 - Acabamentos Customizados | C29: Ø | D29: 2 | E29: 0.75 | G29: =IFERROR(IF('BASE DE DADOS PREÇOS'!$M$71="com",VLOOKUP(CONCATENATE(B29,$G$6),'BASE DE DADOS PREÇOS'!$E:$H,4,0)/(1-SUM($F$1))*VLOOKUP(CAPA!$B$12,'POLITICA DE PREÇO'!#REF!,2,0)*0.95,VLOOKUP(CONCATENATE(B29,$G$6),'BASE DE DADOS PREÇOS'!$E:$H,4,0)/(1-SUM($F$1))*VLOOKUP(CAPA!$B$12,'POLITICA DE PREÇO'!$B$4:$F$100,5,0))*CAPA!$B$14,"") -> 16525.755 | H29: =IFERROR(IF('BASE DE DADOS PREÇOS'!$M$71="com",VLOOKUP(CONCATENATE(B29,$H$6),'BASE DE DADOS PREÇOS'!$E:$H,4,0)/(1-SUM($F$1))*VLOOKUP(CAPA!$B$12,'POLITICA DE PREÇO'!#REF!,2,0)*0.95,VLOOKUP(CONCATENATE(B29,$H$6),'BASE DE DADOS PREÇOS'!$E:$H,4,0)/(1-SUM($F$1))*VLOOKUP(CAPA!$B$12,'POLITICA DE PREÇO'!$B$4:$F$100,5,0))*CAPA!$B$14,"") -> 11923.267 | I29: =IFERROR(IF('BASE DE DADOS PREÇOS'!$M$71="com",VLOOKUP(CONCATENATE(B29,$I$6),'BASE DE DADOS PREÇOS'!$E:$H,4,0)/(1-SUM($F$1))*VLOOKUP(CAPA!$B$12,'POLITICA DE PREÇO'!#REF!,2,0)*0.95,VLOOKUP(CONCATENATE(B29,$I$6),'BASE DE DADOS PREÇOS'!$E:$H,4,0)/(1-SUM($F$1))*VLOOKUP(CAPA!$B$12,'POLITICA DE PREÇO'!$B$4:$F$100,5,0))*CAPA!$B$14,"") -> 29413.485 | J29: =I29*0.9 -> 26472.136
B30: Picasso Mesa de Jantar Organica - 2.2x1.4x0.75 - Acabamentos Customizados | C30: 2.2 | D30: 1.4 | E30: 0.75 | G30: =IFERROR(IF('BASE DE DADOS PREÇOS'!$M$71="com",VLOOKUP(CONCATENATE(B30,$G$6),'BASE DE DADOS PREÇOS'!$E:$H,4,0)/(1-SUM($F$1))*VLOOKUP(CAPA!$B$12,'POLITICA DE PREÇO'!#REF!,2,0)*0.95,VLOOKUP(CONCATENATE(B30,$G$6),'BASE DE DADOS PREÇOS'!$E:$H,4,0)/(1-SUM($F$1))*VLOOKUP(CAPA!$B$12,'POLITICA DE PREÇO'!$B$4:$F$100,5,0))*CAPA!$B$14,"") -> 8701.571 | H30: =IFERROR(IF('BASE DE DADOS PREÇOS'!$M$71="com",VLOOKUP(CONCATENATE(B30,$H$6),'BASE DE DADOS PREÇOS'!$E:$H,4,0)/(1-SUM($F$1))*VLOOKUP(CAPA!$B$12,'POLITICA DE PREÇO'!#REF!,2,0)*0.95,VLOOKUP(CONCATENATE(B30,$H$6),'BASE DE DADOS PREÇOS'!$E:$H,4,0)/(1-SUM($F$1))*VLOOKUP(CAPA!$B$12,'POLITICA DE PREÇO'!$B$4:$F$100,5,0))*CAPA!$B$14,"") -> 5926.8653 | I30: =IFERROR(IF('BASE DE DADOS PREÇOS'!$M$71="com",VLOOKUP(CONCATENATE(B30,$I$6),'BASE DE DADOS PREÇOS'!$E:$H,4,0)/(1-SUM($F$1))*VLOOKUP(CAPA!$B$12,'POLITICA DE PREÇO'!#REF!,2,0)*0.95,VLOOKUP(CONCATENATE(B30,$I$6),'BASE DE DADOS PREÇOS'!$E:$H,4,0)/(1-SUM($F$1))*VLOOKUP(CAPA!$B$12,'POLITICA DE PREÇO'!$B$4:$F$100,5,0))*CAPA!$B$14,"") -> 13959.263 | J30: =I30*0.9 -> 12563.337
B31: Picasso Mesa de Jantar Organica - 2.4x1.4x0.75 - Acabamentos Customizados | C31: 2.4 | D31: 1.4 | E31: 0.75 | G31: =IFERROR(IF('BASE DE DADOS PREÇOS'!$M$71="com",VLOOKUP(CONCATENATE(B31,$G$6),'BASE DE DADOS PREÇOS'!$E:$H,4,0)/(1-SUM($F$1))*VLOOKUP(CAPA!$B$12,'POLITICA DE PREÇO'!#REF!,2,0)*0.95,VLOOKUP(CONCATENATE(B31,$G$6),'BASE DE DADOS PREÇOS'!$E:$H,4,0)/(1-SUM($F$1))*VLOOKUP(CAPA!$B$12,'POLITICA DE PREÇO'!$B$4:$F$100,5,0))*CAPA!$B$14,"") -> 11232.596 | H31: =IFERROR(IF('BASE DE DADOS PREÇOS'!$M$71="com",VLOOKUP(CONCATENATE(B31,$H$6),'BASE DE DADOS PREÇOS'!$E:$H,4,0)/(1-SUM($F$1))*VLOOKUP(CAPA!$B$12,'POLITICA DE PREÇO'!#REF!,2,0)*0.95,VLOOKUP(CONCATENATE(B31,$H$6),'BASE DE DADOS PREÇOS'!$E:$H,4,0)/(1-SUM($F$1))*VLOOKUP(CAPA!$B$12,'POLITICA DE PREÇO'!$B$4:$F$100,5,0))*CAPA!$B$14,"") -> 8178.615 | I31: =IFERROR(IF('BASE DE DADOS PREÇOS'!$M$71="com",VLOOKUP(CONCATENATE(B31,$I$6),'BASE DE DADOS PREÇOS'!$E:$H,4,0)/(1-SUM($F$1))*VLOOKUP(CAPA!$B$12,'POLITICA DE PREÇO'!#REF!,2,0)*0.95,VLOOKUP(CONCATENATE(B31,$I$6),'BASE DE DADOS PREÇOS'!$E:$H,4,0)/(1-SUM($F$1))*VLOOKUP(CAPA!$B$12,'POLITICA DE PREÇO'!$B$4:$F$100,5,0))*CAPA!$B$14,"") -> 20758.594 | J31: =I31*0.9 -> 18682.735
